Workbook

Sheet Summary
B1: Operation Uptime — model summary (hypothetical Tesla Giga Berlin maintenance hiring)
B2: Everything on this tab is a live link to the model. Inputs live only on the Assumptions tab (blue on yellow).
B4: Target: signed contracts by 31 Dec | C4: =Funnel!B9 -> 100
B5: Recommended budget | C5: =Budget!C12 -> 122500
B6: …of which planned spend | C6: =Budget!C9 -> 102255.85
B7: …of which reserve (incl. rounding up) | C7: =Budget!C12-Budget!C9 -> 20244.152
B8: Hires the channel plan buys | C8: =Budget!C13 -> 100
B9: ="Hires actually possible (≤ "&Assumptions!$D$9&" assessments/week)" -> Hires actually possible (≤ 55 assessments/week) | C9: =MIN(Budget!C13,Funnel!B26) -> 100
B10: Media cost per hire | C10: =Budget!C14 -> 1022.5585
B11: Qualified applicants to assess | C11: =Funnel!B23 -> 307.97308
B12: Assessment slots available (capacity × weeks) | C12: =Funnel!B22 -> 314.28571
B13: Slot utilisation | C13: =Funnel!B24 -> 0.97991433
B14: Last useful application date (E/M/A) | C14: =Funnel!B19 -> 46350
B15: Last useful application date (Supervisors) | C15: =Funnel!B20 -> 46343
B16: Hardest role (dearest last hire we must buy; reasons on Funnel row 35) | C16: =IF(MAX(Funnel!H30:H33)<=0,"–",INDEX(Funnel!A30:A33,MATCH(MAX(Funnel!H30:H33),Funnel!H30:H33,0))&" (last hire costs €"&TEXT(MAX(Funnel!H30:H33),"#,##0")&")") -> Electricians (last hire costs €2,272)
B17: Most sensitive assumption | C17: =Funnel!D49 -> Qualified → signed (assessment pass rate) ×0.7
B18: Hires with 30% less budget | C18: =Budget!H46 -> 87.057806
B19: Input checks | C19: =IF(((Assumptions!$D$10<0)+(Assumptions!$D$10>1)+(Assumptions!$D$52<0)+(Assumptions!$D$52>1)+(Assumptions!$D$50<0)+(Assumptions!$D$50>1)+(Assumptions!$D$64<0)+(Assumptions!$D$64>1)+(Assumptions!$D$157<0)+(Assumptions!$D$157>1)+(Assumptions!$D$158<0)+(Assumptions!$D$158>1)+(Assumptions!$D$163<0)+(Assumptions!$D$163>1)+(Assumptions!$D$168<0)+(Assumptions!$D$168>1)+(Assumptions!$D$170<0)+(Assumptions!$D$170>1)+(Assumptions!$D$174<0)+(Assumptions!$D$174>1)+(Assumptions!$D$93<0)+(Assumptions!$D$93>1)+(Assumptions!$D$94<0)+(Assumptions!$D$94>1)+(Assumptions!$D$95<0)+(Assumptions!$D$95>1)+(Assumptions!$D$89<0)+(Assumptions!$D$89>1)+(Assumptions!$D$91<0)+(Assumptions!$D$91>1)+(Assumptions!$D$29<0)+(Assumptions!$D$29>1)+(Assumptions!$D$30<0)+(Assumptions!$D$30>1)+(Assumptions!$D$31<0)+(Assumptions!$D$31>1)+(Assumptions!$D$32<0)+(Assumptions!$D$32>1)+(Assumptions!$D$33<0)+(Assumptions!$D$33>1)+(Assumptions!$D$34<0)+(Assumptions!$D$34>1)+(Assumptions!$D$35<0)+(Assumptions!$D$35>1)+(Assumptions!$D$36<0)+(Assumptions!$D$36>1)+(Assumptions!$D$37<0)+(Assumptions!$D$37>1)+(Assumptions!$D$38<0)+(Assumptions!$D$38>1)+(Assumptions!$D$39<0)+(Assumptions!$D$39>1)+(Assumptions!$D$40<0)+(Assumptions!$D$40>1)+(Assumptions!$D$41<0)+(Assumptions!$D$41>1)+(Assumptions!$D$42<0)+(Assumptions!$D$42>1)+(Assumptions!$D$43<0)+(Assumptions!$D$43>1)+(Assumptions!$D$44<0)+(Assumptions!$D$44>1)+(Assumptions!$D$53<0)+(Assumptions!$D$53>1)+(Assumptions!$D$54<0)+(Assumptions!$D$54>1)+(Assumptions!$D$55<0)+(Assumptions!$D$55>1)+(Assumptions!$D$56<0)+(Assumptions!$D$56>1)+(Assumptions!$D$57<0)+(Assumptions!$D$57>1)+(Assumptions!$D$58<0)+(Assumptions!$D$58>1)+(Assumptions!$D$59<0)+(Assumptions!$D$59>1)+(Assumptions!$D$60<0)+(Assumptions!$D$60>1)+(Assumptions!$D$61<0)+(Assumptions!$D$61>1)+(Assumptions!$D$62<0)+(Assumptions!$D$62>1)+(Assumptions!$D$63<0)+(Assumptions!$D$63>1)+(Assumptions!$D$72<0)+(Assumptions!$D$72>1)+(Assumptions!$D$73<0)+(Assumptions!$D$73>1)+(Assumptions!$D$74<0)+(Assumptions!$D$74>1)+(Assumptions!$D$75<0)+(Assumptions!$D$75>1)+(Assumptions!$D$96<0)+(Assumptions!$D$96>1)+(Assumptions!$D$99<0)+(Assumptions!$D$99>1)+(Assumptions!$D$100<0)+(Assumptions!$D$100>1)+(Assumptions!$D$101<0)+(Assumptions!$D$101>1)+(Assumptions!$D$102<0)+(Assumptions!$D$102>1)+(Assumptions!$D$108<0)+(Assumptions!$D$108>1)+(Assumptions!$D$109<0)+(Assumptions!$D$109>1)+(Assumptions!$D$110<0)+(Assumptions!$D$110>1)+(Assumptions!$D$111<0)+(Assumptions!$D$111>1)+(Assumptions!$D$112<0)+(Assumptions!$D$112>1)+(Assumptions!$D$113<0)+(Assumptions!$D$113>1)+(Assumptions!$D$115<0)+(Assumptions!$D$115>1)+(Assumptions!$D$121<0)+(Assumptions!$D$121>1)+(Assumptions!$D$122<0)+(Assumptions!$D$122>1)+(Assumptions!$D$123<0)+(Assumptions!$D$123>1))+((Assumptions!$D$9<0)+(Assumptions!$D$11<0)+(Assumptions!$D$12<0)+(Assumptions!$D$13<0)+(Assumptions!$D$14<0)+(Assumptions!$D$15<0)+(Assumptions!$D$19<0)+(Assumptions!$D$21<0)+(Assumptions!$D$22<0)+(Assumptions!$D$23<0)+(Assumptions!$D$24<0)+(Assumptions!$D$25<0)+(Assumptions!$D$49<0)+(Assumptions!$D$51<0)+(Assumptions!$D$68<0)+(Assumptions!$D$69<0)+(Assumptions!$D$70<0)+(Assumptions!$D$71<0)+(Assumptions!$D$76<0)+(Assumptions!$D$77<0)+(Assumptions!$D$78<0)+(Assumptions!$D$79<0)+(Assumptions!$D$83<0)+(Assumptions!$D$84<0)+(Assumptions!$D$85<0)+(Assumptions!$D$86<0)+(Assumptions!$D$87<0)+(Assumptions!$D$88<0)+(Assumptions!$D$90<0)+(Assumptions!$D$92<0)+(Assumptions!$D$97<0)+(Assumptions!$D$98<0)+(Assumptions!$D$103<0)+(Assumptions!$D$114<0)+(Assumptions!$D$116<0)+(Assumptions!$D$117<0)+(Assumptions!$D$118<0)+(Assumptions!$D$119<0)+(Assumptions!$D$120<0)+(Assumptions!$D$124<0)+(Assumptions!$D$125<0)+(Assumptions!$D$126<0)+(Assumptions!$D$153<0)+(Assumptions!$D$154<0)+(Assumptions!$D$155<0)+(Assumptions!$D$156<0)+(Assumptions!$D$159<0)+(Assumptions!$D$160<0)+(Assumptions!$D$161<0)+(Assumptions!$D$162<0)+(Assumptions!$D$164<0)+(Assumptions!$D$165<0)+(Assumptions!$D$166<0)+(Assumptions!$D$167<0)+(Assumptions!$D$169<0)+(Assumptions!$D$171<0)+(Assumptions!$D$172<0)+(Assumptions!$D$173<0)+(Assumptions!$D$175<0)+(Assumptions!$D$176<0)+(Assumptions!$D$177<0)+(Assumptions!$D$178<0)+(Assumptions!$D$179<0)+(Assumptions!$D$180<0)+(Assumptions!$D$181<0)+(Assumptions!$D$182<0))+((INT(Assumptions!$D$19)<>Assumptions!$D$19)+(INT(Assumptions!$D$21)<>Assumptions!$D$21)+(INT(Assumptions!$D$22)<>Assumptions!$D$22)+(INT(Assumptions!$D$23)<>Assumptions!$D$23)+(INT(Assumptions!$D$24)<>Assumptions!$D$24)+(INT(Assumptions!$D$25)<>Assumptions!$D$25))+SUMPRODUCT((Assumptions!$E$130:$E$149<0)+(Assumptions!$G$130:$G$149<0)+(Assumptions!$G$130:$G$149>1)+(Assumptions!$H$130:$H$149<0)+(Assumptions!$I$130:$I$149<0)+(Assumptions!$J$130:$J$149<0)+(Assumptions!$F$130:$F$149<0)+((Assumptions!$D$130:$D$149="CPC")*(Assumptions!$F$130:$F$149>1)))+(Assumptions!$D$48<0)+(Assumptions!$D$48>=1)+(Assumptions!$D$20<Assumptions!$D$7)+(Assumptions!$D$20>Assumptions!$D$8)+(Assumptions!$D$8<=Assumptions!$D$7)+(Assumptions!$D$91>=Assumptions!$D$89)+(Assumptions!$D$92<Assumptions!$D$90)=0,"✓ all inputs valid","✗ invalid input: "&IF(((Assumptions!$D$10<0)+(Assumptions!$D$10>1)+(Assumptions!$D$52<0)+(Assumptions!$D$52>1)+(Assumptions!$D$50<0)+(Assumptions!$D$50>1)+(Assumptions!$D$64<0)+(Assumptions!$D$64>1)+(Assumptions!$D$157<0)+(Assumptions!$D$157>1)+(Assumptions!$D$158<0)+(Assumptions!$D$158>1)+(Assumptions!$D$163<0)+(Assumptions!$D$163>1)+(Assumptions!$D$168<0)+(Assumptions!$D$168>1)+(Assumptions!$D$170<0)+(Assumptions!$D$170>1)+(Assumptions!$D$174<0)+(Assumptions!$D$174>1)+(Assumptions!$D$93<0)+(Assumptions!$D$93>1)+(Assumptions!$D$94<0)+(Assumptions!$D$94>1)+(Assumptions!$D$95<0)+(Assumptions!$D$95>1)+(Assumptions!$D$89<0)+(Assumptions!$D$89>1)+(Assumptions!$D$91<0)+(Assumptions!$D$91>1)+(Assumptions!$D$29<0)+(Assumptions!$D$29>1)+(Assumptions!$D$30<0)+(Assumptions!$D$30>1)+(Assumptions!$D$31<0)+(Assumptions!$D$31>1)+(Assumptions!$D$32<0)+(Assumptions!$D$32>1)+(Assumptions!$D$33<0)+(Assumptions!$D$33>1)+(Assumptions!$D$34<0)+(Assumptions!$D$34>1)+(Assumptions!$D$35<0)+(Assumptions!$D$35>1)+(Assumptions!$D$36<0)+(Assumptions!$D$36>1)+(Assumptions!$D$37<0)+(Assumptions!$D$37>1)+(Assumptions!$D$38<0)+(Assumptions!$D$38>1)+(Assumptions!$D$39<0)+(Assumptions!$D$39>1)+(Assumptions!$D$40<0)+(Assumptions!$D$40>1)+(Assumptions!$D$41<0)+(Assumptions!$D$41>1)+(Assumptions!$D$42<0)+(Assumptions!$D$42>1)+(Assumptions!$D$43<0)+(Assumptions!$D$43>1)+(Assumptions!$D$44<0)+(Assumptions!$D$44>1)+(Assumptions!$D$53<0)+(Assumptions!$D$53>1)+(Assumptions!$D$54<0)+(Assumptions!$D$54>1)+(Assumptions!$D$55<0)+(Assumptions!$D$55>1)+(Assumptions!$D$56<0)+(Assumptions!$D$56>1)+(Assumptions!$D$57<0)+(Assumptions!$D$57>1)+(Assumptions!$D$58<0)+(Assumptions!$D$58>1)+(Assumptions!$D$59<0)+(Assumptions!$D$59>1)+(Assumptions!$D$60<0)+(Assumptions!$D$60>1)+(Assumptions!$D$61<0)+(Assumptions!$D$61>1)+(Assumptions!$D$62<0)+(Assumptions!$D$62>1)+(Assumptions!$D$63<0)+(Assumptions!$D$63>1)+(Assumptions!$D$72<0)+(Assumptions!$D$72>1)+(Assumptions!$D$73<0)+(Assumptions!$D$73>1)+(Assumptions!$D$74<0)+(Assumptions!$D$74>1)+(Assumptions!$D$75<0)+(Assumptions!$D$75>1)+(Assumptions!$D$96<0)+(Assumptions!$D$96>1)+(Assumptions!$D$99<0)+(Assumptions!$D$99>1)+(Assumptions!$D$100<0)+(Assumptions!$D$100>1)+(Assumptions!$D$101<0)+(Assumptions!$D$101>1)+(Assumptions!$D$102<0)+(Assumptions!$D$102>1)+(Assumptions!$D$108<0)+(Assumptions!$D$108>1)+(Assumptions!$D$109<0)+(Assumptions!$D$109>1)+(Assumptions!$D$110<0)+(Assumptions!$D$110>1)+(Assumptions!$D$111<0)+(Assumptions!$D$111>1)+(Assumptions!$D$112<0)+(Assumptions!$D$112>1)+(Assumptions!$D$113<0)+(Assumptions!$D$113>1)+(Assumptions!$D$115<0)+(Assumptions!$D$115>1)+(Assumptions!$D$121<0)+(Assumptions!$D$121>1)+(Assumptions!$D$122<0)+(Assumptions!$D$122>1)+(Assumptions!$D$123<0)+(Assumptions!$D$123>1))>0,"a share/rate is outside 0–100%; ","")&IF(((Assumptions!$D$9<0)+(Assumptions!$D$11<0)+(Assumptions!$D$12<0)+(Assumptions!$D$13<0)+(Assumptions!$D$14<0)+(Assumptions!$D$15<0)+(Assumptions!$D$19<0)+(Assumptions!$D$21<0)+(Assumptions!$D$22<0)+(Assumptions!$D$23<0)+(Assumptions!$D$24<0)+(Assumptions!$D$25<0)+(Assumptions!$D$49<0)+(Assumptions!$D$51<0)+(Assumptions!$D$68<0)+(Assumptions!$D$69<0)+(Assumptions!$D$70<0)+(Assumptions!$D$71<0)+(Assumptions!$D$76<0)+(Assumptions!$D$77<0)+(Assumptions!$D$78<0)+(Assumptions!$D$79<0)+(Assumptions!$D$83<0)+(Assumptions!$D$84<0)+(Assumptions!$D$85<0)+(Assumptions!$D$86<0)+(Assumptions!$D$87<0)+(Assumptions!$D$88<0)+(Assumptions!$D$90<0)+(Assumptions!$D$92<0)+(Assumptions!$D$97<0)+(Assumptions!$D$98<0)+(Assumptions!$D$103<0)+(Assumptions!$D$114<0)+(Assumptions!$D$116<0)+(Assumptions!$D$117<0)+(Assumptions!$D$118<0)+(Assumptions!$D$119<0)+(Assumptions!$D$120<0)+(Assumptions!$D$124<0)+(Assumptions!$D$125<0)+(Assumptions!$D$126<0)+(Assumptions!$D$153<0)+(Assumptions!$D$154<0)+(Assumptions!$D$155<0)+(Assumptions!$D$156<0)+(Assumptions!$D$159<0)+(Assumptions!$D$160<0)+(Assumptions!$D$161<0)+(Assumptions!$D$162<0)+(Assumptions!$D$164<0)+(Assumptions!$D$165<0)+(Assumptions!$D$166<0)+(Assumptions!$D$167<0)+(Assumptions!$D$169<0)+(Assumptions!$D$171<0)+(Assumptions!$D$172<0)+(Assumptions!$D$173<0)+(Assumptions!$D$175<0)+(Assumptions!$D$176<0)+(Assumptions!$D$177<0)+(Assumptions!$D$178<0)+(Assumptions!$D$179<0)+(Assumptions!$D$180<0)+(Assumptions!$D$181<0)+(Assumptions!$D$182<0))>0,"a count, cost or day value is negative; ","")&IF(((INT(Assumptions!$D$19)<>Assumptions!$D$19)+(INT(Assumptions!$D$21)<>Assumptions!$D$21)+(INT(Assumptions!$D$22)<>Assumptions!$D$22)+(INT(Assumptions!$D$23)<>Assumptions!$D$23)+(INT(Assumptions!$D$24)<>Assumptions!$D$24)+(INT(Assumptions!$D$25)<>Assumptions!$D$25))>0,"day inputs (T0, T2–T6) must be whole days; ","")&IF(SUMPRODUCT((Assumptions!$E$130:$E$149<0)+(Assumptions!$G$130:$G$149<0)+(Assumptions!$G$130:$G$149>1)+(Assumptions!$H$130:$H$149<0)+(Assumptions!$I$130:$I$149<0)+(Assumptions!$J$130:$J$149<0)+(Assumptions!$F$130:$F$149<0)+((Assumptions!$D$130:$D$149="CPC")*(Assumptions!$F$130:$F$149>1)))>0,"a channel input (Assumptions §7) is out of range; ","")&IF(OR(Assumptions!$D$48<0,Assumptions!$D$48>=1),"reserve share must be 0–99%; ","")&IF(OR(Assumptions!$D$20<Assumptions!$D$7,Assumptions!$D$20>Assumptions!$D$8),"last signing date must fall inside the campaign; ","")&IF(Assumptions!$D$8<=Assumptions!$D$7,"campaign end must be after its start; ","")&IF(OR(Assumptions!$D$91>=Assumptions!$D$89,Assumptions!$D$92<Assumptions!$D$90),"initiative kill thresholds must sit below pass thresholds (TK1 < TP1, TK2 ≥ TP2); ","")) -> ✓ all inputs valid
B20: Plan / schedule check (Weekly S15) | C20: =Weekly!S15 -> ✓ ties to plan
B22: Tabs: Assumptions (every input, its label and source link) → Funnel (Part 1, with the talent-pool check) → Channels (Part 2.2–2.3) → Initiatives (Part 3) → Budget (Part 2.4–2.5, with the budget-cut scenarios) → Weekly (phasing and cash) → Tracker (Part 4, live re-plan).

Sheet Assumptions
A1: Assumptions log = the model's only input sheet
A2: Blue cells on yellow are inputs: change them here and every other tab recalculates. Labels: Given = from the brief; Researched = read from, or calculated by stated arithmetic from, the linked source; Own estimate = my judgement, with the reason (and the benchmark it starts from, where there is one). Black (not blue) values are calculated.
A5: 1. Given in the brief
A6: ID | B6: Parameter | C6: Role / scope | D6: Value | E6: Unit | F6: Label | G6: Source / reasoning
A7: G1 | B7: Campaign start | C7: All | D7: 46315 | E7: date | F7: Given | G7: From the brief.
A8: G2 | B8: Campaign end / hire deadline (signed contract) | C8: All | D8: 46387 | E8: date | F8: Given | G8: From the brief.
A9: G3 | B9: Recruiter capacity: qualified applicants assessed per week | C9: All roles | D9: 55 | E9: per week | F9: Given | G9: From the brief.
A10: G4 | B10: Max share of mechatronics/mechanical hires from Polish sources | C10: Mechatronics | D10: 0.4 | E10: % | F10: Given | G10: From the brief. Polish hires need no work permit (EU free movement) and are insured and taxed in Germany. https://www.make-it-in-germany.com/en/working-in-germany/information-eu-citizens/print
A11: G5 | B11: Openings | C11: Electricians | D11: 30 | E11: hires | F11: Given | G11: From the brief.
A12: G6 | B12: Openings | C12: Mechatronics | D12: 45 | E12: hires | F12: Given | G12: From the brief.
A13: G7 | B13: Openings | C13: Automation | D13: 15 | E13: hires | F13: Given | G13: From the brief.
A14: G8 | B14: Openings | C14: Supervisors | D14: 10 | E14: hires | F14: Given | G14: From the brief.
A15: G9 | B15: Foreign electrical qualification recognition time (info only: makes foreign-trained electricians unhireable by 31 Dec) | C15: Electricians | D15: 2 | E15: months (min) | F15: Given | G15: From the brief, so I plan no foreign-trained electricians. Worth raising: for employees the trade is not legally regulated, which could open this route. https://www.anerkennung-in-deutschland.de/en/interest/finder/profession/62/profile
A17: 2. Hiring timeline (sets the last useful application date)
A18: ID | B18: Parameter | C18: Role / scope | D18: Value | E18: Unit | F18: Label | G18: Source / reasoning
A19: T0 | B19: Days from campaign start to first assessments | C19: All | D19: 2 | E19: days | F19: Own estimate | G19: Own estimate, not sourced: at launch there is no queue, so the first applicants and re-applicants are assessed within 2 days (SmartRecruiters' 6-day median review, T2, applies once a queue exists and sets the cut-off). If first assessments slip to 26 Oct, hires fall to ~92 (model run); 100 would then need 60 a week.
A20: T1 | B20: Last realistic contract-signing date | C20: All | D20: 46374 | E20: date | F20: Own estimate | G20: My choice: the last Friday before Christmas. Indeed job searches fall to 45% below the 1–15 Dec average over the holidays (Indeed Hiring Lab). https://hiringlab.indeed.com/de/blog/2025/02/17/der-stellenmarkt-startet-unausgewogen-in-das-neue-jahr/
A21: T2 | B21: Days: application → recruiter assessment of a qualified applicant | C21: All | D21: 6 | E21: days | F21: Researched | G21: Own estimate: SmartRecruiters 2025 global median is 6 days to review (Germany 8); I assume the client keeps the global pace, an ask. Slide 1 shows the German-pace downside (~92 hires). https://ta.smartrecruiters.com/rs/664-NIC-529/images/Germany%20Recruiting%20Benchmarks%202025%20Report%20DE.pdf
A22: T3 | B22: Days: recruiter assessment → technical interview/test done | C22: All | D22: 8 | E22: days | F22: Own estimate | G22: Own estimate: global median 14 days application → interview minus the 6 above (Germany 20 − 8 = 12); same commitment as T2. https://ta.smartrecruiters.com/rs/664-NIC-529/images/Germany%20Recruiting%20Benchmarks%202025%20Report%20DE.pdf
A23: T4 | B23: Days: interview → written offer | C23: All | D23: 3 | E23: days | F23: Own estimate | G23: My ask to the client: written offer within 3 working days. No public benchmark exists for this step.
A24: T5 | B24: Days: offer → signed contract | C24: All | D24: 7 | E24: days | F24: Own estimate | G24: One-week offer validity; candidates take ~9 days on average to decide (NACE 2025). https://www.naceweb.org/talent-acquisition/trends-and-predictions/employers-make-more-offers-as-student-acceptance-rate-rises-response-time-shortens
A25: T6 | B25: Extra days for supervisors (second round with plant management) | C25: Supervisors | D25: 7 | E25: days | F25: Own estimate | G25: Supervisors have one extra round with plant management (about a week).
A27: 3. Funnel rates by role (Part 1)
A28: ID | B28: Parameter | C28: Role / scope | D28: Value | E28: Unit | F28: Label | G28: Source / reasoning
A29: QE | B29: Application → qualified (baseline, all channels) | C29: Electricians | D29: 0.25 | E29: % | F29: Researched | G29: IAB 2026 chart: production jobs get 12 applications per vacancy, 3 suitable (25%); 28% across all jobs; 23% for specialist roles. https://iab-forum.de/iab-stellenerhebung-2-2026-fast-drei-von-vier-bewerbungen-sind-aus-betrieblicher-sicht-ungeeignet/
A30: QM | B30: Application → qualified (baseline, all channels) | C30: Mechatronics | D30: 0.25 | E30: % | F30: Researched | G30: IAB 2026 chart: production jobs get 12 applications per vacancy, 3 suitable (25%); 28% across all jobs; 23% for specialist roles. https://iab-forum.de/iab-stellenerhebung-2-2026-fast-drei-von-vier-bewerbungen-sind-aus-betrieblicher-sicht-ungeeignet/
A31: QA | B31: Application → qualified (baseline, all channels) | C31: Automation | D31: 0.25 | E31: % | F31: Researched | G31: IAB 2026 chart: production jobs get 12 applications per vacancy, 3 suitable (25%); 28% across all jobs; 23% for specialist roles. https://iab-forum.de/iab-stellenerhebung-2-2026-fast-drei-von-vier-bewerbungen-sind-aus-betrieblicher-sicht-ungeeignet/
A32: QS | B32: Application → qualified (baseline, all channels) | C32: Supervisors | D32: 0.23 | E32: % | F32: Researched | G32: IAB 2026 chart: production jobs get 12 applications per vacancy, 3 suitable (25%); 28% across all jobs; 23% for specialist roles. https://iab-forum.de/iab-stellenerhebung-2-2026-fast-drei-von-vier-bewerbungen-sind-aus-betrieblicher-sicht-ungeeignet/
A33: PE | B33: Qualified → passed assessment | C33: Electricians | D33: 0.5 | E33: % | F33: Own estimate | G33: Gem 2025: ~35% of candidates brought onsite get offers (mostly US tech). Set higher (50%) because only pre-qualified people reach this step. https://lp.gem.com/rs/972-IVV-330/images/2025%20Recruiting%20Benchmarks%20-%20Gem.pdf
A34: PM | B34: Qualified → passed assessment | C34: Mechatronics | D34: 0.55 | E34: % | F34: Own estimate | G34: Gem 2025: ~35% of onsite candidates get offers. Set at 55%: most common trade, the assessment is routine for it. https://lp.gem.com/rs/972-IVV-330/images/2025%20Recruiting%20Benchmarks%20-%20Gem.pdf
A35: PA | B35: Qualified → passed assessment | C35: Automation | D35: 0.45 | E35: % | F35: Own estimate | G35: Gem 2025: ~35% of onsite candidates get offers. Set at 45%: PLC skills are tested hard. https://lp.gem.com/rs/972-IVV-330/images/2025%20Recruiting%20Benchmarks%20-%20Gem.pdf
A36: PS | B36: Qualified → passed assessment | C36: Supervisors | D36: 0.4 | E36: % | F36: Own estimate | G36: Gem 2025: ~35% of onsite candidates get offers. Set at 40%: leadership is assessed on top of trade skills. https://lp.gem.com/rs/972-IVV-330/images/2025%20Recruiting%20Benchmarks%20-%20Gem.pdf
A37: OE | B37: Passed → offer made | C37: Electricians | D37: 0.9 | E37: % | F37: Own estimate | G37: My estimate: ~10% drop out after passing (references, pay, shifts), 15% for supervisors. No public figure exists.
A38: OM | B38: Passed → offer made | C38: Mechatronics | D38: 0.9 | E38: % | F38: Own estimate | G38: My estimate: ~10% drop out after passing (references, pay, shifts), 15% for supervisors. No public figure exists.
A39: OA | B39: Passed → offer made | C39: Automation | D39: 0.9 | E39: % | F39: Own estimate | G39: My estimate: ~10% drop out after passing (references, pay, shifts), 15% for supervisors. No public figure exists.
A40: OS | B40: Passed → offer made | C40: Supervisors | D40: 0.85 | E40: % | F40: Own estimate | G40: My estimate: ~10% drop out after passing (references, pay, shifts), 15% for supervisors. No public figure exists.
... A44: AS | B44: Offer → signed contract | C44: Supervisors | D44: 0.7 | E44: % | F44: Own estimate | G44: Königsteiner 2022: 47% accepted vs 14% declined after an offer → ~77% acceptance. I use 70–75%: shift work and competing offers. https://www.lebensmittelzeitung.net/handel/karriere/rekrutierung-bewerber-sagen-haeufiger-ab-166449
A46: 4. Budget policy and weekly phasing (Part 2)
A47: ID | B47: Parameter | C47: Role / scope | D47: Value | E47: Unit | F47: Label | G47: Source / reasoning
A48: B1 | B48: Reserve held back (share of total budget) | C48: All | D48: 0.15 | E48: % | F48: Own estimate | G48: 15% buffer, in the 10–20% range used for risky projects; released only on results. https://mastt.com/blogs/construction-contingency
A49: B2 | B49: Test tranche: first spend in every paid CPC/CPA channel × role cell, in weeks 1–2 | C49: Paid CPC/CPA cells | D49: 750 | E49: € | F49: Own estimate | G49: €750 per paid channel and role in weeks 1–2: enough to see whether it works before spending more.
A50: B4 | B50: Share of test tranches spent in week 1 (rest in week 2) | C50: Paid CPC/CPA cells | D50: 0.4 | E50: % | F50: Own estimate | G50: Week 1 has fewer assessment days, so 40% of the test money goes there.
A51: B5 | B51: Rounding step for the recommended budget | C51: All | D51: 2500 | E51: € | F51: Own estimate | G51: Rounded up to a clean figure; the difference goes to the reserve.
A52: B3 | B52: Budget cut scenario the client asked about | C52: All | D52: 0.3 | E52: % | F52: Given | G52: From the brief.
A53: W1 | B53: Share of media spend in week 1 | C53: All paid | D53: 0.316 | E53: % | F53: Own estimate | G53: Paced so each week's qualified applicants fit the slots they can use (assessed 6 days after applying). Week 1 is biggest: it also fills the first assessment days (22–25 Oct). Week 6 is small: only 24 Nov is still useful.
A54: W2 | B54: Share of media spend in week 2 | C54: All paid | D54: 0.131 | E54: % | F54: Own estimate | G54: Paced so each week's qualified applicants fit the slots they can use (assessed 6 days after applying). Week 1 is biggest: it also fills the first assessment days (22–25 Oct). Week 6 is small: only 24 Nov is still useful.
A55: W3 | B55: Share of media spend in week 3 | C55: All paid | D55: 0.161 | E55: % | F55: Own estimate | G55: Paced so each week's qualified applicants fit the slots they can use (assessed 6 days after applying). Week 1 is biggest: it also fills the first assessment days (22–25 Oct). Week 6 is small: only 24 Nov is still useful.
A56: W4 | B56: Share of media spend in week 4 | C56: All paid | D56: 0.17 | E56: % | F56: Own estimate | G56: Paced so each week's qualified applicants fit the slots they can use (assessed 6 days after applying). Week 1 is biggest: it also fills the first assessment days (22–25 Oct). Week 6 is small: only 24 Nov is still useful.
A57: W5 | B57: Share of media spend in week 5 | C57: All paid | D57: 0.195 | E57: % | F57: Own estimate | G57: Paced so each week's qualified applicants fit the slots they can use (assessed 6 days after applying). Week 1 is biggest: it also fills the first assessment days (22–25 Oct). Week 6 is small: only 24 Nov is still useful.
A58: W6 | B58: Share of media spend in week 6 | C58: All paid | D58: 0.027 | E58: % | F58: Own estimate | G58: Paced so each week's qualified applicants fit the slots they can use (assessed 6 days after applying). Week 1 is biggest: it also fills the first assessment days (22–25 Oct). Week 6 is small: only 24 Nov is still useful.
A59: W7 | B59: Share of media spend in week 7 | C59: All paid | D59: 0 | E59: % | F59: Own estimate | G59: No spend after the last useful application date.
... A64: S1 | B64: Stress size for sensitivity test | C64: All | D64: 0.3 | E64: % | F64: Given | G64: From the brief.
A66: 5. Talent pool sanity check (Part 2.2)
A67: ID | B67: Parameter | C67: Role / scope | D67: Value | E67: Unit | F67: Label | G67: Source / reasoning
A68: PSE | B68: Qualified people employed within 75 km (Berlin + ~60% of Brandenburg) | C68: Electricians | D68: 4800 | E68: people | F68: Own estimate | G68: BA employment, KldB 2625 + 2622: Berlin 2,708 + 60% of Brandenburg 3,417 (own scaling: ~60% of Brandenburg lies within 75 km) ≈ 4,800. Berlin file: https://statistik.arbeitsagentur.de/Statistikdaten/Detail/202512/iiia6/beschaeftigung-sozbe-bo-heft/bo-heft-11-0-202512-xlsx.xlsx?__blob=publicationFile https://statistik.arbeitsagentur.de/Statistikdaten/Detail/202512/iiia6/beschaeftigung-sozbe-bo-heft/bo-heft-12-0-202512-xlsx.xlsx?__blob=publicationFile
A69: PSM | B69: Qualified people employed within 75 km (Berlin + ~60% of Brandenburg) | C69: Mechatronics | D69: 26400 | E69: people | F69: Own estimate | G69: BA employment, KldB 2611 + 2510/2511/2513 (skilled level): Berlin 17,490 + 60% of Brandenburg 14,878 (own scaling: ~60% of Brandenburg lies within 75 km) ≈ 26,400. Berlin file: https://statistik.arbeitsagentur.de/Statistikdaten/Detail/202512/iiia6/beschaeftigung-sozbe-bo-heft/bo-heft-11-0-202512-xlsx.xlsx?__blob=publicationFile https://statistik.arbeitsagentur.de/Statistikdaten/Detail/202512/iiia6/beschaeftigung-sozbe-bo-heft/bo-heft-12-0-202512-xlsx.xlsx?__blob=publicationFile
A70: PSA | B70: Qualified people employed within 75 km (Berlin + ~60% of Brandenburg) | C70: Automation | D70: 2000 | E70: people | F70: Own estimate | G70: BA employment, KldB 2612: Berlin 1,254 + 60% of Brandenburg 1,206 (own scaling: ~60% of Brandenburg lies within 75 km) ≈ 2,000. Berlin file: https://statistik.arbeitsagentur.de/Statistikdaten/Detail/202512/iiia6/beschaeftigung-sozbe-bo-heft/bo-heft-11-0-202512-xlsx.xlsx?__blob=publicationFile https://statistik.arbeitsagentur.de/Statistikdaten/Detail/202512/iiia6/beschaeftigung-sozbe-bo-heft/bo-heft-12-0-202512-xlsx.xlsx?__blob=publicationFile
A71: PSS | B71: Qualified people employed within 75 km (Berlin + ~60% of Brandenburg) | C71: Supervisors | D71: 2200 | E71: people | F71: Own estimate | G71: BA employment, supervisor codes 2519 + 2619 + 2629 + 2639: Berlin 1,494 + 60% of Brandenburg 1,209 (own scaling: ~60% of Brandenburg lies within 75 km) ≈ 2,200. Berlin file: https://statistik.arbeitsagentur.de/Statistikdaten/Detail/202512/iiia6/beschaeftigung-sozbe-bo-heft/bo-heft-11-0-202512-xlsx.xlsx?__blob=publicationFile https://statistik.arbeitsagentur.de/Statistikdaten/Detail/202512/iiia6/beschaeftigung-sozbe-bo-heft/bo-heft-12-0-202512-xlsx.xlsx?__blob=publicationFile
A72: PIE | B72: Share in-market or persuadable during the 6-week window | C72: Electricians | D72: 0.11 | E72: % | F72: Researched | G72: Gallup 2024: active job search is 3% / 10% / 23% for high / low / no engagement; weighted by the 9% / 78% / 13% shares ≈ 11%. https://gallup.com/file/de/657716/Engagement-Index-Deutschland-Report-2024.pdf
A73: PIM | B73: Share in-market or persuadable during the 6-week window | C73: Mechatronics | D73: 0.11 | E73: % | F73: Researched | G73: Gallup 2024: active job search is 3% / 10% / 23% for high / low / no engagement; weighted by the 9% / 78% / 13% shares ≈ 11%. https://gallup.com/file/de/657716/Engagement-Index-Deutschland-Report-2024.pdf
A74: PIA | B74: Share in-market or persuadable during the 6-week window | C74: Automation | D74: 0.11 | E74: % | F74: Researched | G74: Gallup 2024: active job search is 3% / 10% / 23% for high / low / no engagement; weighted by the 9% / 78% / 13% shares ≈ 11%. https://gallup.com/file/de/657716/Engagement-Index-Deutschland-Report-2024.pdf
A75: PIS | B75: Share in-market or persuadable during the 6-week window | C75: Supervisors | D75: 0.11 | E75: % | F75: Researched | G75: Gallup 2024: active job search is 3% / 10% / 23% for high / low / no engagement; weighted by the 9% / 78% / 13% shares ≈ 11%. https://gallup.com/file/de/657716/Engagement-Index-Deutschland-Report-2024.pdf
A76: PRE | B76: Qualified people elsewhere in Germany willing to relocate in the window | C76: Electricians | D76: 41 | E76: people | F76: Own estimate | G76: Own sizing: few trades workers move across Germany for a job; national headcount × yearly move rate × share moving to Berlin-Brandenburg.
A77: PRM | B77: Qualified people elsewhere in Germany willing to relocate in the window | C77: Mechatronics | D77: 28 | E77: people | F77: Own estimate | G77: Own sizing: few trades workers move across Germany for a job; national headcount × yearly move rate × share moving to Berlin-Brandenburg.
A78: PRA | B78: Qualified people elsewhere in Germany willing to relocate in the window | C78: Automation | D78: 16 | E78: people | F78: Own estimate | G78: Own sizing: few trades workers move across Germany for a job; national headcount × yearly move rate × share moving to Berlin-Brandenburg.
A79: PRS | B79: Qualified people elsewhere in Germany willing to relocate in the window | C79: Supervisors | D79: 4 | E79: people | F79: Own estimate | G79: Own sizing: few trades workers move across Germany for a job; national headcount × yearly move rate × share moving to Berlin-Brandenburg.
A81: 6. Week-by-week money rules (Part 4) — used by the Tracker tab
A82: ID | B82: Parameter | C82: Role / scope | D82: Value | E82: Unit | F82: Label | G82: Source / reasoning
A83: R1 | B83: Minimum spend before judging a cell | C83: Per cell | D83: 500 | E83: € | F83: Own estimate | G83: Don't judge a channel on less than €500 or 30 applications; too little data.
A84: R2 | B84: …or minimum applications before judging a cell | C84: Per cell | D84: 30 | E84: apps | F84: Own estimate | G84: Don't judge a channel on less than €500 or 30 applications; too little data.
A85: R3 | B85: Scale up when re-forecast cost per qualified ≤ this × plan | C85: Per cell | D85: 0.8 | E85: × plan | F85: Own estimate | G85: 20% cheaper than plan and slots free → scale up.
A86: R4 | B86: Cut budget 50% when re-forecast cost per qualified ≥ this × plan | C86: Per cell | D86: 1.5 | E86: × plan | F86: Own estimate | G86: A common ad rule is 'reduce if cost is 1.2–2× target' (roaspig); I halve at 1.5×. https://roaspig.com/blog/automated-rules-manage-meta-budgets/
A87: R5 | B87: Switch off when cost per qualified ≥ this × plan | C87: Per cell | D87: 2 | E87: × plan | F87: Own estimate | G87: Twice the plan cost → switch off (common ad practice). https://roaspig.com/blog/automated-rules-manage-meta-budgets/
A88: R6 | B88: …or switch off when spend reaches this and R2 applications brought zero qualified | C88: Per cell | D88: 750 | E88: € | F88: Own estimate | G88: Test spent (€750) and 30+ applications with none qualified → off. By chance that happens < 0.1% of the time for job boards (~22–25% qualify: 0.775^30) and ~4% for Meta (~10% qualify: 0.9^30).
A89: TP1 | B89: Initiative test: PASS needs about this share of planned qualified in the window (rounded down) | C89: Initiatives | D89: 0.6 | E89: % | F89: Own estimate | G89: Two-week test passes at about 60% of the planned qualified applicants (rounded down to a whole person, so 54–58% at the current plan).
A90: TP2 | B90: Initiative test: PASS needs cost per qualified ≤ this × plan | C90: Initiatives | D90: 1.5 | E90: × plan | F90: Own estimate | G90: Same cost limit as the channel cut rule (1.5× plan).
A91: TK1 | B91: Initiative test: KILL if qualified below this share of plan | C91: Initiatives | D91: 0.3 | E91: % | F91: Own estimate | G91: Kill the initiative if fewer than about 30% of the planned qualified arrive (rounded up to a whole person).
A92: TK2 | B92: Initiative test: KILL if cost per qualified above this × plan | C92: Initiatives | D92: 2 | E92: × plan | F92: Own estimate | G92: Same cost limit as the channel switch-off rule (2× plan).
A93: I1W1 | B93: I1a re-applications arriving in week 1 (waves on days 2 and 7) | C93: Rediscovery | D93: 0.6 | E93: % | F93: Own estimate | G93: Most replies come within a day of each message (Pin 2026), so 60% arrive in week 1. https://www.pin.com/blog/recruiting-outreach-benchmark-report/
A94: I1W2 | B94: I1a re-applications arriving in week 2 | C94: Rediscovery | D94: 0.29 | E94: % | F94: Own estimate | G94: Most replies come within a day of each message (Pin 2026), so 60% arrive in week 1. https://www.pin.com/blog/recruiting-outreach-benchmark-report/
... A103: R13 | B103: Pacing floor: release reserve to the cheapest cells with capacity when next week's forecast qualified falls below | C103: All roles | D103: 50 | E103: qualified/wk | F103: Own estimate | G103: Next week below 90% of the 55 slots → release reserve to the cheapest working channel.
A106: 6a. Facts behind channel quality and volumes (cells in black below are calculated from these)
A107: ID | B107: Parameter | C107: Role / scope | D107: Value | E107: Unit | F107: Label | G107: Source / reasoning
A108: CXB | B108: Channel quality index: online job boards (programmatic, StepStone, LinkedIn) | C108: Channels | D108: 0.9 | E108: × | F108: Researched | G108: Derived from IAB 2025: decisive ÷ used for job boards (21% ÷ 57% = 0.37) ÷ 0.41 = 0.90. Average = mean of decisive ÷ used over the three channels IAB reports (homepage 20/70, job boards 21/57, personal contacts 27/48) = 0.41. https://iab-forum.de/online-medien-sind-bei-der-personalsuche-auf-dem-vormarsch/
A109: CXH | B109: Channel quality index: own careers page (organic, Google Search ads) | C109: Channels | D109: 0.7 | E109: × | F109: Researched | G109: Derived from IAB 2025: decisive ÷ used for the employer homepage (20% ÷ 70% = 0.29) ÷ 0.41 = 0.70. Average = mean of decisive ÷ used over the three channels IAB reports (homepage 20/70, job boards 21/57, personal contacts 27/48) = 0.41. https://iab-forum.de/online-medien-sind-bei-der-personalsuche-auf-dem-vormarsch/
A110: CXS | B110: Channel quality index: social media (Meta) | C110: Channels | D110: 0.41 | E110: × | F110: Researched | G110: Derived from IAB data (2022): social media was used for 42% of filled jobs but decisive for 1 in 14; (7.1% ÷ 42%) ÷ 0.41 ≈ 0.41. https://ohn.haendlerbund.de/themen/unternehmen-maerkte/139538-social-media-whatsapp-mitarbeitersuche-immer-wichtiger
A111: RXP | B111: Reach: share of skilled-worker job seekers using Indeed (programmatic cap) | C111: Channels | D111: 0.36 | E111: % | F111: Researched | G111: 36% of skilled-worker job seekers use Indeed (Trendence 2023). https://www.personalwirtschaft.de/?p=157882
A112: RXL | B112: Reach: share of skilled-worker job seekers using LinkedIn | C112: Channels | D112: 0.15 | E112: % | F112: Researched | G112: 15% of skilled-worker job seekers use LinkedIn (Trendence 2023). https://www.personalwirtschaft.de/?p=157882
A113: RXG | B113: Reach: share of job seekers starting their search on Google | C113: Channels | D113: 0.105 | E113: % | F113: Researched | G113: 10.5% of job seekers start their search on Google (softgarden). https://www.personalwirtschaft.de/news/recruiting/jeder-zehnte-nutzt-google-zur-jobsuche-97400/
A114: APV | B114: Applications per vacancy, firms with 250+ staff | C114: Organic | D114: 27 | E114: apps | F114: Researched | G114: Firms with 250+ staff get ~27 applications per vacancy (IAB 2026). https://iab-forum.de/iab-stellenerhebung-2-2026-fast-drei-von-vier-bewerbungen-sind-aus-betrieblicher-sicht-ungeeignet/
A115: CPS | B115: Share of applications that come via the careers page | C115: Organic | D115: 0.13 | E115: % | F115: Researched | G115: 13% of applications come through the careers page (CareerPlug 2025). https://www.careerplug.com/wp-content/uploads/2025/04/Recruiting-Metrics-Report.pdf
A116: RDE | B116: Qualified applications per Elektroniker social campaign (median) | C116: Meta electricians | D116: 20 | E116: qualified | F116: Researched | G116: Typical social campaign for electricians brings ~20 qualified applications (Redline, 181 campaigns). https://redline-grow.de/bewerbungen-pro-stelle
A117: RDM | B117: Qualified applications per Kfz-Mechatroniker social campaign (median) | C117: Meta mechatronics | D117: 23 | E117: qualified | F117: Researched | G117: Typical social campaign for mechatronics brings ~23 qualified applications (Redline). https://redline-grow.de/bewerbungen-pro-stelle
A118: RD2 | B118: Qualified applications per Elektroniker social campaign (mean, sizes I2) | C118: I2 | D118: 29.5 | E118: qualified | F118: Researched | G118: Redline 2024–26: mean 29.5 qualified applications per Elektroniker campaign (11 campaigns). https://redline-grow.de/bewerbungen-pro-stelle
A119: SSW | B119: Days one StepStone ad runs | C119: StepStone | D119: 30 | E119: days | F119: Researched | G119: A StepStone ad runs 30 days. https://www.stepstone.de/e-recruiting/stellenanzeige-aufgeben/
... A126: PLT | B126: …of which in machine/vehicle, metalworking and building trades | C126: I3 | D126: 1678 | E126: people | F126: Researched | G126: Same table: machine and vehicle technology 825 + metal 424 + building construction 429 = 1,678 (https://doku.iab.de/regional/BB/2020/regional_bb_0120.pdf).
A128: 7. Channel × role inputs (Part 2.2). Basis: CPC → CPA = CPC ÷ click-to-apply rate; CPA = bought per application/lead; Slot = fixed-price 30-day ad → CPA = price ÷ apps per ad; Free = no media cost.
A129: ID | B129: Channel | C129: Role | D129: Basis | E129: Unit cost € (CPC / CPA / slot price) | F129: Click→apply % or apps per slot | G129: Share qualified | H129: Max applications over campaign (or no. of slots) | I129: Downstream adj. (× role conversion) | J129: Fixed cost € | K129: Label | L129: Source / reasoning
A130: C01 | B130: Organic (Tesla careers, BA Jobbörse, Google for Jobs) | C130: Electricians | D130: Free | E130: 0 | G130: =Assumptions!$D$29*Assumptions!$D$109 -> 0.175 | H130: =ROUND(Assumptions!$D$11*Assumptions!$D$114*Assumptions!$D$115,0) -> 105 | I130: 1 | J130: 0 | K130: Researched | L130: Free listings (careers site, BA Jobbörse, Google for Jobs). Volume: ~27 applications per vacancy, 13% via the careers page. https://www.arbeitsagentur.de/faktor-a/mitarbeiter-finden/so-funktioniert-deutschlands-groesste-jobboerse
A131: C02 | B131: Organic (Tesla careers, BA Jobbörse, Google for Jobs) | C131: Mechatronics | D131: Free | E131: 0 | G131: =Assumptions!$D$30*Assumptions!$D$109 -> 0.175 | H131: =ROUND(Assumptions!$D$12*Assumptions!$D$114*Assumptions!$D$115,0) -> 158 | I131: 1 | J131: 0 | K131: Researched | L131: Free listings (careers site, BA Jobbörse, Google for Jobs). Volume: ~27 applications per vacancy, 13% via the careers page. https://www.arbeitsagentur.de/faktor-a/mitarbeiter-finden/so-funktioniert-deutschlands-groesste-jobboerse
...

Sheet Funnel
A1: Part 1 — Funnel by role (work back from openings)
A2: How: qualified needed = openings ÷ (pass × offer × accept); applications needed = qualified ÷ share qualified. Rates from Assumptions §3. 'Qualified' = right trade qualification + English or German + accepts shifts (brief).
A4: Role | B4: Openings | C4: App → qualified | D4: Qualified → passed | E4: Passed → offer | F4: Offer → signed | G4: Qualified → signed | H4: App → signed | I4: Offers needed | J4: Passed needed | K4: Qualified needed | L4: Applications needed (baseline Q) | M4: Applications in plan (channel mix) | N4: Blended Q in plan | O4: Qualified in plan | P4: Share of assessment slots
A5: Electricians | B5: =Assumptions!$D$11 -> 30 | C5: =Assumptions!$D$29 -> 0.25 | D5: =Assumptions!$D$33 -> 0.5 | E5: =Assumptions!$D$37 -> 0.9 | F5: =Assumptions!$D$41 -> 0.7 | G5: =D5*E5*F5 -> 0.315 | H5: =C5*G5 -> 0.07875 | I5: =IF(F5>0,B5/F5,0) -> 42.857143 | J5: =IF(E5>0,I5/E5,0) -> 47.619048 | K5: =IF(D5>0,J5/D5,0) -> 95.238095 | L5: =IF(C5>0,K5/C5,0) -> 380.95238 | M5: =SUMIFS(Channels!$W:$W,Channels!$C:$C,A5) -> 414.27263 | N5: =IF(M5>0,O5/M5,0) -> 0.23234239 | O5: =SUMIFS(Channels!$V:$V,Channels!$C:$C,A5) -> 96.253095 | P5: =IF($B$22>0,O5/$B$22,0) -> 0.30625985
A6: Mechatronics | B6: =Assumptions!$D$12 -> 45 | C6: =Assumptions!$D$30 -> 0.25 | D6: =Assumptions!$D$34 -> 0.55 | E6: =Assumptions!$D$38 -> 0.9 | F6: =Assumptions!$D$42 -> 0.75 | G6: =D6*E6*F6 -> 0.37125 | H6: =C6*G6 -> 0.0928125 | I6: =IF(F6>0,B6/F6,0) -> 60 | J6: =IF(E6>0,I6/E6,0) -> 66.666667 | K6: =IF(D6>0,J6/D6,0) -> 121.21212 | L6: =IF(C6>0,K6/C6,0) -> 484.84848 | M6: =SUMIFS(Channels!$W:$W,Channels!$C:$C,A6) -> 662.46932 | N6: =IF(M6>0,O6/M6,0) -> 0.17928848 | O6: =SUMIFS(Channels!$V:$V,Channels!$C:$C,A6) -> 118.77312 | P6: =IF($B$22>0,O6/$B$22,0) -> 0.37791448
A7: Automation | B7: =Assumptions!$D$13 -> 15 | C7: =Assumptions!$D$31 -> 0.25 | D7: =Assumptions!$D$35 -> 0.45 | E7: =Assumptions!$D$39 -> 0.9 | F7: =Assumptions!$D$43 -> 0.7 | G7: =D7*E7*F7 -> 0.2835 | H7: =C7*G7 -> 0.070875 | I7: =IF(F7>0,B7/F7,0) -> 21.428571 | J7: =IF(E7>0,I7/E7,0) -> 23.809524 | K7: =IF(D7>0,J7/D7,0) -> 52.910053 | L7: =IF(C7>0,K7/C7,0) -> 211.64021 | M7: =SUMIFS(Channels!$W:$W,Channels!$C:$C,A7) -> 226.47133 | N7: =IF(M7>0,O7/M7,0) -> 0.22883935 | O7: =SUMIFS(Channels!$V:$V,Channels!$C:$C,A7) -> 51.825553 | P7: =IF($B$22>0,O7/$B$22,0) -> 0.16489949
A8: Supervisors | B8: =Assumptions!$D$14 -> 10 | C8: =Assumptions!$D$32 -> 0.23 | D8: =Assumptions!$D$36 -> 0.4 | E8: =Assumptions!$D$40 -> 0.85 | F8: =Assumptions!$D$44 -> 0.7 | G8: =D8*E8*F8 -> 0.238 | H8: =C8*G8 -> 0.05474 | I8: =IF(F8>0,B8/F8,0) -> 14.285714 | J8: =IF(E8>0,I8/E8,0) -> 16.806723 | K8: =IF(D8>0,J8/D8,0) -> 42.016807 | L8: =IF(C8>0,K8/C8,0) -> 182.68177 | M8: =SUMIFS(Channels!$W:$W,Channels!$C:$C,A8) -> 191.36195 | N8: =IF(M8>0,O8/M8,0) -> 0.21488758 | O8: =SUMIFS(Channels!$V:$V,Channels!$C:$C,A8) -> 41.121307 | P8: =IF($B$22>0,O8/$B$22,0) -> 0.13084052
A9: Total | B9: =SUM(B5:B8) -> 100 | G9: =IF(K9>0,B9/K9,0) -> 0.32115402 | I9: =SUM(I5:I8) -> 138.57143 | J9: =SUM(J5:J8) -> 154.90196 | K9: =SUM(K5:K8) -> 311.37708 | L9: =SUM(L5:L8) -> 1260.1228 | M9: =SUM(M5:M8) -> 1494.5752 | N9: =IF(M9>0,O9/M9,0) -> 0.2060606 | O9: =SUM(O5:O8) -> 307.97308 | P9: =IF($B$22>0,O9/$B$22,0) -> 0.97991433
A10: Qualified needed (col K) uses role averages; 'Qualified in plan' (col O) reflects the actual channel mix incl. better/worse downstream conversion of initiatives. Capacity is checked on col O.
A12: Timeline and recruiter capacity (Part 1.3)
A13: First assessment date | B13: =Assumptions!$D$7+Assumptions!$D$19 -> 46317
A14: Last signing date | B14: =Assumptions!$D$20 -> 46374
A15: Days assessment → signed (E/M/A) | B15: =Assumptions!$D$22+Assumptions!$D$23+Assumptions!$D$24 -> 18
A16: Days assessment → signed (Supervisors) | B16: =B15+Assumptions!$D$25 -> 25
A17: Last assessment date (E/M/A) | B17: =B14-B15 -> 46356
A18: Last assessment date (Supervisors) | B18: =B14-B16 -> 46349
A19: Last useful application date (E/M/A) | B19: =B17-Assumptions!$D$21 -> 46350
A20: Last useful application date (Supervisors) | B20: =B18-Assumptions!$D$21 -> 46343
A21: Assessment window (days, E/M/A) | B21: =MAX(0,B17-B13+1) -> 40
A22: Assessment slots available (capacity × weeks) | B22: =Assumptions!$D$9*B21/7 -> 314.28571
A23: Qualified applicants in plan | B23: =O9 -> 307.97308
A24: Slot utilisation | B24: =IF(B22>0,B23/B22,IF(B23>0,9.99,0)) -> 0.97991433 | C24: =IF(B24>1,"OVER CAPACITY – plan cannot be assessed",IF(B24>Assumptions!$D$101,"Tight: little headroom","OK")) -> Tight: little headroom
A25: Hires per qualified applicant (plan mix) | B25: =IF(O9>0,Channels!U35/O9,0) -> 0.32470371
A26: Max hires the 55/week limit allows before 31 Dec | B26: =B22*B25 -> 102.04974 | C26: If every slot is filled at the plan's conversion; above 100 = headroom.
A28: Which role is hardest to fill? (Part 1.3)
A29: Role | B29: Openings | C29: Qualified needed (plan) | D29: Hire capacity of all channels at plan rates | E29: Coverage (capacity ÷ openings) | F29: Reachable qualified pool (pool check below) | G29: Qualified needed ÷ reachable pool (excl. I2, pool check below) | H29: Highest cost per hire we must buy (beyond tests) | I29: Polish route allowed? | J29: Foreign-trained route by 31 Dec? | K29: Coverage without the unproven I2 initiative | L29: Ranking helper (roles with openings)
A30: Electricians | B30: =B5 -> 30 | C30: =O5 -> 96.253095 | D30: =SUMIFS(Channels!$N:$N,Channels!$C:$C,A30) -> 110.22165 | E30: =IF(B30>0,D30/B30,0) -> 3.674055 | F30: =Funnel!F58 -> 569 | G30: =Funnel!H58 -> 0.11731651 | H30: =_xlfn.MAXIFS(Channels!$P:$P,Channels!$C:$C,A30,Channels!$AI:$AI,">0") -> 2271.6049 | I30: No | J30: No – recognition takes 2–4 months | K30: =IF(B30>0,(D30-SUMIFS(Channels!$N:$N,Channels!$A:$A,"I2-E",Channels!$C:$C,A30))/B30,0) -> 3.39528 | L30: =IF(B30>0,K30,1000000000) -> 3.39528
A31: Mechatronics | B31: =B6 -> 45 | C31: =O6 -> 118.77312 | D31: =SUMIFS(Channels!$N:$N,Channels!$C:$C,A31) -> 551.69007 | E31: =IF(B31>0,D31/B31,0) -> 12.259779 | F31: =Funnel!F59 -> 2932 | G31: =Funnel!H59 -> 0.04050925 | H31: =_xlfn.MAXIFS(Channels!$P:$P,Channels!$C:$C,A31,Channels!$AI:$AI,">0") -> 1927.4224 | I31: Yes (≤40%) | J31: Yes (no recognition gate in brief) | K31: =IF(B31>0,(D31-SUMIFS(Channels!$N:$N,Channels!$A:$A,"I2-E",Channels!$C:$C,A31))/B31,0) -> 12.259779 | L31: =IF(B31>0,K31,1000000000) -> 12.259779
A32: Automation | B32: =B7 -> 15 | C32: =O7 -> 51.825553 | D32: =SUMIFS(Channels!$N:$N,Channels!$C:$C,A32) -> 47.908523 | E32: =IF(B32>0,D32/B32,0) -> 3.1939016 | F32: =Funnel!F60 -> 236 | G32: =Funnel!H60 -> 0.2195998 | H32: =_xlfn.MAXIFS(Channels!$P:$P,Channels!$C:$C,A32,Channels!$AI:$AI,">0") -> 1504.9971 | I32: No | J32: Yes (no recognition gate in brief) | K32: =IF(B32>0,(D32-SUMIFS(Channels!$N:$N,Channels!$A:$A,"I2-E",Channels!$C:$C,A32))/B32,0) -> 3.1939016 | L32: =IF(B32>0,K32,1000000000) -> 3.1939016
A33: Supervisors | B33: =B8 -> 10 | C33: =O8 -> 41.121307 | D33: =SUMIFS(Channels!$N:$N,Channels!$C:$C,A33) -> 39.749451 | E33: =IF(B33>0,D33/B33,0) -> 3.9749451 | F33: =Funnel!F61 -> 246 | G33: =Funnel!H61 -> 0.16715978 | H33: =_xlfn.MAXIFS(Channels!$P:$P,Channels!$C:$C,A33,Channels!$AI:$AI,">0") -> 1948.6055 | I33: No | J33: Yes (no recognition gate in brief) | K33: =IF(B33>0,(D33-SUMIFS(Channels!$N:$N,Channels!$A:$A,"I2-E",Channels!$C:$C,A33))/B33,0) -> 3.9749451 | L33: =IF(B33>0,K33,1000000000) -> 3.9749451
A35: ="Hardest role: "&Summary!C16&", the highest in column H. Why: industrial electricians are the scarcest trade in Brandenburg (KOFA 2026: 85.7% of vacancies have no suitable unemployed candidate vs 41.4% overall, https://www.kofa.de/media/Publikationen/Laendersteckbriefe/Brandenburg.pdf), and they have no Polish or foreign-trained route under the brief. Automation’s pool and channel coverage are tighter (column G: "&TEXT(G32,"0%")&" of reachable people vs "&TEXT(G30,"0%")&"; column E: "&TEXT(E32,"0.0")&"× vs "&TEXT(E30,"0.0")&"×), but it needs only "&B32&" hires and its last hire is cheaper, so it is watched in the weekly pool check rather than ranked hardest." -> Hardest role: Electricians (last hire costs €2,272), the highest in column H. Why: industrial electricians are the scarcest trade in Brandenburg (KOFA 2026: 85.7% of vacancies have no suitable unemployed candidate vs 41.4% overall, https://www.kofa.de/media/Publikationen/Laendersteckbriefe/Brandenburg.pdf), and they have no Polish or foreign-trained route under the brief. Automation’s pool and channel coverage are tighter (column G: 22% of reachable people vs 12%; column E: 3.2× vs 3.7×), but it needs only 15 hires and its last hire is cheaper, so it is watched in the weekly pool check rather than ranked hardest.
A39: Sensitivity: each assumption 30% worse (Part 1.4)
A40: Stress size: | B40: =Assumptions!$D$64 -> 0.3
A41: Assumption made 30% worse | B41: Qualified applicants needed | C41: Slot utilisation | D41: Hires possible before 31 Dec | E41: Hires lost vs 100 | F41: Spend needed (€, approx.: all variable spend scaled, channel caps ignored) | G41: Change in media | H41: Why
A42: Base case | B42: =O9 -> 307.97308 | C42: =IF(($B$22)>0,B42/($B$22),IF(B42>0,9.99,0)) -> 0.97991433 | D42: =MIN($B$9,IF(B42>0,$B$22/B42*$B$9,$B$9),MIN(B5,D30*1)+MIN(B6,D31*1)+MIN(B7,D32*1)+MIN(B8,D33*1)) -> 100 | E42: =$B$9-D42 -> 0 | F42: =Budget!$C$7*1 -> 102255.85 | G42: =IF(Budget!$C$7>0,F42/Budget!$C$7-1,0) -> 0 | H42: Plan as built.
A43: Qualified → signed (assessment pass rate) ×0.7 | B43: =O9/(1-$B$40) -> 439.96154 | C43: =IF(($B$22)>0,B43/($B$22),IF(B43>0,9.99,0)) -> 1.3998776 | D43: =MIN($B$9,IF(B43>0,$B$22/B43*$B$9,$B$9),MIN(B5,D30*(1-$B$40))+MIN(B6,D31*(1-$B$40))+MIN(B7,D32*(1-$B$40))+MIN(B8,D33*(1-$B$40))) -> 71.434816 | E43: =$B$9-D43 -> 28.565184 | F43: =Budget!$C$7*1/(1-$B$40) -> 146079.78 | G43: =IF(Budget!$C$7>0,F43/Budget!$C$7-1,0) -> 0.42857143 | H43: Each qualified applicant yields 30% fewer hires → 43% more qualified needed, but slots are fixed at 55/week.
A44: Offer acceptance ×0.7 | B44: =O9/(1-$B$40) -> 439.96154 | C44: =IF(($B$22)>0,B44/($B$22),IF(B44>0,9.99,0)) -> 1.3998776 | D44: =MIN($B$9,IF(B44>0,$B$22/B44*$B$9,$B$9),MIN(B5,D30*(1-$B$40))+MIN(B6,D31*(1-$B$40))+MIN(B7,D32*(1-$B$40))+MIN(B8,D33*(1-$B$40))) -> 71.434816 | E44: =$B$9-D44 -> 28.565184 | F44: =Budget!$C$7*1/(1-$B$40) -> 146079.78 | G44: =IF(Budget!$C$7>0,F44/Budget!$C$7-1,0) -> 0.42857143 | H44: Same arithmetic as pass rate: it also sits between the capacity limit and the hire.
A45: Application → qualified ×0.7 | B45: =O9 -> 307.97308 | C45: =IF(($B$22)>0,B45/($B$22),IF(B45>0,9.99,0)) -> 0.97991433 | D45: =MIN($B$9,IF(B45>0,$B$22/B45*$B$9,$B$9),MIN(B5,D30*(1-$B$40))+MIN(B6,D31*(1-$B$40))+MIN(B7,D32*(1-$B$40))+MIN(B8,D33*(1-$B$40))) -> 100 | E45: =$B$9-D45 -> 0 | F45: =Budget!$C$7*1/(1-$B$40) -> 146079.78 | G45: =IF(Budget!$C$7>0,F45/Budget!$C$7-1,0) -> 0.42857143 | H45: Costs 43% more per qualified; slots unaffected; channels run out sooner (electricians first).
A46: Cost per application ×1.3 | B46: =O9 -> 307.97308 | C46: =IF(($B$22)>0,B46/($B$22),IF(B46>0,9.99,0)) -> 0.97991433 | D46: =MIN($B$9,IF(B46>0,$B$22/B46*$B$9,$B$9),MIN(B5,D30*1)+MIN(B6,D31*1)+MIN(B7,D32*1)+MIN(B8,D33*1)) -> 100 | E46: =$B$9-D46 -> 0 | F46: =Budget!$C$7*(1+$B$40) -> 132932.6 | G46: =IF(Budget!$C$7>0,F46/Budget!$C$7-1,0) -> 0.3 | H46: Pure money: +30% media, no effect on hires if the money is there.
A47: Recruiter capacity ×0.7 (≈38/week), given in the brief, shown for context | B47: =O9 -> 307.97308 | C47: =IF(($B$22*(1-$B$40))>0,B47/($B$22*(1-$B$40)),IF(B47>0,9.99,0)) -> 1.3998776 | D47: =MIN($B$9,IF(B47>0,$B$22*(1-$B$40)/B47*$B$9,$B$9),MIN(B5,D30*1)+MIN(B6,D31*1)+MIN(B7,D32*1)+MIN(B8,D33*1)) -> 71.434816 | E47: =$B$9-D47 -> 28.565184 | F47: =Budget!$C$7*1 -> 102255.85 | G47: =IF(Budget!$C$7>0,F47/Budget!$C$7-1,0) -> 0 | H47: Fewer slots: hires capped by capacity. Not ranked: 55/week is given, not assumed.
A49: Most sensitive assumption (largest hire loss; capacity excluded as it is given): | D49: =INDEX(A43:A46,MATCH(MAX(E43:E46),E43:E46,0)) -> Qualified → signed (assessment pass rate) ×0.7
A50: =IF(AND(E43>0,ROUND(E43,6)=ROUND(E44,6)),"Pass rate and acceptance tie ("&TEXT(E43,"0")&" hires lost each). I name the pass rate: it depends on this plant’s own test, so it is the least known, and it can only be read after interviews (week-2 check). Acceptance can be protected with fast offers. ","")&"Why it matters: assessment capacity, not money, is the limit, so a lower pass rate or acceptance can’t be fixed by spending more; a lower share qualified or dearer clicks only cost money." -> Pass rate and acceptance tie (29 hires lost each). I name the pass rate: it depends on this plant’s own test, so it is the least known, and it can only be read after interviews (week-2 check). Acceptance can be protected with fast offers. Why it matters: assessment capacity, not money, is the limit, so a lower pass rate or acceptance can’t be fixed by spending more; a lower share qualified or dearer clicks only cost money.
A54: Talent-pool sanity check (Part 2.2): can the channels plausibly deliver the qualified applicants we plan?
A57: Role | B57: Employed within 75 km | C57: Share in market / persuadable | D57: Local reachable | E57: Relocators | F57: Reachable qualified pool | G57: Qualified applicants in plan from this pool (excl. I2) | H57: Plan ÷ pool | I57: Max qualified all channels could deliver (excl. I2) | J57: Channel max ÷ pool | K57: Read-out
A58: Electricians | B58: =Assumptions!$D$68 -> 4800 | C58: =Assumptions!$D$72 -> 0.11 | D58: =B58*C58 -> 528 | E58: =Assumptions!$D$76 -> 41 | F58: =D58+E58 -> 569 | G58: =Funnel!O5-SUMIFS(Channels!$V:$V,Channels!$A:$A,"I2-E",Channels!$C:$C,A58) -> 66.753095 | H58: =IF(F58>0,G58/F58,0) -> 0.11731651 | I58: =SUMIFS(Channels!$K:$K,Channels!$C:$C,A58)-SUMIFS(Channels!$K:$K,Channels!$A:$A,"I2-E",Channels!$C:$C,A58) -> 321.425 | J58: =IF(F58>0,I58/F58,0) -> 0.56489455 | K58: =IF(H58>Assumptions!$D$99,"Very hard",IF(H58>Assumptions!$D$100,"Tight","Comfortable")) -> Comfortable
A59: Mechatronics | B59: =Assumptions!$D$69 -> 26400 | C59: =Assumptions!$D$73 -> 0.11 | D59: =B59*C59 -> 2904 | E59: =Assumptions!$D$77 -> 28 | F59: =D59+E59 -> 2932 | G59: =Funnel!O6-SUMIFS(Channels!$V:$V,Channels!$A:$A,"I2-E",Channels!$C:$C,A59) -> 118.77312 | H59: =IF(F59>0,G59/F59,0) -> 0.04050925 | I59: =SUMIFS(Channels!$K:$K,Channels!$C:$C,A59)-SUMIFS(Channels!$K:$K,Channels!$A:$A,"I2-E",Channels!$C:$C,A59) -> 1484.11 | J59: =IF(F59>0,I59/F59,0) -> 0.50617667 | K59: =IF(H59>Assumptions!$D$99,"Very hard",IF(H59>Assumptions!$D$100,"Tight","Comfortable")) -> Comfortable
A60: Automation | B60: =Assumptions!$D$70 -> 2000 | C60: =Assumptions!$D$74 -> 0.11 | D60: =B60*C60 -> 220 | E60: =Assumptions!$D$78 -> 16 | F60: =D60+E60 -> 236 | G60: =Funnel!O7-SUMIFS(Channels!$V:$V,Channels!$A:$A,"I2-E",Channels!$C:$C,A60) -> 51.825553 | H60: =IF(F60>0,G60/F60,0) -> 0.2195998 | I60: =SUMIFS(Channels!$K:$K,Channels!$C:$C,A60)-SUMIFS(Channels!$K:$K,Channels!$A:$A,"I2-E",Channels!$C:$C,A60) -> 167.905 | J60: =IF(F60>0,I60/F60,0) -> 0.71146186 | K60: =IF(H60>Assumptions!$D$99,"Very hard",IF(H60>Assumptions!$D$100,"Tight","Comfortable")) -> Tight
A61: Supervisors | B61: =Assumptions!$D$71 -> 2200 | C61: =Assumptions!$D$75 -> 0.11 | D61: =B61*C61 -> 242 | E61: =Assumptions!$D$79 -> 4 | F61: =D61+E61 -> 246 | G61: =Funnel!O8-SUMIFS(Channels!$V:$V,Channels!$A:$A,"I2-E",Channels!$C:$C,A61) -> 41.121307 | H61: =IF(F61>0,G61/F61,0) -> 0.16715978 | I61: =SUMIFS(Channels!$K:$K,Channels!$C:$C,A61)-SUMIFS(Channels!$K:$K,Channels!$A:$A,"I2-E",Channels!$C:$C,A61) -> 166.119 | J61: =IF(F61>0,I61/F61,0) -> 0.67528049 | K61: =IF(H61>Assumptions!$D$99,"Very hard",IF(H61>Assumptions!$D$100,"Tight","Comfortable")) -> Tight
A63: Channel max can exceed the pool because the same people apply via several channels. Construction electricians (I2) are a separate pool and excluded here.

Sheet Initiatives
A1: Part 3 — New sources beyond the usual paid channels (maths feeds the Channels tab)
A2: How: people reachable × share who apply = applications; × share qualified × qualified → signed = hires; cost ÷ hires = cost per hire.
A3: I1 · Talent rediscovery (past applicants in client ATS) + employee referral sprint — built for electricians, used for all roles
A4: Line | B4: Electricians | C4: Mechatronics | D4: Automation | E4: Supervisors | F4: Total
A5: I1a Past qualified applicants in ATS | B5: =Assumptions!$D$153 -> 65 | C5: =Assumptions!$D$154 -> 76 | D5: =Assumptions!$D$155 -> 38 | E5: =Assumptions!$D$156 -> 32 | F5: =SUM(B5:E5) -> 211
A6: I1a Re-application rate | B6: =Assumptions!$D$157 -> 0.12 | C6: =Assumptions!$D$157 -> 0.12 | D6: =Assumptions!$D$157 -> 0.12 | E6: =Assumptions!$D$157 -> 0.12
A7: I1a Re-applications (max) | B7: =B5*B6 -> 7.8 | C7: =C5*C6 -> 9.12 | D7: =D5*D6 -> 4.56 | E7: =E5*E6 -> 3.84 | F7: =SUM(B7:E7) -> 25.32
A8: I1a Share qualified | B8: =Assumptions!$D$158 -> 0.5 | C8: =Assumptions!$D$158 -> 0.5 | D8: =Assumptions!$D$158 -> 0.5 | E8: =Assumptions!$D$158 -> 0.5
A9: I1 Qualified → signed (role × adj.) | B9: =Funnel!$G$5*Assumptions!$D$166 -> 0.36225 | C9: =Funnel!$G$6*Assumptions!$D$166 -> 0.4269375 | D9: =Funnel!$G$7*Assumptions!$D$166 -> 0.326025 | E9: =Funnel!$G$8*Assumptions!$D$166 -> 0.2737
A10: I1a Messaging cost (records × €/contact) | B10: =B5*Assumptions!$D$164 -> 19.5 | C10: =C5*Assumptions!$D$164 -> 22.8 | D10: =D5*Assumptions!$D$164 -> 11.4 | E10: =E5*Assumptions!$D$164 -> 9.6 | F10: =SUM(B10:E10) -> 63.3
A11: I1a Cost per application (→ Channels) | B11: =IF(B7>0,B10/B7,0) -> 2.5 | C11: =IF(C7>0,C10/C7,0) -> 2.5 | D11: =IF(D7>0,D10/D7,0) -> 2.5 | E11: =IF(E7>0,E10/E7,0) -> 2.5 | G11: ="≈"&TEXT(B11,"€0.00")&" per application: messaging is nearly free; the scarce input is the client’s ATS export." -> ≈€2.50 per application: messaging is nearly free; the scarce input is the client’s ATS export.
A12: I1a Hires if fully used | B12: =B7*B8*B9 -> 1.412775 | C12: =C7*C8*C9 -> 1.946835 | D12: =D7*D8*D9 -> 0.743337 | E12: =E7*E8*E9 -> 0.525504 | F12: =SUM(B12:E12) -> 4.628451
A13: I1b Referral applications (max) | B13: =Assumptions!$D$159 -> 20 | C13: =Assumptions!$D$160 -> 26 | D13: =Assumptions!$D$161 -> 11 | E13: =Assumptions!$D$162 -> 9 | F13: =SUM(B13:E13) -> 66
A14: I1b Share qualified | B14: =Assumptions!$D$163 -> 0.45 | C14: =Assumptions!$D$163 -> 0.45 | D14: =Assumptions!$D$163 -> 0.45 | E14: =Assumptions!$D$163 -> 0.45
A15: I1b Hires if fully used | B15: =B13*B14*B9 -> 3.26025 | C15: =C13*C14*C9 -> 4.9951688 | D15: =D13*D14*D9 -> 1.6138237 | E15: =E13*E14*E9 -> 1.108485 | F15: =SUM(B15:E15) -> 10.977728
A16: I1b Referral bonuses at full use (hires × bonus) | B16: =B15*Assumptions!$D$165 -> 3260.25 | C16: =C15*Assumptions!$D$165 -> 4995.1687 | D16: =D15*Assumptions!$D$165 -> 1613.8238 | E16: =E15*Assumptions!$D$165 -> 1108.485 | F16: =SUM(B16:E16) -> 10977.728
A17: I1b Expected bonus cost per application (→ Channels) | B17: =IF(B13>0,B16/B13,0) -> 163.0125 | C17: =IF(C13>0,C16/C13,0) -> 192.12187 | D17: =IF(D13>0,D16/D13,0) -> 146.71125 | E17: =IF(E13>0,E16/E13,0) -> 123.165 | G17: Bonus is only paid when a referred hire signs; shown per application so it ranks against paid channels.
A18: I1 Total hires if fully used | B18: =B12+B15 -> 4.673025 | C18: =C12+C15 -> 6.9420037 | D18: =D12+D15 -> 2.3571607 | E18: =E12+E15 -> 1.633989 | F18: =SUM(B18:E18) -> 15.606179
A19: I1 Total cost if fully used | B19: =B10+B16 -> 3279.75 | C19: =C10+C16 -> 5017.9688 | D19: =D10+D16 -> 1625.2238 | E19: =E10+E16 -> 1118.085 | F19: =SUM(B19:E19) -> 11041.028
A20: I1 Cost per hire | B20: =IF(B18>0,B19/B18,0) -> 701.8473 | C20: =IF(C18>0,C19/C18,0) -> 722.84155 | D20: =IF(D18>0,D19/D18,0) -> 689.48363 | E20: =IF(E18>0,E19/E18,0) -> 684.26715 | F20: =IF(F18>0,F19/F18,0) -> 707.47797
A23: I2 · 'Vom Handwerk in die Industrie' — construction electricians → plant maintenance (electricians only)
A24: Construction/Handwerk electricians within 75 km | B24: =Assumptions!$D$167 -> 10000
A25: Share who apply | B25: =Assumptions!$D$168 -> 0.0118
A26: Max applications | B26: =B24*B25 -> 118
A27: Cost per application | B27: =Assumptions!$D$169 -> 84
A28: Share qualified (client accepts profile) | B28: =Assumptions!$D$170 -> 0.25
A29: Qualified | B29: =B26*B28 -> 29.5
A30: Qualified → signed (electrician rate × I2A adjustment) | B30: =Funnel!$G$5*Assumptions!$D$171 -> 0.2835
A31: Expected hires if fully used | B31: =B29*B30 -> 8.36325
A32: Media at full use | B32: =B26*B27 -> 9912
A33: Fixed set-up | B33: =Assumptions!$D$172 -> 1200
A34: Cost per hire at full use | B34: =IF(B31>0,(B32+B33)/B31,0) -> 1328.6701
A37: I3 · Polish border corridor with a remote Polish-speaking pre-screener (mechatronics only, ≤40% of those hires)
A38: All-in cost per application (ads + pre-screen call) (→ Channels) | B38: =B44+B45 -> 18.75
A39: Share qualified after pre-screen | B39: =Assumptions!$D$174 -> 0.14
A40: Max applications | B40: =Assumptions!$D$175 -> 350
A41: Qualified → signed (mechatronics rate × I3A adjustment) | B41: =Funnel!$G$6*Assumptions!$D$176 -> 0.37125
A42: Hire cap from the 40% rule | B42: =Assumptions!$D$10*Assumptions!$D$12 -> 18
A43: Hires if fully used (capped) | B43: =MIN(B40*B39*B41,B42) -> 18
A44: Ad cost per application (Pracuj.pl, OLX Praca, PL-geo Meta) | B44: =Assumptions!$D$173 -> 14
A45: Pre-screen cost per applicant (minutes ÷ 60 × hourly rate) | B45: =Assumptions!$D$177/60*Assumptions!$D$178 -> 4.75
A46: Fixed cost: translation | B46: =Assumptions!$D$179 -> 400
A47: Applications needed to hit the cap | B47: =IF(B41*B39>0,B43/B41/B39,0) -> 346.32035
A48: Cost per hire at cap (incl. fixed) | B48: =IF(B43>0,(B47*B38+B46)/B43,0) -> 382.97258
A49: ="Polish supply check: the border regions have ~"&TEXT(Assumptions!$D$124*Assumptions!$D$121,"#,##0")&" maintenance-type workers (Eurostat 2025: "&TEXT(Assumptions!$D$124,"#,##0")&" industry workers × the German BA maintenance share "&TEXT(Assumptions!$D$121,"0.0%")&", applied to Poland as my estimate; an upper bound, since whole regions and all industry staff are counted). The plan needs "&TEXT(B47,"0")&" applications = "&TEXT(B47/(Assumptions!$D$124*Assumptions!$D$121),"0.0%")&" of them, vs the "&TEXT(Assumptions!$D$168,"0.0%")&" response assumed for construction electricians (I2). So the corridor needs a stronger response (German pay is the pull); at I2’s rate it brings ~"&TEXT(Assumptions!$D$124*Assumptions!$D$121*Assumptions!$D$168,"0")&" applications. The 9 Nov test decides; if it fails, the budget rises (slide 7)." -> Polish supply check: the border regions have ~18,525 maintenance-type workers (Eurostat 2025: 237,500 industry workers × the German BA maintenance share 7.8%, applied to Poland as my estimate; an upper bound, since whole regions and all industry staff are counted). The plan needs 346 applications = 1.9% of them, vs the 1.2% response assumed for construction electricians (I2). So the corridor needs a stronger response (German pay is the pull); at I2’s rate it brings ~219 applications. The 9 Nov test decides; if it fails, the budget rises (slide 7).
A51: Two-week tests: bars are set from each initiative's planned volume in its own 14-day window (inputs TP1–TK2 on Assumptions)
A52: Initiative | B52: Test window (14 days from launch) | C52: Share of planned volume in window (days of each spend week inside the window) | D52: Test budget € | E52: Planned qualified in window | F52: Planned cost per qualified | G52: PASS if qualified ≥ | H52: …and cost per qualified ≤ | I52: KILL if qualified < | J52: …or cost per qualified > | K52: Other conditions
A53: I1 Rediscovery + referrals | B53: Wed 21 Oct – Tue 3 Nov (waves 1–3) | C53: =(Assumptions!$D$93+Assumptions!$D$94) -> 0.89 | D53: =F10 -> 63.3 | E53: =(SUMIFS(Channels!$V:$V,Channels!$A:$A,"I1a-E")+SUMIFS(Channels!$V:$V,Channels!$A:$A,"I1a-M")+SUMIFS(Channels!$V:$V,Channels!$A:$A,"I1a-A")+SUMIFS(Channels!$V:$V,Channels!$A:$A,"I1a-S"))*(Assumptions!$D$93+Assumptions!$D$94)+(SUMIFS(Channels!$V:$V,Channels!$A:$A,"I1b-E")+SUMIFS(Channels!$V:$V,Channels!$A:$A,"I1b-M")+SUMIFS(Channels!$V:$V,Channels!$A:$A,"I1b-A")+SUMIFS(Channels!$V:$V,Channels!$A:$A,"I1b-S"))*(Weekly!$D$4+Weekly!$D$5) -> 24.5433 | F53: n/a (≈€8) | G53: =MAX(1,ROUNDDOWN(E53*Assumptions!$D$89,0)) -> 14 | H53: – | I53: =MIN(G53,MAX(1,ROUNDUP(E53*Assumptions!$D$91,0))) -> 8 | J53: – | K53: A kill means no more re-contact waves; the referral bonus stays live (paid only on a signed hire).
A54: I2 Handwerk → Industrie | B54: Fri 23 Oct – Thu 5 Nov (read Mon 9 Nov) | C54: =(Weekly!$AB$4+Weekly!$AB$5+Weekly!$AB$6*3/7) -> 0.44018506 | D54: =B33+SUMIFS(Channels!$X:$X,Channels!$A:$A,"I2-E")*C54 -> 5563.1143 | E54: =SUMIFS(Channels!$V:$V,Channels!$A:$A,"I2-E")*C54 -> 12.985459 | F54: =IF(B28>0,B27/B28,0) -> 336 | G54: =MAX(1,ROUNDDOWN(E54*Assumptions!$D$89,0)) -> 7 | H54: =ROUND(F54*Assumptions!$D$90/10,0)*10 -> 500 | I54: =MIN(G54,MAX(1,ROUNDUP(E54*Assumptions!$D$91,0))) -> 4 | J54: =MAX(H54,ROUND(F54*Assumptions!$D$92/10,0)*10) -> 670 | K54: Also stop at once if the client rejects the profile; the money moves to programmatic electricians.
A55: I3 Polish corridor | B55: Tue 27 Oct – Mon 9 Nov (freelancer starts 27 Oct) | C55: =(Weekly!$AC$5+Weekly!$AC$6) -> 0.42690058 | D55: =B46+SUMIFS(Channels!$X:$X,Channels!$A:$A,"I3-M")*C55 -> 3172.0817 | E55: =SUMIFS(Channels!$V:$V,Channels!$A:$A,"I3-M")*C55 -> 20.69821 | F55: =IF(B39>0,B38/B39,0) -> 133.92857 | G55: =MAX(1,ROUNDDOWN(E55*Assumptions!$D$89,0)) -> 12 | H55: =ROUND(F55*Assumptions!$D$90/10,0)*10 -> 200 | I55: =MIN(G55,MAX(1,ROUNDUP(E55*Assumptions!$D$91,0))) -> 7 | J55: =MAX(H55,ROUND(F55*Assumptions!$D$92/10,0)*10) -> 270 | K55: Also stop if far fewer than planned pass the language call. The freelancer is paid hourly, so stopping costs little.
A57: Who does what is on deck slide 7. I2 and I3 are read on Mon 9 Nov, I1 on Mon 2 Nov.

Sheet Channels
A1: Part 2 — Channel × role economics and allocation (cheapest cost-per-hire first, until each role's openings are covered)
A2: How hires are bought: within each role, channels are used cheapest cost per hire first, each up to its volume cap, until openings are filled.
A3: Every paid channel first gets a €750 test in weeks 1–2; its hires count. Then only the remaining need is bought.
A4: ID | B4: Channel | C4: Role | D4: Type | E4: Basis | F4: Unit cost € | G4: Click→apply / apps per slot | H4: Cost per application | I4: Share qualified | J4: Max applications | K4: Qualified capacity | L4: Qualified → signed | M4: Downstream adj. | N4: Hire capacity | O4: Cost per qualified | P4: Cost per hire at capacity (incl. fixed) | Q4: Sort key | R4: Rank in role | S4: Remaining capacity of cheaper channels | T4: Need after all tests (openings – test hires) | U4: Hires (test + allocated) | V4: Qualified (total) | W4: Applications (total) | X4: Media € (incl. test tranche) | Y4: Fixed € | Z4: Test tranche wk 1–2 € | AA4: Total € | AB4: Planned cost per hire | AC4: Rank overall | AD4: Status | AE4: Test applications | AF4: Test qualified | AG4: Test hires | AH4: Hire capacity left after test | AI4: Hires allocated beyond test
A5: =Assumptions!A130 -> C01 | B5: =Assumptions!B130 -> Organic (Tesla careers, BA Jobbörse, Google for Jobs) | C5: =Assumptions!C130 -> Electricians | D5: Channel | E5: =Assumptions!D130 -> Free | F5: =Assumptions!E130 -> 0 | G5: =IF(E5="Free","",Assumptions!F130) | H5: =MAX(0,IF(OR(E5="CPC",E5="Slot"),IF(N(G5)>0,F5/G5,0),F5)) -> 0 | I5: =Assumptions!G130 -> 0.175 | J5: =IF(AND(OR(E5="CPC",E5="Slot"),NOT(N(G5)>0)),0,IF(E5="Slot",Assumptions!H130*G5,Assumptions!H130)) -> 105 | K5: =J5*I5 -> 18.375 | L5: =INDEX(Funnel!$G$5:$G$8,MATCH(C5,Funnel!$A$5:$A$8,0))*M5 -> 0.315 | M5: =Assumptions!I130 -> 1 | N5: =K5*L5 -> 5.788125 | O5: =IF(I5>0,H5/I5,0) -> 0 | P5: =IF(N5>0,(N5/L5/I5*H5+Assumptions!J130)/N5,0) -> 0 | Q5: =P5+ROW()/1000000 -> 5e-06 | R5: =SUMPRODUCT(($C$5:$C$34=C5)*($Q$5:$Q$34<Q5))+1 -> 1 | S5: =SUMPRODUCT(($C$5:$C$34=C5)*($Q$5:$Q$34<Q5)*$AH$5:$AH$34) -> 0 | T5: =INDEX(Funnel!$B$5:$B$8,MATCH(C5,Funnel!$A$5:$A$8,0))-SUMIFS($AG$5:$AG$34,$C$5:$C$34,C5) -> 29.150585 | U5: =AG5+AI5 -> 5.788125 | V5: =IF(L5>0,U5/L5,0) -> 18.375 | W5: =IF(I5>0,V5/I5,0) -> 105 | X5: =IF(E5="Slot",IF(N(G5)>0,ROUNDUP(W5/G5,0)*MAX(0,F5),0),W5*H5) -> 0 | Y5: =IF(U5>0,Assumptions!J130,0) -> 0 | Z5: =IF(AND(D5="Channel",OR(E5="CPC",E5="CPA"),INDEX(Funnel!$B$5:$B$8,MATCH(C5,Funnel!$A$5:$A$8,0))>0),MIN(Assumptions!$D$49,J5*H5,IF(I5*L5>0,INDEX(Funnel!$B$5:$B$8,MATCH(C5,Funnel!$A$5:$A$8,0))/SUMPRODUCT(($C$5:$C$34=C5)*($D$5:$D$34="Channel")*(($E$5:$E$34="CPC")+($E$5:$E$34="CPA")))/(I5*L5)*H5,0)),0) -> 0 | AA5: =X5+Y5 -> 0 | AB5: =IF(U5>0,(X5+Y5)/U5,"–") -> 0 | AC5: =SUMPRODUCT(--($Q$5:$Q$34<Q5))+1 -> 1 | AD5: =IF(AND(AH5>0,AI5>=AH5*0.999),"Used to capacity",IF(AI5>0,"Marginal (fills the gap)",IF(Z5>0,"Test only (wk 1–2)","Not used"))) -> Used to capacity | AE5: =IF(H5>0,Z5/H5,0) -> 0 | AF5: =AE5*I5 -> 0 | AG5: =AF5*L5 -> 0 | AH5: =MAX(0,N5-AG5) -> 5.788125 | AI5: =MIN(AH5,MAX(0,T5-S5)) -> 5.788125
A6: =Assumptions!A131 -> C02 | B6: =Assumptions!B131 -> Organic (Tesla careers, BA Jobbörse, Google for Jobs) | C6: =Assumptions!C131 -> Mechatronics | D6: Channel | E6: =Assumptions!D131 -> Free | F6: =Assumptions!E131 -> 0 | G6: =IF(E6="Free","",Assumptions!F131) | H6: =MAX(0,IF(OR(E6="CPC",E6="Slot"),IF(N(G6)>0,F6/G6,0),F6)) -> 0 | I6: =Assumptions!G131 -> 0.175 | J6: =IF(AND(OR(E6="CPC",E6="Slot"),NOT(N(G6)>0)),0,IF(E6="Slot",Assumptions!H131*G6,Assumptions!H131)) -> 158 | K6: =J6*I6 -> 27.65 | L6: =INDEX(Funnel!$G$5:$G$8,MATCH(C6,Funnel!$A$5:$A$8,0))*M6 -> 0.37125 | M6: =Assumptions!I131 -> 1 | N6: =K6*L6 -> 10.265063 | O6: =IF(I6>0,H6/I6,0) -> 0 | P6: =IF(N6>0,(N6/L6/I6*H6+Assumptions!J131)/N6,0) -> 0 | Q6: =P6+ROW()/1000000 -> 6e-06 | R6: =SUMPRODUCT(($C$5:$C$34=C6)*($Q$5:$Q$34<Q6))+1 -> 1 | S6: =SUMPRODUCT(($C$5:$C$34=C6)*($Q$5:$Q$34<Q6)*$AH$5:$AH$34) -> 0 | T6: =INDEX(Funnel!$B$5:$B$8,MATCH(C6,Funnel!$A$5:$A$8,0))-SUMIFS($AG$5:$AG$34,$C$5:$C$34,C6) -> 43.998904 | U6: =AG6+AI6 -> 10.265063 | V6: =IF(L6>0,U6/L6,0) -> 27.65 | W6: =IF(I6>0,V6/I6,0) -> 158 | X6: =IF(E6="Slot",IF(N(G6)>0,ROUNDUP(W6/G6,0)*MAX(0,F6),0),W6*H6) -> 0 | Y6: =IF(U6>0,Assumptions!J131,0) -> 0 | Z6: =IF(AND(D6="Channel",OR(E6="CPC",E6="CPA"),INDEX(Funnel!$B$5:$B$8,MATCH(C6,Funnel!$A$5:$A$8,0))>0),MIN(Assumptions!$D$49,J6*H6,IF(I6*L6>0,INDEX(Funnel!$B$5:$B$8,MATCH(C6,Funnel!$A$5:$A$8,0))/SUMPRODUCT(($C$5:$C$34=C6)*($D$5:$D$34="Channel")*(($E$5:$E$34="CPC")+($E$5:$E$34="CPA")))/(I6*L6)*H6,0)),0) -> 0 | AA6: =X6+Y6 -> 0 | AB6: =IF(U6>0,(X6+Y6)/U6,"–") -> 0 | AC6: =SUMPRODUCT(--($Q$5:$Q$34<Q6))+1 -> 2 | AD6: =IF(AND(AH6>0,AI6>=AH6*0.999),"Used to capacity",IF(AI6>0,"Marginal (fills the gap)",IF(Z6>0,"Test only (wk 1–2)","Not used"))) -> Used to capacity | AE6: =IF(H6>0,Z6/H6,0) -> 0 | AF6: =AE6*I6 -> 0 | AG6: =AF6*L6 -> 0 | AH6: =MAX(0,N6-AG6) -> 10.265063 | AI6: =MIN(AH6,MAX(0,T6-S6)) -> 10.265063
A7: =Assumptions!A132 -> C03 | B7: =Assumptions!B132 -> Organic (Tesla careers, BA Jobbörse, Google for Jobs) | C7: =Assumptions!C132 -> Automation | D7: Channel | E7: =Assumptions!D132 -> Free | F7: =Assumptions!E132 -> 0 | G7: =IF(E7="Free","",Assumptions!F132) | H7: =MAX(0,IF(OR(E7="CPC",E7="Slot"),IF(N(G7)>0,F7/G7,0),F7)) -> 0 | I7: =Assumptions!G132 -> 0.175 | J7: =IF(AND(OR(E7="CPC",E7="Slot"),NOT(N(G7)>0)),0,IF(E7="Slot",Assumptions!H132*G7,Assumptions!H132)) -> 53 | K7: =J7*I7 -> 9.275 | L7: =INDEX(Funnel!$G$5:$G$8,MATCH(C7,Funnel!$A$5:$A$8,0))*M7 -> 0.2835 | M7: =Assumptions!I132 -> 1 | N7: =K7*L7 -> 2.6294625 | O7: =IF(I7>0,H7/I7,0) -> 0 | P7: =IF(N7>0,(N7/L7/I7*H7+Assumptions!J132)/N7,0) -> 0 | Q7: =P7+ROW()/1000000 -> 7e-06 | R7: =SUMPRODUCT(($C$5:$C$34=C7)*($Q$5:$Q$34<Q7))+1 -> 1 | S7: =SUMPRODUCT(($C$5:$C$34=C7)*($Q$5:$Q$34<Q7)*$AH$5:$AH$34) -> 0 | T7: =INDEX(Funnel!$B$5:$B$8,MATCH(C7,Funnel!$A$5:$A$8,0))-SUMIFS($AG$5:$AG$34,$C$5:$C$34,C7) -> 13.99664 | U7: =AG7+AI7 -> 2.6294625 | V7: =IF(L7>0,U7/L7,0) -> 9.275 | W7: =IF(I7>0,V7/I7,0) -> 53 | X7: =IF(E7="Slot",IF(N(G7)>0,ROUNDUP(W7/G7,0)*MAX(0,F7),0),W7*H7) -> 0 | Y7: =IF(U7>0,Assumptions!J132,0) -> 0 | Z7: =IF(AND(D7="Channel",OR(E7="CPC",E7="CPA"),INDEX(Funnel!$B$5:$B$8,MATCH(C7,Funnel!$A$5:$A$8,0))>0),MIN(Assumptions!$D$49,J7*H7,IF(I7*L7>0,INDEX(Funnel!$B$5:$B$8,MATCH(C7,Funnel!$A$5:$A$8,0))/SUMPRODUCT(($C$5:$C$34=C7)*($D$5:$D$34="Channel")*(($E$5:$E$34="CPC")+($E$5:$E$34="CPA")))/(I7*L7)*H7,0)),0) -> 0 | AA7: =X7+Y7 -> 0 | AB7: =IF(U7>0,(X7+Y7)/U7,"–") -> 0 | AC7: =SUMPRODUCT(--($Q$5:$Q$34<Q7))+1 -> 3 | AD7: =IF(AND(AH7>0,AI7>=AH7*0.999),"Used to capacity",IF(AI7>0,"Marginal (fills the gap)",IF(Z7>0,"Test only (wk 1–2)","Not used"))) -> Used to capacity | AE7: =IF(H7>0,Z7/H7,0) -> 0 | AF7: =AE7*I7 -> 0 | AG7: =AF7*L7 -> 0 | AH7: =MAX(0,N7-AG7) -> 2.6294625 | AI7: =MIN(AH7,MAX(0,T7-S7)) -> 2.6294625
A8: =Assumptions!A133 -> C04 | B8: =Assumptions!B133 -> Organic (Tesla careers, BA Jobbörse, Google for Jobs) | C8: =Assumptions!C133 -> Supervisors | D8: Channel | E8: =Assumptions!D133 -> Free | F8: =Assumptions!E133 -> 0 | G8: =IF(E8="Free","",Assumptions!F133) | H8: =MAX(0,IF(OR(E8="CPC",E8="Slot"),IF(N(G8)>0,F8/G8,0),F8)) -> 0 | I8: =Assumptions!G133 -> 0.161 | J8: =IF(AND(OR(E8="CPC",E8="Slot"),NOT(N(G8)>0)),0,IF(E8="Slot",Assumptions!H133*G8,Assumptions!H133)) -> 35 | K8: =J8*I8 -> 5.635 | L8: =INDEX(Funnel!$G$5:$G$8,MATCH(C8,Funnel!$A$5:$A$8,0))*M8 -> 0.238 | M8: =Assumptions!I133 -> 1 | N8: =K8*L8 -> 1.34113 | O8: =IF(I8>0,H8/I8,0) -> 0 | P8: =IF(N8>0,(N8/L8/I8*H8+Assumptions!J133)/N8,0) -> 0 | Q8: =P8+ROW()/1000000 -> 8e-06 | R8: =SUMPRODUCT(($C$5:$C$34=C8)*($Q$5:$Q$34<Q8))+1 -> 1 | S8: =SUMPRODUCT(($C$5:$C$34=C8)*($Q$5:$Q$34<Q8)*$AH$5:$AH$34) -> 0 | T8: =INDEX(Funnel!$B$5:$B$8,MATCH(C8,Funnel!$A$5:$A$8,0))-SUMIFS($AG$5:$AG$34,$C$5:$C$34,C8) -> 9.2250591 | U8: =AG8+AI8 -> 1.34113 | V8: =IF(L8>0,U8/L8,0) -> 5.635 | W8: =IF(I8>0,V8/I8,0) -> 35 | X8: =IF(E8="Slot",IF(N(G8)>0,ROUNDUP(W8/G8,0)*MAX(0,F8),0),W8*H8) -> 0 | Y8: =IF(U8>0,Assumptions!J133,0) -> 0 | Z8: =IF(AND(D8="Channel",OR(E8="CPC",E8="CPA"),INDEX(Funnel!$B$5:$B$8,MATCH(C8,Funnel!$A$5:$A$8,0))>0),MIN(Assumptions!$D$49,J8*H8,IF(I8*L8>0,INDEX(Funnel!$B$5:$B$8,MATCH(C8,Funnel!$A$5:$A$8,0))/SUMPRODUCT(($C$5:$C$34=C8)*($D$5:$D$34="Channel")*(($E$5:$E$34="CPC")+($E$5:$E$34="CPA")))/(I8*L8)*H8,0)),0) -> 0 | AA8: =X8+Y8 -> 0 | AB8: =IF(U8>0,(X8+Y8)/U8,"–") -> 0 | AC8: =SUMPRODUCT(--($Q$5:$Q$34<Q8))+1 -> 4 | AD8: =IF(AND(AH8>0,AI8>=AH8*0.999),"Used to capacity",IF(AI8>0,"Marginal (fills the gap)",IF(Z8>0,"Test only (wk 1–2)","Not used"))) -> Used to capacity | AE8: =IF(H8>0,Z8/H8,0) -> 0 | AF8: =AE8*I8 -> 0 | AG8: =AF8*L8 -> 0 | AH8: =MAX(0,N8-AG8) -> 1.34113 | AI8: =MIN(AH8,MAX(0,T8-S8)) -> 1.34113
A9: =Assumptions!A134 -> C05 | B9: =Assumptions!B134 -> Programmatic job ads (Joveo: Indeed, Jooble, Talent.com, Kimeta, meinestadt…) | C9: =Assumptions!C134 -> Electricians | D9: Channel | E9: =Assumptions!D134 -> CPA | F9: =Assumptions!E134 -> 161 | G9: =IF(E9="Free","",Assumptions!F134) -> 0 | H9: =MAX(0,IF(OR(E9="CPC",E9="Slot"),IF(N(G9)>0,F9/G9,0),F9)) -> 161 | I9: =Assumptions!G134 -> 0.225 | J9: =IF(AND(OR(E9="CPC",E9="Slot"),NOT(N(G9)>0)),0,IF(E9="Slot",Assumptions!H134*G9,Assumptions!H134)) -> 910 | K9: =J9*I9 -> 204.75 | L9: =INDEX(Funnel!$G$5:$G$8,MATCH(C9,Funnel!$A$5:$A$8,0))*M9 -> 0.315 | M9: =Assumptions!I134 -> 1 | N9: =K9*L9 -> 64.49625 | O9: =IF(I9>0,H9/I9,0) -> 715.55556 | P9: =IF(N9>0,(N9/L9/I9*H9+Assumptions!J134)/N9,0) -> 2271.6049 | Q9: =P9+ROW()/1000000 -> 2271.6049 | R9: =SUMPRODUCT(($C$5:$C$34=C9)*($Q$5:$Q$34<Q9))+1 -> 6 | S9: =SUMPRODUCT(($C$5:$C$34=C9)*($Q$5:$Q$34<Q9)*$AH$5:$AH$34) -> 20.5254 | T9: =INDEX(Funnel!$B$5:$B$8,MATCH(C9,Funnel!$A$5:$A$8,0))-SUMIFS($AG$5:$AG$34,$C$5:$C$34,C9) -> 29.150585 | U9: =AG9+AI9 -> 8.9553481 | V9: =IF(L9>0,U9/L9,0) -> 28.429676 | W9: =IF(I9>0,V9/I9,0) -> 126.35412 | X9: =IF(E9="Slot",IF(N(G9)>0,ROUNDUP(W9/G9,0)*MAX(0,F9),0),W9*H9) -> 20343.013 | Y9: =IF(U9>0,Assumptions!J134,0) -> 0 | Z9: =IF(AND(D9="Channel",OR(E9="CPC",E9="CPA"),INDEX(Funnel!$B$5:$B$8,MATCH(C9,Funnel!$A$5:$A$8,0))>0),MIN(Assumptions!$D$49,J9*H9,IF(I9*L9>0,INDEX(Funnel!$B$5:$B$8,MATCH(C9,Funnel!$A$5:$A$8,0))/SUMPRODUCT(($C$5:$C$34=C9)*($D$5:$D$34="Channel")*(($E$5:$E$34="CPC")+($E$5:$E$34="CPA")))/(I9*L9)*H9,0)),0) -> 750 | AA9: =X9+Y9 -> 20343.013 | AB9: =IF(U9>0,(X9+Y9)/U9,"–") -> 2271.6049 | AC9: =SUMPRODUCT(--($Q$5:$Q$34<Q9))+1 -> 22 | AD9: =IF(AND(AH9>0,AI9>=AH9*0.999),"Used to capacity",IF(AI9>0,"Marginal (fills the gap)",IF(Z9>0,"Test only (wk 1–2)","Not used"))) -> Marginal (fills the gap) | AE9: =IF(H9>0,Z9/H9,0) -> 4.6583851 | AF9: =AE9*I9 -> 1.0481366 | AG9: =AF9*L9 -> 0.33016304 | AH9: =MAX(0,N9-AG9) -> 64.166087 | AI9: =MIN(AH9,MAX(0,T9-S9)) -> 8.625185
A10: =Assumptions!A135 -> C06 | B10: =Assumptions!B135 -> Programmatic job ads (Joveo: Indeed, Jooble, Talent.com, Kimeta, meinestadt…) | C10: =Assumptions!C135 -> Mechatronics | D10: Channel | E10: =Assumptions!D135 -> CPA | F10: =Assumptions!E135 -> 161 | G10: =IF(E10="Free","",Assumptions!F135) -> 0 | H10: =MAX(0,IF(OR(E10="CPC",E10="Slot"),IF(N(G10)>0,F10/G10,0),F10)) -> 161 | I10: =Assumptions!G135 -> 0.225 | J10: =IF(AND(OR(E10="CPC",E10="Slot"),NOT(N(G10)>0)),0,IF(E10="Slot",Assumptions!H135*G10,Assumptions!H135)) -> 4690 | K10: =J10*I10 -> 1055.25 | L10: =INDEX(Funnel!$G$5:$G$8,MATCH(C10,Funnel!$A$5:$A$8,0))*M10 -> 0.37125 | M10: =Assumptions!I135 -> 1 | N10: =K10*L10 -> 391.76156 | O10: =IF(I10>0,H10/I10,0) -> 715.55556 | P10: =IF(N10>0,(N10/L10/I10*H10+Assumptions!J135)/N10,0) -> 1927.4224 | Q10: =P10+ROW()/1000000 -> 1927.4224 | R10: =SUMPRODUCT(($C$5:$C$34=C10)*($Q$5:$Q$34<Q10))+1 -> 6 | S10: =SUMPRODUCT(($C$5:$C$34=C10)*($Q$5:$Q$34<Q10)*$AH$5:$AH$34) -> 37.211816 | T10: =INDEX(Funnel!$B$5:$B$8,MATCH(C10,Funnel!$A$5:$A$8,0))-SUMIFS($AG$5:$AG$34,$C$5:$C$34,C10) -> 43.998904 | U10: =AG10+AI10 -> 7.1762083 | V10: =IF(L10>0,U10/L10,0) -> 19.329854 | W10: =IF(I10>0,V10/I10,0) -> 85.910462 | X10: =IF(E10="Slot",IF(N(G10)>0,ROUNDUP(W10/G10,0)*MAX(0,F10),0),W10*H10) -> 13831.584 | Y10: =IF(U10>0,Assumptions!J135,0) -> 0 | Z10: =IF(AND(D10="Channel",OR(E10="CPC",E10="CPA"),INDEX(Funnel!$B$5:$B$8,MATCH(C10,Funnel!$A$5:$A$8,0))>0),MIN(Assumptions!$D$49,J10*H10,IF(I10*L10>0,INDEX(Funnel!$B$5:$B$8,MATCH(C10,Funnel!$A$5:$A$8,0))/SUMPRODUCT(($C$5:$C$34=C10)*($D$5:$D$34="Channel")*(($E$5:$E$34="CPC")+($E$5:$E$34="CPA")))/(I10*L10)*H10,0)),0) -> 750 | AA10: =X10+Y10 -> 13831.584 | AB10: =IF(U10>0,(X10+Y10)/U10,"–") -> 1927.4224 | AC10: =SUMPRODUCT(--($Q$5:$Q$34<Q10))+1 -> 19 | AD10: =IF(AND(AH10>0,AI10>=AH10*0.999),"Used to capacity",IF(AI10>0,"Marginal (fills the gap)",IF(Z10>0,"Test only (wk 1–2)","Not used"))) -> Marginal (fills the gap) | AE10: =IF(H10>0,Z10/H10,0) -> 4.6583851 | AF10: =AE10*I10 -> 1.0481366 | AG10: =AF10*L10 -> 0.38912073 | AH10: =MAX(0,N10-AG10) -> 391.37244 | AI10: =MIN(AH10,MAX(0,T10-S10)) -> 6.7870875
A11: =Assumptions!A136 -> C07 | B11: =Assumptions!B136 -> Programmatic job ads (Joveo: Indeed, Jooble, Talent.com, Kimeta, meinestadt…) | C11: =Assumptions!C136 -> Automation | D11: Channel | E11: =Assumptions!D136 -> CPA | F11: =Assumptions!E136 -> 161 | G11: =IF(E11="Free","",Assumptions!F136) -> 0 | H11: =MAX(0,IF(OR(E11="CPC",E11="Slot"),IF(N(G11)>0,F11/G11,0),F11)) -> 161 | I11: =Assumptions!G136 -> 0.225 | J11: =IF(AND(OR(E11="CPC",E11="Slot"),NOT(N(G11)>0)),0,IF(E11="Slot",Assumptions!H136*G11,Assumptions!H136)) -> 380 | K11: =J11*I11 -> 85.5 | L11: =INDEX(Funnel!$G$5:$G$8,MATCH(C11,Funnel!$A$5:$A$8,0))*M11 -> 0.2835 | M11: =Assumptions!I136 -> 1 | N11: =K11*L11 -> 24.23925 | O11: =IF(I11>0,H11/I11,0) -> 715.55556 | P11: =IF(N11>0,(N11/L11/I11*H11+Assumptions!J136)/N11,0) -> 2524.0055 | Q11: =P11+ROW()/1000000 -> 2524.0055 | R11: =SUMPRODUCT(($C$5:$C$34=C11)*($Q$5:$Q$34<Q11))+1 -> 6 | S11: =SUMPRODUCT(($C$5:$C$34=C11)*($Q$5:$Q$34<Q11)*$AH$5:$AH$34) -> 16.225183 | T11: =INDEX(Funnel!$B$5:$B$8,MATCH(C11,Funnel!$A$5:$A$8,0))-SUMIFS($AG$5:$AG$34,$C$5:$C$34,C11) -> 13.99664 | U11: =AG11+AI11 -> 0.29714674 | V11: =IF(L11>0,U11/L11,0) -> 1.0481366 | W11: =IF(I11>0,V11/I11,0) -> 4.6583851 | X11: =IF(E11="Slot",IF(N(G11)>0,ROUNDUP(W11/G11,0)*MAX(0,F11),0),W11*H11) -> 750 | Y11: =IF(U11>0,Assumptions!J136,0) -> 0 | Z11: =IF(AND(D11="Channel",OR(E11="CPC",E11="CPA"),INDEX(Funnel!$B$5:$B$8,MATCH(C11,Funnel!$A$5:$A$8,0))>0),MIN(Assumptions!$D$49,J11*H11,IF(I11*L11>0,INDEX(Funnel!$B$5:$B$8,MATCH(C11,Funnel!$A$5:$A$8,0))/SUMPRODUCT(($C$5:$C$34=C11)*($D$5:$D$34="Channel")*(($E$5:$E$34="CPC")+($E$5:$E$34="CPA")))/(I11*L11)*H11,0)),0) -> 750 | AA11: =X11+Y11 -> 750 | AB11: =IF(U11>0,(X11+Y11)/U11,"–") -> 2524.0055 | AC11: =SUMPRODUCT(--($Q$5:$Q$34<Q11))+1 -> 24 | AD11: =IF(AND(AH11>0,AI11>=AH11*0.999),"Used to capacity",IF(AI11>0,"Marginal (fills the gap)",IF(Z11>0,"Test only (wk 1–2)","Not used"))) -> Test only (wk 1–2) | AE11: =IF(H11>0,Z11/H11,0) -> 4.6583851 | AF11: =AE11*I11 -> 1.0481366 | AG11: =AF11*L11 -> 0.29714674 | AH11: =MAX(0,N11-AG11) -> 23.942103 | AI11: =MIN(AH11,MAX(0,T11-S11)) -> 0
A12: =Assumptions!A137 -> C08 | B12: =Assumptions!B137 -> Programmatic job ads (Joveo: Indeed, Jooble, Talent.com, Kimeta, meinestadt…) | C12: =Assumptions!C137 -> Supervisors | D12: Channel | E12: =Assumptions!D137 -> CPA | F12: =Assumptions!E137 -> 161 | G12: =IF(E12="Free","",Assumptions!F137) -> 0 | H12: =MAX(0,IF(OR(E12="CPC",E12="Slot"),IF(N(G12)>0,F12/G12,0),F12)) -> 161 | I12: =Assumptions!G137 -> 0.207 | J12: =IF(AND(OR(E12="CPC",E12="Slot"),NOT(N(G12)>0)),0,IF(E12="Slot",Assumptions!H137*G12,Assumptions!H137)) -> 430 | K12: =J12*I12 -> 89.01 | L12: =INDEX(Funnel!$G$5:$G$8,MATCH(C12,Funnel!$A$5:$A$8,0))*M12 -> 0.238 | M12: =Assumptions!I137 -> 1 | N12: =K12*L12 -> 21.18438 | O12: =IF(I12>0,H12/I12,0) -> 777.77778 | P12: =IF(N12>0,(N12/L12/I12*H12+Assumptions!J137)/N12,0) -> 3267.9739 | Q12: =P12+ROW()/1000000 -> 3267.9739 | R12: =SUMPRODUCT(($C$5:$C$34=C12)*($Q$5:$Q$34<Q12))+1 -> 6 | S12: =SUMPRODUCT(($C$5:$C$34=C12)*($Q$5:$Q$34<Q12)*$AH$5:$AH$34) -> 12.0493 | T12: =INDEX(Funnel!$B$5:$B$8,MATCH(C12,Funnel!$A$5:$A$8,0))-SUMIFS($AG$5:$AG$34,$C$5:$C$34,C12) -> 9.2250591 | U12: =AG12+AI12 -> 0.2295 | V12: =IF(L12>0,U12/L12,0) -> 0.96428571 | W12: =IF(I12>0,V12/I12,0) -> 4.6583851 | X12: =IF(E12="Slot",IF(N(G12)>0,ROUNDUP(W12/G12,0)*MAX(0,F12),0),W12*H12) -> 750 | Y12: =IF(U12>0,Assumptions!J137,0) -> 0 | Z12: =IF(AND(D12="Channel",OR(E12="CPC",E12="CPA"),INDEX(Funnel!$B$5:$B$8,MATCH(C12,Funnel!$A$5:$A$8,0))>0),MIN(Assumptions!$D$49,J12*H12,IF(I12*L12>0,INDEX(Funnel!$B$5:$B$8,MATCH(C12,Funnel!$A$5:$A$8,0))/SUMPRODUCT(($C$5:$C$34=C12)*($D$5:$D$34="Channel")*(($E$5:$E$34="CPC")+($E$5:$E$34="CPA")))/(I12*L12)*H12,0)),0) -> 750 | AA12: =X12+Y12 -> 750 | AB12: =IF(U12>0,(X12+Y12)/U12,"–") -> 3267.9739 | AC12: =SUMPRODUCT(--($Q$5:$Q$34<Q12))+1 -> 28 | AD12: =IF(AND(AH12>0,AI12>=AH12*0.999),"Used to capacity",IF(AI12>0,"Marginal (fills the gap)",IF(Z12>0,"Test only (wk 1–2)","Not used"))) -> Test only (wk 1–2) | AE12: =IF(H12>0,Z12/H12,0) -> 4.6583851 | AF12: =AE12*I12 -> 0.96428571 | AG12: =AF12*L12 -> 0.2295 | AH12: =MAX(0,N12-AG12) -> 20.95488 | AI12: =MIN(AH12,MAX(0,T12-S12)) -> 0
A13: =Assumptions!A138 -> C09 | B13: =Assumptions!B138 -> StepStone (30-day single ad) | C13: =Assumptions!C138 -> Electricians | D13: Channel | E13: =Assumptions!D138 -> Slot | F13: =Assumptions!E138 -> 1449 | G13: =IF(E13="Free","",Assumptions!F138) -> 12 | H13: =MAX(0,IF(OR(E13="CPC",E13="Slot"),IF(N(G13)>0,F13/G13,0),F13)) -> 120.75 | I13: =Assumptions!G138 -> 0.225 | J13: =IF(AND(OR(E13="CPC",E13="Slot"),NOT(N(G13)>0)),0,IF(E13="Slot",Assumptions!H138*G13,Assumptions!H138)) -> 24 | K13: =J13*I13 -> 5.4 | L13: =INDEX(Funnel!$G$5:$G$8,MATCH(C13,Funnel!$A$5:$A$8,0))*M13 -> 0.315 | M13: =Assumptions!I138 -> 1 | N13: =K13*L13 -> 1.701 | O13: =IF(I13>0,H13/I13,0) -> 536.66667 | P13: =IF(N13>0,(N13/L13/I13*H13+Assumptions!J138)/N13,0) -> 1703.7037 | Q13: =P13+ROW()/1000000 -> 1703.7037 | R13: =SUMPRODUCT(($C$5:$C$34=C13)*($Q$5:$Q$34<Q13))+1 -> 5 | S13: =SUMPRODUCT(($C$5:$C$34=C13)*($Q$5:$Q$34<Q13)*$AH$5:$AH$34) -> 18.8244 | T13: =INDEX(Funnel!$B$5:$B$8,MATCH(C13,Funnel!$A$5:$A$8,0))-SUMIFS($AG$5:$AG$34,$C$5:$C$34,C13) -> 29.150585 | U13: =AG13+AI13 -> 1.701 | V13: =IF(L13>0,U13/L13,0) -> 5.4 | W13: =IF(I13>0,V13/I13,0) -> 24 | X13: =IF(E13="Slot",IF(N(G13)>0,ROUNDUP(W13/G13,0)*MAX(0,F13),0),W13*H13) -> 2898 | Y13: =IF(U13>0,Assumptions!J138,0) -> 0 | Z13: =IF(AND(D13="Channel",OR(E13="CPC",E13="CPA"),INDEX(Funnel!$B$5:$B$8,MATCH(C13,Funnel!$A$5:$A$8,0))>0),MIN(Assumptions!$D$49,J13*H13,IF(I13*L13>0,INDEX(Funnel!$B$5:$B$8,MATCH(C13,Funnel!$A$5:$A$8,0))/SUMPRODUCT(($C$5:$C$34=C13)*($D$5:$D$34="Channel")*(($E$5:$E$34="CPC")+($E$5:$E$34="CPA")))/(I13*L13)*H13,0)),0) -> 0 | AA13: =X13+Y13 -> 2898 | AB13: =IF(U13>0,(X13+Y13)/U13,"–") -> 1703.7037 | AC13: =SUMPRODUCT(--($Q$5:$Q$34<Q13))+1 -> 17 | AD13: =IF(AND(AH13>0,AI13>=AH13*0.999),"Used to capacity",IF(AI13>0,"Marginal (fills the gap)",IF(Z13>0,"Test only (wk 1–2)","Not used"))) -> Used to capacity | AE13: =IF(H13>0,Z13/H13,0) -> 0 | AF13: =AE13*I13 -> 0 | AG13: =AF13*L13 -> 0 | AH13: =MAX(0,N13-AG13) -> 1.701 | AI13: =MIN(AH13,MAX(0,T13-S13)) -> 1.701
A14: =Assumptions!A139 -> C10 | B14: =Assumptions!B139 -> StepStone (30-day single ad) | C14: =Assumptions!C139 -> Mechatronics | D14: Channel | E14: =Assumptions!D139 -> Slot | F14: =Assumptions!E139 -> 1449 | G14: =IF(E14="Free","",Assumptions!F139) -> 12 | H14: =MAX(0,IF(OR(E14="CPC",E14="Slot"),IF(N(G14)>0,F14/G14,0),F14)) -> 120.75 | I14: =Assumptions!G139 -> 0.225 | J14: =IF(AND(OR(E14="CPC",E14="Slot"),NOT(N(G14)>0)),0,IF(E14="Slot",Assumptions!H139*G14,Assumptions!H139)) -> 24 | K14: =J14*I14 -> 5.4 | L14: =INDEX(Funnel!$G$5:$G$8,MATCH(C14,Funnel!$A$5:$A$8,0))*M14 -> 0.37125 | M14: =Assumptions!I139 -> 1 | N14: =K14*L14 -> 2.00475 | O14: =IF(I14>0,H14/I14,0) -> 536.66667 | P14: =IF(N14>0,(N14/L14/I14*H14+Assumptions!J139)/N14,0) -> 1445.5668 | Q14: =P14+ROW()/1000000 -> 1445.5668 | R14: =SUMPRODUCT(($C$5:$C$34=C14)*($Q$5:$Q$34<Q14))+1 -> 5 | S14: =SUMPRODUCT(($C$5:$C$34=C14)*($Q$5:$Q$34<Q14)*$AH$5:$AH$34) -> 35.207066 | T14: =INDEX(Funnel!$B$5:$B$8,MATCH(C14,Funnel!$A$5:$A$8,0))-SUMIFS($AG$5:$AG$34,$C$5:$C$34,C14) -> 43.998904 | U14: =AG14+AI14 -> 2.00475 | V14: =IF(L14>0,U14/L14,0) -> 5.4 | W14: =IF(I14>0,V14/I14,0) -> 24 | X14: =IF(E14="Slot",IF(N(G14)>0,ROUNDUP(W14/G14,0)*MAX(0,F14),0),W14*H14) -> 2898 | Y14: =IF(U14>0,Assumptions!J139,0) -> 0 | Z14: =IF(AND(D14="Channel",OR(E14="CPC",E14="CPA"),INDEX(Funnel!$B$5:$B$8,MATCH(C14,Funnel!$A$5:$A$8,0))>0),MIN(Assumptions!$D$49,J14*H14,IF(I14*L14>0,INDEX(Funnel!$B$5:$B$8,MATCH(C14,Funnel!$A$5:$A$8,0))/SUMPRODUCT(($C$5:$C$34=C14)*($D$5:$D$34="Channel")*(($E$5:$E$34="CPC")+($E$5:$E$34="CPA")))/(I14*L14)*H14,0)),0) -> 0 | AA14: =X14+Y14 -> 2898 | AB14: =IF(U14>0,(X14+Y14)/U14,"–") -> 1445.5668 | AC14: =SUMPRODUCT(--($Q$5:$Q$34<Q14))+1 -> 15 | AD14: =IF(AND(AH14>0,AI14>=AH14*0.999),"Used to capacity",IF(AI14>0,"Marginal (fills the gap)",IF(Z14>0,"Test only (wk 1–2)","Not used"))) -> Used to capacity | AE14: =IF(H14>0,Z14/H14,0) -> 0 | AF14: =AE14*I14 -> 0 | AG14: =AF14*L14 -> 0 | AH14: =MAX(0,N14-AG14) -> 2.00475 | AI14: =MIN(AH14,MAX(0,T14-S14)) -> 2.00475
A15: =Assumptions!A140 -> C11 | B15: =Assumptions!B140 -> StepStone (30-day single ad) | C15: =Assumptions!C140 -> Automation | D15: Channel | E15: =Assumptions!D140 -> Slot | F15: =Assumptions!E140 -> 1449 | G15: =IF(E15="Free","",Assumptions!F140) -> 12 | H15: =MAX(0,IF(OR(E15="CPC",E15="Slot"),IF(N(G15)>0,F15/G15,0),F15)) -> 120.75 | I15: =Assumptions!G140 -> 0.225 | J15: =IF(AND(OR(E15="CPC",E15="Slot"),NOT(N(G15)>0)),0,IF(E15="Slot",Assumptions!H140*G15,Assumptions!H140)) -> 24 | K15: =J15*I15 -> 5.4 | L15: =INDEX(Funnel!$G$5:$G$8,MATCH(C15,Funnel!$A$5:$A$8,0))*M15 -> 0.2835 | M15: =Assumptions!I140 -> 1 | N15: =K15*L15 -> 1.5309 | O15: =IF(I15>0,H15/I15,0) -> 536.66667 | P15: =IF(N15>0,(N15/L15/I15*H15+Assumptions!J140)/N15,0) -> 1893.0041 | Q15: =P15+ROW()/1000000 -> 1893.0041 | R15: =SUMPRODUCT(($C$5:$C$34=C15)*($Q$5:$Q$34<Q15))+1 -> 5 | S15: =SUMPRODUCT(($C$5:$C$34=C15)*($Q$5:$Q$34<Q15)*$AH$5:$AH$34) -> 14.694283 | T15: =INDEX(Funnel!$B$5:$B$8,MATCH(C15,Funnel!$A$5:$A$8,0))-SUMIFS($AG$5:$AG$34,$C$5:$C$34,C15) -> 13.99664 | U15: =AG15+AI15 -> 0 | V15: =IF(L15>0,U15/L15,0) -> 0 | W15: =IF(I15>0,V15/I15,0) -> 0 | X15: =IF(E15="Slot",IF(N(G15)>0,ROUNDUP(W15/G15,0)*MAX(0,F15),0),W15*H15) -> 0 | Y15: =IF(U15>0,Assumptions!J140,0) -> 0 | Z15: =IF(AND(D15="Channel",OR(E15="CPC",E15="CPA"),INDEX(Funnel!$B$5:$B$8,MATCH(C15,Funnel!$A$5:$A$8,0))>0),MIN(Assumptions!$D$49,J15*H15,IF(I15*L15>0,INDEX(Funnel!$B$5:$B$8,MATCH(C15,Funnel!$A$5:$A$8,0))/SUMPRODUCT(($C$5:$C$34=C15)*($D$5:$D$34="Channel")*(($E$5:$E$34="CPC")+($E$5:$E$34="CPA")))/(I15*L15)*H15,0)),0) -> 0 | AA15: =X15+Y15 -> 0 | AB15: =IF(U15>0,(X15+Y15)/U15,"–") -> – | AC15: =SUMPRODUCT(--($Q$5:$Q$34<Q15))+1 -> 18 | AD15: =IF(AND(AH15>0,AI15>=AH15*0.999),"Used to capacity",IF(AI15>0,"Marginal (fills the gap)",IF(Z15>0,"Test only (wk 1–2)","Not used"))) -> Not used | AE15: =IF(H15>0,Z15/H15,0) -> 0 | AF15: =AE15*I15 -> 0 | AG15: =AF15*L15 -> 0 | AH15: =MAX(0,N15-AG15) -> 1.5309 | AI15: =MIN(AH15,MAX(0,T15-S15)) -> 0
A16: =Assumptions!A141 -> C12 | B16: =Assumptions!B141 -> StepStone (30-day single ad) | C16: =Assumptions!C141 -> Supervisors | D16: Channel | E16: =Assumptions!D141 -> Slot | F16: =Assumptions!E141 -> 1449 | G16: =IF(E16="Free","",Assumptions!F141) -> 12 | H16: =MAX(0,IF(OR(E16="CPC",E16="Slot"),IF(N(G16)>0,F16/G16,0),F16)) -> 120.75 | I16: =Assumptions!G141 -> 0.207 | J16: =IF(AND(OR(E16="CPC",E16="Slot"),NOT(N(G16)>0)),0,IF(E16="Slot",Assumptions!H141*G16,Assumptions!H141)) -> 12 | K16: =J16*I16 -> 2.484 | L16: =INDEX(Funnel!$G$5:$G$8,MATCH(C16,Funnel!$A$5:$A$8,0))*M16 -> 0.238 | M16: =Assumptions!I141 -> 1 | N16: =K16*L16 -> 0.591192 | O16: =IF(I16>0,H16/I16,0) -> 583.33333 | P16: =IF(N16>0,(N16/L16/I16*H16+Assumptions!J141)/N16,0) -> 2450.9804 | Q16: =P16+ROW()/1000000 -> 2450.9804 | R16: =SUMPRODUCT(($C$5:$C$34=C16)*($Q$5:$Q$34<Q16))+1 -> 5 | S16: =SUMPRODUCT(($C$5:$C$34=C16)*($Q$5:$Q$34<Q16)*$AH$5:$AH$34) -> 11.458108 | T16: =INDEX(Funnel!$B$5:$B$8,MATCH(C16,Funnel!$A$5:$A$8,0))-SUMIFS($AG$5:$AG$34,$C$5:$C$34,C16) -> 9.2250591 | U16: =AG16+AI16 -> 0 | V16: =IF(L16>0,U16/L16,0) -> 0 | W16: =IF(I16>0,V16/I16,0) -> 0 | X16: =IF(E16="Slot",IF(N(G16)>0,ROUNDUP(W16/G16,0)*MAX(0,F16),0),W16*H16) -> 0 | Y16: =IF(U16>0,Assumptions!J141,0) -> 0 | Z16: =IF(AND(D16="Channel",OR(E16="CPC",E16="CPA"),INDEX(Funnel!$B$5:$B$8,MATCH(C16,Funnel!$A$5:$A$8,0))>0),MIN(Assumptions!$D$49,J16*H16,IF(I16*L16>0,INDEX(Funnel!$B$5:$B$8,MATCH(C16,Funnel!$A$5:$A$8,0))/SUMPRODUCT(($C$5:$C$34=C16)*($D$5:$D$34="Channel")*(($E$5:$E$34="CPC")+($E$5:$E$34="CPA")))/(I16*L16)*H16,0)),0) -> 0 | AA16: =X16+Y16 -> 0 | AB16: =IF(U16>0,(X16+Y16)/U16,"–") -> – | AC16: =SUMPRODUCT(--($Q$5:$Q$34<Q16))+1 -> 23 | AD16: =IF(AND(AH16>0,AI16>=AH16*0.999),"Used to capacity",IF(AI16>0,"Marginal (fills the gap)",IF(Z16>0,"Test only (wk 1–2)","Not used"))) -> Not used | AE16: =IF(H16>0,Z16/H16,0) -> 0 | AF16: =AE16*I16 -> 0 | AG16: =AF16*L16 -> 0 | AH16: =MAX(0,N16-AG16) -> 0.591192 | AI16: =MIN(AH16,MAX(0,T16-S16)) -> 0
... A24: =Assumptions!A149 -> C20 | B24: =Assumptions!B149 -> Google Search ads (job-intent keywords) | C24: =Assumptions!C149 -> Supervisors | D24: Channel | E24: =Assumptions!D149 -> CPA | F24: =Assumptions!E149 -> 179 | G24: =IF(E24="Free","",Assumptions!F149) -> 0 | H24: =MAX(0,IF(OR(E24="CPC",E24="Slot"),IF(N(G24)>0,F24/G24,0),F24)) -> 179 | I24: =Assumptions!G149 -> 0.161 | J24: =IF(AND(OR(E24="CPC",E24="Slot"),NOT(N(G24)>0)),0,IF(E24="Slot",Assumptions!H149*G24,Assumptions!H149)) -> 160 | K24: =J24*I24 -> 25.76 | L24: =INDEX(Funnel!$G$5:$G$8,MATCH(C24,Funnel!$A$5:$A$8,0))*M24 -> 0.238 | M24: =Assumptions!I149 -> 1 | N24: =K24*L24 -> 6.13088 | O24: =IF(I24>0,H24/I24,0) -> 1111.8012 | P24: =IF(N24>0,(N24/L24/I24*H24+Assumptions!J149)/N24,0) -> 4671.4338 | Q24: =P24+ROW()/1000000 -> 4671.4338 | R24: =SUMPRODUCT(($C$5:$C$34=C24)*($Q$5:$Q$34<Q24))+1 -> 7 | S24: =SUMPRODUCT(($C$5:$C$34=C24)*($Q$5:$Q$34<Q24)*$AH$5:$AH$34) -> 33.00418 | T24: =INDEX(Funnel!$B$5:$B$8,MATCH(C24,Funnel!$A$5:$A$8,0))-SUMIFS($AG$5:$AG$34,$C$5:$C$34,C24) -> 9.2250591 | U24: =AG24+AI24 -> 0.16055028 | V24: =IF(L24>0,U24/L24,0) -> 0.67458101 | W24: =IF(I24>0,V24/I24,0) -> 4.1899441 | X24: =IF(E24="Slot",IF(N(G24)>0,ROUNDUP(W24/G24,0)*MAX(0,F24),0),W24*H24) -> 750 | Y24: =IF(U24>0,Assumptions!J149,0) -> 0 | Z24: =IF(AND(D24="Channel",OR(E24="CPC",E24="CPA"),INDEX(Funnel!$B$5:$B$8,MATCH(C24,Funnel!$A$5:$A$8,0))>0),MIN(Assumptions!$D$49,J24*H24,IF(I24*L24>0,INDEX(Funnel!$B$5:$B$8,MATCH(C24,Funnel!$A$5:$A$8,0))/SUMPRODUCT(($C$5:$C$34=C24)*($D$5:$D$34="Channel")*(($E$5:$E$34="CPC")+($E$5:$E$34="CPA")))/(I24*L24)*H24,0)),0) -> 750 | AA24: =X24+Y24 -> 750 | AB24: =IF(U24>0,(X24+Y24)/U24,"–") -> 4671.4338 | AC24: =SUMPRODUCT(--($Q$5:$Q$34<Q24))+1 -> 30 | AD24: =IF(AND(AH24>0,AI24>=AH24*0.999),"Used to capacity",IF(AI24>0,"Marginal (fills the gap)",IF(Z24>0,"Test only (wk 1–2)","Not used"))) -> Test only (wk 1–2) | AE24: =IF(H24>0,Z24/H24,0) -> 4.1899441 | AF24: =AE24*I24 -> 0.67458101 | AG24: =AF24*L24 -> 0.16055028 | AH24: =MAX(0,N24-AG24) -> 5.9703297 | AI24: =MIN(AH24,MAX(0,T24-S24)) -> 0
A25: I1a-E | B25: I1a Talent rediscovery (past applicants in ATS) | C25: Electricians | D25: Initiative | E25: CPA | F25: =Initiatives!B11 -> 2.5 | H25: =F25 -> 2.5 | I25: =Initiatives!B8 -> 0.5 | J25: =Initiatives!B7 -> 7.8 | K25: =J25*I25 -> 3.9 | L25: =INDEX(Funnel!$G$5:$G$8,MATCH(C25,Funnel!$A$5:$A$8,0))*M25 -> 0.36225 | M25: =Assumptions!$D$166 -> 1.15 | N25: =K25*L25 -> 1.412775 | O25: =IF(I25>0,H25/I25,0) -> 5 | P25: =IF(N25>0,(N25/L25/I25*H25+0)/N25,0) -> 13.802622 | Q25: =P25+ROW()/1000000 -> 13.802647 | R25: =SUMPRODUCT(($C$5:$C$34=C25)*($Q$5:$Q$34<Q25))+1 -> 2 | S25: =SUMPRODUCT(($C$5:$C$34=C25)*($Q$5:$Q$34<Q25)*$AH$5:$AH$34) -> 5.788125 | T25: =INDEX(Funnel!$B$5:$B$8,MATCH(C25,Funnel!$A$5:$A$8,0))-SUMIFS($AG$5:$AG$34,$C$5:$C$34,C25) -> 29.150585 | U25: =AG25+AI25 -> 1.412775 | V25: =IF(L25>0,U25/L25,0) -> 3.9 | W25: =IF(I25>0,V25/I25,0) -> 7.8 | X25: =IF(E25="Slot",IF(N(G25)>0,ROUNDUP(W25/G25,0)*MAX(0,F25),0),W25*H25) -> 19.5 | Y25: =IF(U25>0,0,0) -> 0 | Z25: =IF(AND(D25="Channel",OR(E25="CPC",E25="CPA"),INDEX(Funnel!$B$5:$B$8,MATCH(C25,Funnel!$A$5:$A$8,0))>0),MIN(Assumptions!$D$49,J25*H25,IF(I25*L25>0,INDEX(Funnel!$B$5:$B$8,MATCH(C25,Funnel!$A$5:$A$8,0))/SUMPRODUCT(($C$5:$C$34=C25)*($D$5:$D$34="Channel")*(($E$5:$E$34="CPC")+($E$5:$E$34="CPA")))/(I25*L25)*H25,0)),0) -> 0 | AA25: =X25+Y25 -> 19.5 | AB25: =IF(U25>0,(X25+Y25)/U25,"–") -> 13.802622 | AC25: =SUMPRODUCT(--($Q$5:$Q$34<Q25))+1 -> 6 | AD25: =IF(AND(AH25>0,AI25>=AH25*0.999),"Used to capacity",IF(AI25>0,"Marginal (fills the gap)",IF(Z25>0,"Test only (wk 1–2)","Not used"))) -> Used to capacity | AE25: =IF(H25>0,Z25/H25,0) -> 0 | AF25: =AE25*I25 -> 0 | AG25: =AF25*L25 -> 0 | AH25: =MAX(0,N25-AG25) -> 1.412775 | AI25: =MIN(AH25,MAX(0,T25-S25)) -> 1.412775
A26: I1a-M | B26: I1a Talent rediscovery (past applicants in ATS) | C26: Mechatronics | D26: Initiative | E26: CPA | F26: =Initiatives!C11 -> 2.5 | H26: =F26 -> 2.5 | I26: =Initiatives!C8 -> 0.5 | J26: =Initiatives!C7 -> 9.12 | K26: =J26*I26 -> 4.56 | L26: =INDEX(Funnel!$G$5:$G$8,MATCH(C26,Funnel!$A$5:$A$8,0))*M26 -> 0.4269375 | M26: =Assumptions!$D$166 -> 1.15 | N26: =K26*L26 -> 1.946835 | O26: =IF(I26>0,H26/I26,0) -> 5 | P26: =IF(N26>0,(N26/L26/I26*H26+0)/N26,0) -> 11.711316 | Q26: =P26+ROW()/1000000 -> 11.711342 | R26: =SUMPRODUCT(($C$5:$C$34=C26)*($Q$5:$Q$34<Q26))+1 -> 2 | S26: =SUMPRODUCT(($C$5:$C$34=C26)*($Q$5:$Q$34<Q26)*$AH$5:$AH$34) -> 10.265063 | T26: =INDEX(Funnel!$B$5:$B$8,MATCH(C26,Funnel!$A$5:$A$8,0))-SUMIFS($AG$5:$AG$34,$C$5:$C$34,C26) -> 43.998904 | U26: =AG26+AI26 -> 1.946835 | V26: =IF(L26>0,U26/L26,0) -> 4.56 | W26: =IF(I26>0,V26/I26,0) -> 9.12 | X26: =IF(E26="Slot",IF(N(G26)>0,ROUNDUP(W26/G26,0)*MAX(0,F26),0),W26*H26) -> 22.8 | Y26: =IF(U26>0,0,0) -> 0 | Z26: =IF(AND(D26="Channel",OR(E26="CPC",E26="CPA"),INDEX(Funnel!$B$5:$B$8,MATCH(C26,Funnel!$A$5:$A$8,0))>0),MIN(Assumptions!$D$49,J26*H26,IF(I26*L26>0,INDEX(Funnel!$B$5:$B$8,MATCH(C26,Funnel!$A$5:$A$8,0))/SUMPRODUCT(($C$5:$C$34=C26)*($D$5:$D$34="Channel")*(($E$5:$E$34="CPC")+($E$5:$E$34="CPA")))/(I26*L26)*H26,0)),0) -> 0 | AA26: =X26+Y26 -> 22.8 | AB26: =IF(U26>0,(X26+Y26)/U26,"–") -> 11.711316 | AC26: =SUMPRODUCT(--($Q$5:$Q$34<Q26))+1 -> 5 | AD26: =IF(AND(AH26>0,AI26>=AH26*0.999),"Used to capacity",IF(AI26>0,"Marginal (fills the gap)",IF(Z26>0,"Test only (wk 1–2)","Not used"))) -> Used to capacity | AE26: =IF(H26>0,Z26/H26,0) -> 0 | AF26: =AE26*I26 -> 0 | AG26: =AF26*L26 -> 0 | AH26: =MAX(0,N26-AG26) -> 1.946835 | AI26: =MIN(AH26,MAX(0,T26-S26)) -> 1.946835
A27: I1a-A | B27: I1a Talent rediscovery (past applicants in ATS) | C27: Automation | D27: Initiative | E27: CPA | F27: =Initiatives!D11 -> 2.5 | H27: =F27 -> 2.5 | I27: =Initiatives!D8 -> 0.5 | J27: =Initiatives!D7 -> 4.56 | K27: =J27*I27 -> 2.28 | L27: =INDEX(Funnel!$G$5:$G$8,MATCH(C27,Funnel!$A$5:$A$8,0))*M27 -> 0.326025 | M27: =Assumptions!$D$166 -> 1.15 | N27: =K27*L27 -> 0.743337 | O27: =IF(I27>0,H27/I27,0) -> 5 | P27: =IF(N27>0,(N27/L27/I27*H27+0)/N27,0) -> 15.336247 | Q27: =P27+ROW()/1000000 -> 15.336274 | R27: =SUMPRODUCT(($C$5:$C$34=C27)*($Q$5:$Q$34<Q27))+1 -> 2 | S27: =SUMPRODUCT(($C$5:$C$34=C27)*($Q$5:$Q$34<Q27)*$AH$5:$AH$34) -> 2.6294625 | T27: =INDEX(Funnel!$B$5:$B$8,MATCH(C27,Funnel!$A$5:$A$8,0))-SUMIFS($AG$5:$AG$34,$C$5:$C$34,C27) -> 13.99664 | U27: =AG27+AI27 -> 0.743337 | V27: =IF(L27>0,U27/L27,0) -> 2.28 | W27: =IF(I27>0,V27/I27,0) -> 4.56 | X27: =IF(E27="Slot",IF(N(G27)>0,ROUNDUP(W27/G27,0)*MAX(0,F27),0),W27*H27) -> 11.4 | Y27: =IF(U27>0,0,0) -> 0 | Z27: =IF(AND(D27="Channel",OR(E27="CPC",E27="CPA"),INDEX(Funnel!$B$5:$B$8,MATCH(C27,Funnel!$A$5:$A$8,0))>0),MIN(Assumptions!$D$49,J27*H27,IF(I27*L27>0,INDEX(Funnel!$B$5:$B$8,MATCH(C27,Funnel!$A$5:$A$8,0))/SUMPRODUCT(($C$5:$C$34=C27)*($D$5:$D$34="Channel")*(($E$5:$E$34="CPC")+($E$5:$E$34="CPA")))/(I27*L27)*H27,0)),0) -> 0 | AA27: =X27+Y27 -> 11.4 | AB27: =IF(U27>0,(X27+Y27)/U27,"–") -> 15.336247 | AC27: =SUMPRODUCT(--($Q$5:$Q$34<Q27))+1 -> 7 | AD27: =IF(AND(AH27>0,AI27>=AH27*0.999),"Used to capacity",IF(AI27>0,"Marginal (fills the gap)",IF(Z27>0,"Test only (wk 1–2)","Not used"))) -> Used to capacity | AE27: =IF(H27>0,Z27/H27,0) -> 0 | AF27: =AE27*I27 -> 0 | AG27: =AF27*L27 -> 0 | AH27: =MAX(0,N27-AG27) -> 0.743337 | AI27: =MIN(AH27,MAX(0,T27-S27)) -> 0.743337
A28: I1a-S | B28: I1a Talent rediscovery (past applicants in ATS) | C28: Supervisors | D28: Initiative | E28: CPA | F28: =Initiatives!E11 -> 2.5 | H28: =F28 -> 2.5 | I28: =Initiatives!E8 -> 0.5 | J28: =Initiatives!E7 -> 3.84 | K28: =J28*I28 -> 1.92 | L28: =INDEX(Funnel!$G$5:$G$8,MATCH(C28,Funnel!$A$5:$A$8,0))*M28 -> 0.2737 | M28: =Assumptions!$D$166 -> 1.15 | N28: =K28*L28 -> 0.525504 | O28: =IF(I28>0,H28/I28,0) -> 5 | P28: =IF(N28>0,(N28/L28/I28*H28+0)/N28,0) -> 18.268177 | Q28: =P28+ROW()/1000000 -> 18.268205 | R28: =SUMPRODUCT(($C$5:$C$34=C28)*($Q$5:$Q$34<Q28))+1 -> 2 | S28: =SUMPRODUCT(($C$5:$C$34=C28)*($Q$5:$Q$34<Q28)*$AH$5:$AH$34) -> 1.34113 | T28: =INDEX(Funnel!$B$5:$B$8,MATCH(C28,Funnel!$A$5:$A$8,0))-SUMIFS($AG$5:$AG$34,$C$5:$C$34,C28) -> 9.2250591 | U28: =AG28+AI28 -> 0.525504 | V28: =IF(L28>0,U28/L28,0) -> 1.92 | W28: =IF(I28>0,V28/I28,0) -> 3.84 | X28: =IF(E28="Slot",IF(N(G28)>0,ROUNDUP(W28/G28,0)*MAX(0,F28),0),W28*H28) -> 9.6 | Y28: =IF(U28>0,0,0) -> 0 | Z28: =IF(AND(D28="Channel",OR(E28="CPC",E28="CPA"),INDEX(Funnel!$B$5:$B$8,MATCH(C28,Funnel!$A$5:$A$8,0))>0),MIN(Assumptions!$D$49,J28*H28,IF(I28*L28>0,INDEX(Funnel!$B$5:$B$8,MATCH(C28,Funnel!$A$5:$A$8,0))/SUMPRODUCT(($C$5:$C$34=C28)*($D$5:$D$34="Channel")*(($E$5:$E$34="CPC")+($E$5:$E$34="CPA")))/(I28*L28)*H28,0)),0) -> 0 | AA28: =X28+Y28 -> 9.6 | AB28: =IF(U28>0,(X28+Y28)/U28,"–") -> 18.268177 | AC28: =SUMPRODUCT(--($Q$5:$Q$34<Q28))+1 -> 8 | AD28: =IF(AND(AH28>0,AI28>=AH28*0.999),"Used to capacity",IF(AI28>0,"Marginal (fills the gap)",IF(Z28>0,"Test only (wk 1–2)","Not used"))) -> Used to capacity | AE28: =IF(H28>0,Z28/H28,0) -> 0 | AF28: =AE28*I28 -> 0 | AG28: =AF28*L28 -> 0 | AH28: =MAX(0,N28-AG28) -> 0.525504 | AI28: =MIN(AH28,MAX(0,T28-S28)) -> 0.525504
A29: I1b-E | B29: I1b Employee referral sprint (bonus on hire) | C29: Electricians | D29: Initiative | E29: CPA | F29: =Initiatives!B17 -> 163.0125 | H29: =F29 -> 163.0125 | I29: =Initiatives!B14 -> 0.45 | J29: =Initiatives!B13 -> 20 | K29: =J29*I29 -> 9 | L29: =INDEX(Funnel!$G$5:$G$8,MATCH(C29,Funnel!$A$5:$A$8,0))*M29 -> 0.36225 | M29: =Assumptions!$D$166 -> 1.15 | N29: =K29*L29 -> 3.26025 | O29: =IF(I29>0,H29/I29,0) -> 362.25 | P29: =IF(N29>0,(N29/L29/I29*H29+0)/N29,0) -> 1000 | Q29: =P29+ROW()/1000000 -> 1000 | R29: =SUMPRODUCT(($C$5:$C$34=C29)*($Q$5:$Q$34<Q29))+1 -> 3 | S29: =SUMPRODUCT(($C$5:$C$34=C29)*($Q$5:$Q$34<Q29)*$AH$5:$AH$34) -> 7.2009 | T29: =INDEX(Funnel!$B$5:$B$8,MATCH(C29,Funnel!$A$5:$A$8,0))-SUMIFS($AG$5:$AG$34,$C$5:$C$34,C29) -> 29.150585 | U29: =AG29+AI29 -> 3.26025 | V29: =IF(L29>0,U29/L29,0) -> 9 | W29: =IF(I29>0,V29/I29,0) -> 20 | X29: =IF(E29="Slot",IF(N(G29)>0,ROUNDUP(W29/G29,0)*MAX(0,F29),0),W29*H29) -> 3260.25 | Y29: =IF(U29>0,0,0) -> 0 | Z29: =IF(AND(D29="Channel",OR(E29="CPC",E29="CPA"),INDEX(Funnel!$B$5:$B$8,MATCH(C29,Funnel!$A$5:$A$8,0))>0),MIN(Assumptions!$D$49,J29*H29,IF(I29*L29>0,INDEX(Funnel!$B$5:$B$8,MATCH(C29,Funnel!$A$5:$A$8,0))/SUMPRODUCT(($C$5:$C$34=C29)*($D$5:$D$34="Channel")*(($E$5:$E$34="CPC")+($E$5:$E$34="CPA")))/(I29*L29)*H29,0)),0) -> 0 | AA29: =X29+Y29 -> 3260.25 | AB29: =IF(U29>0,(X29+Y29)/U29,"–") -> 1000 | AC29: =SUMPRODUCT(--($Q$5:$Q$34<Q29))+1 -> 10 | AD29: =IF(AND(AH29>0,AI29>=AH29*0.999),"Used to capacity",IF(AI29>0,"Marginal (fills the gap)",IF(Z29>0,"Test only (wk 1–2)","Not used"))) -> Used to capacity | AE29: =IF(H29>0,Z29/H29,0) -> 0 | AF29: =AE29*I29 -> 0 | AG29: =AF29*L29 -> 0 | AH29: =MAX(0,N29-AG29) -> 3.26025 | AI29: =MIN(AH29,MAX(0,T29-S29)) -> 3.26025
A30: I1b-M | B30: I1b Employee referral sprint (bonus on hire) | C30: Mechatronics | D30: Initiative | E30: CPA | F30: =Initiatives!C17 -> 192.12187 | H30: =F30 -> 192.12187 | I30: =Initiatives!C14 -> 0.45 | J30: =Initiatives!C13 -> 26 | K30: =J30*I30 -> 11.7 | L30: =INDEX(Funnel!$G$5:$G$8,MATCH(C30,Funnel!$A$5:$A$8,0))*M30 -> 0.4269375 | M30: =Assumptions!$D$166 -> 1.15 | N30: =K30*L30 -> 4.9951688 | O30: =IF(I30>0,H30/I30,0) -> 426.9375 | P30: =IF(N30>0,(N30/L30/I30*H30+0)/N30,0) -> 1000 | Q30: =P30+ROW()/1000000 -> 1000 | R30: =SUMPRODUCT(($C$5:$C$34=C30)*($Q$5:$Q$34<Q30))+1 -> 4 | S30: =SUMPRODUCT(($C$5:$C$34=C30)*($Q$5:$Q$34<Q30)*$AH$5:$AH$34) -> 30.211897 | T30: =INDEX(Funnel!$B$5:$B$8,MATCH(C30,Funnel!$A$5:$A$8,0))-SUMIFS($AG$5:$AG$34,$C$5:$C$34,C30) -> 43.998904 | U30: =AG30+AI30 -> 4.9951688 | V30: =IF(L30>0,U30/L30,0) -> 11.7 | W30: =IF(I30>0,V30/I30,0) -> 26 | X30: =IF(E30="Slot",IF(N(G30)>0,ROUNDUP(W30/G30,0)*MAX(0,F30),0),W30*H30) -> 4995.1687 | Y30: =IF(U30>0,0,0) -> 0 | Z30: =IF(AND(D30="Channel",OR(E30="CPC",E30="CPA"),INDEX(Funnel!$B$5:$B$8,MATCH(C30,Funnel!$A$5:$A$8,0))>0),MIN(Assumptions!$D$49,J30*H30,IF(I30*L30>0,INDEX(Funnel!$B$5:$B$8,MATCH(C30,Funnel!$A$5:$A$8,0))/SUMPRODUCT(($C$5:$C$34=C30)*($D$5:$D$34="Channel")*(($E$5:$E$34="CPC")+($E$5:$E$34="CPA")))/(I30*L30)*H30,0)),0) -> 0 | AA30: =X30+Y30 -> 4995.1687 | AB30: =IF(U30>0,(X30+Y30)/U30,"–") -> 1000 | AC30: =SUMPRODUCT(--($Q$5:$Q$34<Q30))+1 -> 11 | AD30: =IF(AND(AH30>0,AI30>=AH30*0.999),"Used to capacity",IF(AI30>0,"Marginal (fills the gap)",IF(Z30>0,"Test only (wk 1–2)","Not used"))) -> Used to capacity | AE30: =IF(H30>0,Z30/H30,0) -> 0 | AF30: =AE30*I30 -> 0 | AG30: =AF30*L30 -> 0 | AH30: =MAX(0,N30-AG30) -> 4.9951688 | AI30: =MIN(AH30,MAX(0,T30-S30)) -> 4.9951688
A31: I1b-A | B31: I1b Employee referral sprint (bonus on hire) | C31: Automation | D31: Initiative | E31: CPA | F31: =Initiatives!D17 -> 146.71125 | H31: =F31 -> 146.71125 | I31: =Initiatives!D14 -> 0.45 | J31: =Initiatives!D13 -> 11 | K31: =J31*I31 -> 4.95 | L31: =INDEX(Funnel!$G$5:$G$8,MATCH(C31,Funnel!$A$5:$A$8,0))*M31 -> 0.326025 | M31: =Assumptions!$D$166 -> 1.15 | N31: =K31*L31 -> 1.6138237 | O31: =IF(I31>0,H31/I31,0) -> 326.025 | P31: =IF(N31>0,(N31/L31/I31*H31+0)/N31,0) -> 1000 | Q31: =P31+ROW()/1000000 -> 1000 | R31: =SUMPRODUCT(($C$5:$C$34=C31)*($Q$5:$Q$34<Q31))+1 -> 3 | S31: =SUMPRODUCT(($C$5:$C$34=C31)*($Q$5:$Q$34<Q31)*$AH$5:$AH$34) -> 3.3727995 | T31: =INDEX(Funnel!$B$5:$B$8,MATCH(C31,Funnel!$A$5:$A$8,0))-SUMIFS($AG$5:$AG$34,$C$5:$C$34,C31) -> 13.99664 | U31: =AG31+AI31 -> 1.6138237 | V31: =IF(L31>0,U31/L31,0) -> 4.95 | W31: =IF(I31>0,V31/I31,0) -> 11 | X31: =IF(E31="Slot",IF(N(G31)>0,ROUNDUP(W31/G31,0)*MAX(0,F31),0),W31*H31) -> 1613.8238 | Y31: =IF(U31>0,0,0) -> 0 | Z31: =IF(AND(D31="Channel",OR(E31="CPC",E31="CPA"),INDEX(Funnel!$B$5:$B$8,MATCH(C31,Funnel!$A$5:$A$8,0))>0),MIN(Assumptions!$D$49,J31*H31,IF(I31*L31>0,INDEX(Funnel!$B$5:$B$8,MATCH(C31,Funnel!$A$5:$A$8,0))/SUMPRODUCT(($C$5:$C$34=C31)*($D$5:$D$34="Channel")*(($E$5:$E$34="CPC")+($E$5:$E$34="CPA")))/(I31*L31)*H31,0)),0) -> 0 | AA31: =X31+Y31 -> 1613.8238 | AB31: =IF(U31>0,(X31+Y31)/U31,"–") -> 1000 | AC31: =SUMPRODUCT(--($Q$5:$Q$34<Q31))+1 -> 12 | AD31: =IF(AND(AH31>0,AI31>=AH31*0.999),"Used to capacity",IF(AI31>0,"Marginal (fills the gap)",IF(Z31>0,"Test only (wk 1–2)","Not used"))) -> Used to capacity | AE31: =IF(H31>0,Z31/H31,0) -> 0 | AF31: =AE31*I31 -> 0 | AG31: =AF31*L31 -> 0 | AH31: =MAX(0,N31-AG31) -> 1.6138237 | AI31: =MIN(AH31,MAX(0,T31-S31)) -> 1.6138237
A32: I1b-S | B32: I1b Employee referral sprint (bonus on hire) | C32: Supervisors | D32: Initiative | E32: CPA | F32: =Initiatives!E17 -> 123.165 | H32: =F32 -> 123.165 | I32: =Initiatives!E14 -> 0.45 | J32: =Initiatives!E13 -> 9 | K32: =J32*I32 -> 4.05 | L32: =INDEX(Funnel!$G$5:$G$8,MATCH(C32,Funnel!$A$5:$A$8,0))*M32 -> 0.2737 | M32: =Assumptions!$D$166 -> 1.15 | N32: =K32*L32 -> 1.108485 | O32: =IF(I32>0,H32/I32,0) -> 273.7 | P32: =IF(N32>0,(N32/L32/I32*H32+0)/N32,0) -> 1000 | Q32: =P32+ROW()/1000000 -> 1000 | R32: =SUMPRODUCT(($C$5:$C$34=C32)*($Q$5:$Q$34<Q32))+1 -> 3 | S32: =SUMPRODUCT(($C$5:$C$34=C32)*($Q$5:$Q$34<Q32)*$AH$5:$AH$34) -> 1.866634 | T32: =INDEX(Funnel!$B$5:$B$8,MATCH(C32,Funnel!$A$5:$A$8,0))-SUMIFS($AG$5:$AG$34,$C$5:$C$34,C32) -> 9.2250591 | U32: =AG32+AI32 -> 1.108485 | V32: =IF(L32>0,U32/L32,0) -> 4.05 | W32: =IF(I32>0,V32/I32,0) -> 9 | X32: =IF(E32="Slot",IF(N(G32)>0,ROUNDUP(W32/G32,0)*MAX(0,F32),0),W32*H32) -> 1108.485 | Y32: =IF(U32>0,0,0) -> 0 | Z32: =IF(AND(D32="Channel",OR(E32="CPC",E32="CPA"),INDEX(Funnel!$B$5:$B$8,MATCH(C32,Funnel!$A$5:$A$8,0))>0),MIN(Assumptions!$D$49,J32*H32,IF(I32*L32>0,INDEX(Funnel!$B$5:$B$8,MATCH(C32,Funnel!$A$5:$A$8,0))/SUMPRODUCT(($C$5:$C$34=C32)*($D$5:$D$34="Channel")*(($E$5:$E$34="CPC")+($E$5:$E$34="CPA")))/(I32*L32)*H32,0)),0) -> 0 | AA32: =X32+Y32 -> 1108.485 | AB32: =IF(U32>0,(X32+Y32)/U32,"–") -> 1000 | AC32: =SUMPRODUCT(--($Q$5:$Q$34<Q32))+1 -> 13 | AD32: =IF(AND(AH32>0,AI32>=AH32*0.999),"Used to capacity",IF(AI32>0,"Marginal (fills the gap)",IF(Z32>0,"Test only (wk 1–2)","Not used"))) -> Used to capacity | AE32: =IF(H32>0,Z32/H32,0) -> 0 | AF32: =AE32*I32 -> 0 | AG32: =AF32*L32 -> 0 | AH32: =MAX(0,N32-AG32) -> 1.108485 | AI32: =MIN(AH32,MAX(0,T32-S32)) -> 1.108485
A33: I2-E | B33: I2 Handwerk → Industrie (construction electricians) | C33: Electricians | D33: Initiative | E33: CPA | F33: =Initiatives!B27 -> 84 | H33: =F33 -> 84 | I33: =Initiatives!B28 -> 0.25 | J33: =Initiatives!B26 -> 118 | K33: =J33*I33 -> 29.5 | L33: =INDEX(Funnel!$G$5:$G$8,MATCH(C33,Funnel!$A$5:$A$8,0))*M33 -> 0.2835 | M33: =Assumptions!$D$171 -> 0.9 | N33: =K33*L33 -> 8.36325 | O33: =IF(I33>0,H33/I33,0) -> 336 | P33: =IF(N33>0,(N33/L33/I33*H33+Initiatives!B33)/N33,0) -> 1328.6701 | Q33: =P33+ROW()/1000000 -> 1328.6701 | R33: =SUMPRODUCT(($C$5:$C$34=C33)*($Q$5:$Q$34<Q33))+1 -> 4 | S33: =SUMPRODUCT(($C$5:$C$34=C33)*($Q$5:$Q$34<Q33)*$AH$5:$AH$34) -> 10.46115 | T33: =INDEX(Funnel!$B$5:$B$8,MATCH(C33,Funnel!$A$5:$A$8,0))-SUMIFS($AG$5:$AG$34,$C$5:$C$34,C33) -> 29.150585 | U33: =AG33+AI33 -> 8.36325 | V33: =IF(L33>0,U33/L33,0) -> 29.5 | W33: =IF(I33>0,V33/I33,0) -> 118 | X33: =IF(E33="Slot",IF(N(G33)>0,ROUNDUP(W33/G33,0)*MAX(0,F33),0),W33*H33) -> 9912 | Y33: =IF(U33>0,Initiatives!B33,0) -> 1200 | Z33: =IF(AND(D33="Channel",OR(E33="CPC",E33="CPA"),INDEX(Funnel!$B$5:$B$8,MATCH(C33,Funnel!$A$5:$A$8,0))>0),MIN(Assumptions!$D$49,J33*H33,IF(I33*L33>0,INDEX(Funnel!$B$5:$B$8,MATCH(C33,Funnel!$A$5:$A$8,0))/SUMPRODUCT(($C$5:$C$34=C33)*($D$5:$D$34="Channel")*(($E$5:$E$34="CPC")+($E$5:$E$34="CPA")))/(I33*L33)*H33,0)),0) -> 0 | AA33: =X33+Y33 -> 11112 | AB33: =IF(U33>0,(X33+Y33)/U33,"–") -> 1328.6701 | AC33: =SUMPRODUCT(--($Q$5:$Q$34<Q33))+1 -> 14 | AD33: =IF(AND(AH33>0,AI33>=AH33*0.999),"Used to capacity",IF(AI33>0,"Marginal (fills the gap)",IF(Z33>0,"Test only (wk 1–2)","Not used"))) -> Used to capacity | AE33: =IF(H33>0,Z33/H33,0) -> 0 | AF33: =AE33*I33 -> 0 | AG33: =AF33*L33 -> 0 | AH33: =MAX(0,N33-AG33) -> 8.36325 | AI33: =MIN(AH33,MAX(0,T33-S33)) -> 8.36325
A34: I3-M | B34: I3 Polish border corridor + PL pre-screener | C34: Mechatronics | D34: Initiative | E34: CPA | F34: =Initiatives!B38 -> 18.75 | H34: =F34 -> 18.75 | I34: =Initiatives!B39 -> 0.14 | J34: =Initiatives!B40 -> 350 | K34: =J34*I34 -> 49 | L34: =INDEX(Funnel!$G$5:$G$8,MATCH(C34,Funnel!$A$5:$A$8,0))*M34 -> 0.37125 | M34: =Assumptions!$D$176 -> 1 | N34: =MIN(K34*L34,Initiatives!B42) -> 18 | O34: =IF(I34>0,H34/I34,0) -> 133.92857 | P34: =IF(N34>0,(N34/L34/I34*H34+Initiatives!B46)/N34,0) -> 382.97258 | Q34: =P34+ROW()/1000000 -> 382.97262 | R34: =SUMPRODUCT(($C$5:$C$34=C34)*($Q$5:$Q$34<Q34))+1 -> 3 | S34: =SUMPRODUCT(($C$5:$C$34=C34)*($Q$5:$Q$34<Q34)*$AH$5:$AH$34) -> 12.211897 | T34: =INDEX(Funnel!$B$5:$B$8,MATCH(C34,Funnel!$A$5:$A$8,0))-SUMIFS($AG$5:$AG$34,$C$5:$C$34,C34) -> 43.998904 | U34: =AG34+AI34 -> 18 | V34: =IF(L34>0,U34/L34,0) -> 48.484848 | W34: =IF(I34>0,V34/I34,0) -> 346.32035 | X34: =IF(E34="Slot",IF(N(G34)>0,ROUNDUP(W34/G34,0)*MAX(0,F34),0),W34*H34) -> 6493.5065 | Y34: =IF(U34>0,Initiatives!B46,0) -> 400 | Z34: =IF(AND(D34="Channel",OR(E34="CPC",E34="CPA"),INDEX(Funnel!$B$5:$B$8,MATCH(C34,Funnel!$A$5:$A$8,0))>0),MIN(Assumptions!$D$49,J34*H34,IF(I34*L34>0,INDEX(Funnel!$B$5:$B$8,MATCH(C34,Funnel!$A$5:$A$8,0))/SUMPRODUCT(($C$5:$C$34=C34)*($D$5:$D$34="Channel")*(($E$5:$E$34="CPC")+($E$5:$E$34="CPA")))/(I34*L34)*H34,0)),0) -> 0 | AA34: =X34+Y34 -> 6893.5065 | AB34: =IF(U34>0,(X34+Y34)/U34,"–") -> 382.97258 | AC34: =SUMPRODUCT(--($Q$5:$Q$34<Q34))+1 -> 9 | AD34: =IF(AND(AH34>0,AI34>=AH34*0.999),"Used to capacity",IF(AI34>0,"Marginal (fills the gap)",IF(Z34>0,"Test only (wk 1–2)","Not used"))) -> Used to capacity | AE34: =IF(H34>0,Z34/H34,0) -> 0 | AF34: =AE34*I34 -> 0 | AG34: =AF34*L34 -> 0 | AH34: =MAX(0,N34-AG34) -> 18 | AI34: =MIN(AH34,MAX(0,T34-S34)) -> 18
A35: Total | J35: =SUM(J5:J34) -> 10564.32 | K35: =SUM(K5:K34) -> 2169.059 | N35: =SUM(N5:N34) -> 749.56969 | U35: =SUM(U5:U34) -> 100 | V35: =SUM(V5:V34) -> 307.97308 | W35: =SUM(W5:W34) -> 1494.5752 | X35: =SUM(X5:X34) -> 100655.85 | Y35: =SUM(Y5:Y34) -> 1600 | Z35: =SUM(Z5:Z34) -> 9000 | AA35: =SUM(AA5:AA34) -> 102255.85 | AB35: =IF(U35>0,(X35+Y35)/U35,0) -> 1022.5585 | AE35: =SUM(AE5:AE34) -> 68.87546 | AF35: =SUM(AF5:AF34) -> 12.188354 | AG35: =SUM(AG5:AG34) -> 3.6288123 | AI35: =SUM(AI5:AI34) -> 96.371188
A37: Role coverage check
B38: Role | C38: Openings | D38: Hires planned (test + allocated) | E38: Shortfall
B39: Electricians | C39: =Funnel!B5 -> 30 | D39: =SUMIFS($U$5:$U$34,$C$5:$C$34,B39) -> 30 | E39: =IF(C39-D39>0.05,C39-D39,0) -> 0
B40: Mechatronics | C40: =Funnel!B6 -> 45 | D40: =SUMIFS($U$5:$U$34,$C$5:$C$34,B40) -> 45 | E40: =IF(C40-D40>0.05,C40-D40,0) -> 0
B41: Automation | C41: =Funnel!B7 -> 15 | D41: =SUMIFS($U$5:$U$34,$C$5:$C$34,B41) -> 15 | E41: =IF(C41-D41>0.05,C41-D41,0) -> 0
B42: Supervisors | C42: =Funnel!B8 -> 10 | D42: =SUMIFS($U$5:$U$34,$C$5:$C$34,B42) -> 10 | E42: =IF(C42-D42>0.05,C42-D42,0) -> 0

Sheet Budget
B1: Part 2.4 — Recommended budget and allocation
B2: ="How: planned spend = paid media + initiatives + set-up (from Channels); reserve = "&TEXT(Assumptions!$D$48,"0%")&" of the total; rounded up to the next €"&TEXT(Assumptions!$D$51,"#,##0")&"." -> How: planned spend = paid media + initiatives + set-up (from Channels); reserve = 15% of the total; rounded up to the next €2,500.
B4: Paid channels: media (incl. test tranches) | C4: =SUMIFS(Channels!X5:X34,Channels!D5:D34,"Channel") -> 73209.314
B5: New initiatives: media + referral bonuses | C5: =SUMIFS(Channels!X5:X34,Channels!D5:D34,"Initiative") -> 27446.534
B6: New initiatives: fixed set-up costs (Polish translation, German creative + quiz tool) | C6: =Channels!Y35 -> 1600
B7: Media + initiatives to hit plan | C7: =C4+C5+C6 -> 102255.85
B8: …of which test tranches in weeks 1–2 (info) | C8: =Channels!Z35 -> 9000
B9: Planned spend (allocated to channels × weeks) | C9: =C7 -> 102255.85
B10: Reserve (unallocated; released from wk 3 by Tracker rules) | C10: =IF(Assumptions!$D$48<1,C9/(1-Assumptions!$D$48)*Assumptions!$D$48,0) -> 18045.15
B11: Total budget (calculated) | C11: =C9+C10 -> 120301
B12: RECOMMENDED BUDGET (rounded up, step B5) | C12: =IF(Assumptions!$D$51>0,ROUNDUP(C11/Assumptions!$D$51,0)*Assumptions!$D$51,C11) -> 122500
B13: Expected signed hires (capped by assessment slots, Funnel B26) | C13: =MIN(Channels!U35,Funnel!B26) -> 100
B14: Media cost per hire (planned spend ÷ hires) | C14: =IF(C13>0,C9/C13,0) -> 1022.5585
B15: All-in cost per hire if reserve is spent | C15: =IF(C13>0,C12/C13,0) -> 1225
B16: Share of recommended budget spent in weeks 1–2 | C16: =IF(C12>0,Weekly!N5/C12,0) -> 0.39747175
B19: By role
B20: Role | C20: Media € | D20: Fixed € | E20: …of which tests € | F20: Total € | G20: Hires | H20: Cost per hire | I20: Qualified applicants
B21: Electricians | C21: =SUMIFS(Channels!$X$5:$X$34,Channels!$C$5:$C$34,B21) -> 37932.763 | D21: =SUMIFS(Channels!$Y$5:$Y$34,Channels!$C$5:$C$34,B21) -> 1200 | E21: =SUMIFS(Channels!$Z$5:$Z$34,Channels!$C$5:$C$34,B21) -> 2250 | F21: =C21+D21 -> 39132.763 | G21: =SUMIFS(Channels!$U$5:$U$34,Channels!$C$5:$C$34,B21) -> 30 | H21: =IF(G21>0,F21/G21,0) -> 1304.4254 | I21: =SUMIFS(Channels!$V$5:$V$34,Channels!$C$5:$C$34,B21) -> 96.253095
B22: Mechatronics | C22: =SUMIFS(Channels!$X$5:$X$34,Channels!$C$5:$C$34,B22) -> 29741.06 | D22: =SUMIFS(Channels!$Y$5:$Y$34,Channels!$C$5:$C$34,B22) -> 400 | E22: =SUMIFS(Channels!$Z$5:$Z$34,Channels!$C$5:$C$34,B22) -> 2250 | F22: =C22+D22 -> 30141.06 | G22: =SUMIFS(Channels!$U$5:$U$34,Channels!$C$5:$C$34,B22) -> 45 | H22: =IF(G22>0,F22/G22,0) -> 669.80132 | I22: =SUMIFS(Channels!$V$5:$V$34,Channels!$C$5:$C$34,B22) -> 118.77312
B23: Automation | C23: =SUMIFS(Channels!$X$5:$X$34,Channels!$C$5:$C$34,B23) -> 17435.272 | D23: =SUMIFS(Channels!$Y$5:$Y$34,Channels!$C$5:$C$34,B23) -> 0 | E23: =SUMIFS(Channels!$Z$5:$Z$34,Channels!$C$5:$C$34,B23) -> 2250 | F23: =C23+D23 -> 17435.272 | G23: =SUMIFS(Channels!$U$5:$U$34,Channels!$C$5:$C$34,B23) -> 15 | H23: =IF(G23>0,F23/G23,0) -> 1162.3515 | I23: =SUMIFS(Channels!$V$5:$V$34,Channels!$C$5:$C$34,B23) -> 51.825553
B24: Supervisors | C24: =SUMIFS(Channels!$X$5:$X$34,Channels!$C$5:$C$34,B24) -> 15546.753 | D24: =SUMIFS(Channels!$Y$5:$Y$34,Channels!$C$5:$C$34,B24) -> 0 | E24: =SUMIFS(Channels!$Z$5:$Z$34,Channels!$C$5:$C$34,B24) -> 2250 | F24: =C24+D24 -> 15546.753 | G24: =SUMIFS(Channels!$U$5:$U$34,Channels!$C$5:$C$34,B24) -> 10 | H24: =IF(G24>0,F24/G24,0) -> 1554.6753 | I24: =SUMIFS(Channels!$V$5:$V$34,Channels!$C$5:$C$34,B24) -> 41.121307
B25: Total | C25: =SUM(C21:C24) -> 100655.85 | D25: =SUM(D21:D24) -> 1600 | E25: =SUM(E21:E24) -> 9000 | F25: =SUM(F21:F24) -> 102255.85 | G25: =SUM(G21:G24) -> 100 | H25: =IF(G25>0,F25/G25,0) -> 1022.5585 | I25: =SUM(I21:I24) -> 307.97308
B27: By channel
B28: Channel | C28: Total € | D28: Hires | E28: Cost per hire | F28: Share of planned spend
B29: Organic (Tesla careers, BA Jobbörse, Google for Jobs) | C29: =SUMIFS(Channels!$AA$5:$AA$34,Channels!$B$5:$B$34,B29) -> 0 | D29: =SUMIFS(Channels!$U$5:$U$34,Channels!$B$5:$B$34,B29) -> 20.02378 | E29: =IF(D29>0,C29/D29,"–") -> 0 | F29: =IF($C$9>0,C29/$C$9,0) -> 0
B30: Programmatic job ads (Joveo: Indeed, Jooble, Talent.com, Kimeta, meinestadt…) | C30: =SUMIFS(Channels!$AA$5:$AA$34,Channels!$B$5:$B$34,B30) -> 35674.597 | D30: =SUMIFS(Channels!$U$5:$U$34,Channels!$B$5:$B$34,B30) -> 16.658203 | E30: =IF(D30>0,C30/D30,"–") -> 2141.5634 | F30: =IF($C$9>0,C30/$C$9,0) -> 0.34887587
B31: StepStone (30-day single ad) | C31: =SUMIFS(Channels!$AA$5:$AA$34,Channels!$B$5:$B$34,B31) -> 5796 | D31: =SUMIFS(Channels!$U$5:$U$34,Channels!$B$5:$B$34,B31) -> 3.70575 | E31: =IF(D31>0,C31/D31,"–") -> 1564.0559 | F31: =IF($C$9>0,C31/$C$9,0) -> 0.056681355
B32: LinkedIn (promoted jobs + InMail) | C32: =SUMIFS(Channels!$AA$5:$AA$34,Channels!$B$5:$B$34,B32) -> 27238.716 | D32: =SUMIFS(Channels!$U$5:$U$34,Channels!$B$5:$B$34,B32) -> 16.143187 | E32: =IF(D32>0,C32/D32,"–") -> 1687.3196 | F32: =IF($C$9>0,C32/$C$9,0) -> 0.26637808
B33: Meta social (FB/IG lead ads, 75 km geo) | C33: =SUMIFS(Channels!$AA$5:$AA$34,Channels!$B$5:$B$34,B33) -> 1500 | D33: =SUMIFS(Channels!$U$5:$U$34,Channels!$B$5:$B$34,B33) -> 0.62804129 | E33: =IF(D33>0,C33/D33,"–") -> 2388.378 | F33: =IF($C$9>0,C33/$C$9,0) -> 0.014669088
B34: Google Search ads (job-intent keywords) | C34: =SUMIFS(Channels!$AA$5:$AA$34,Channels!$B$5:$B$34,B34) -> 3000 | D34: =SUMIFS(Channels!$U$5:$U$34,Channels!$B$5:$B$34,B34) -> 0.87160999 | E34: =IF(D34>0,C34/D34,"–") -> 3441.9064 | F34: =IF($C$9>0,C34/$C$9,0) -> 0.029338175
B35: I1a Talent rediscovery (past applicants in ATS) | C35: =SUMIFS(Channels!$AA$5:$AA$34,Channels!$B$5:$B$34,B35) -> 63.3 | D35: =SUMIFS(Channels!$U$5:$U$34,Channels!$B$5:$B$34,B35) -> 4.628451 | E35: =IF(D35>0,C35/D35,"–") -> 13.676282 | F35: =IF($C$9>0,C35/$C$9,0) -> 0.0006190355
B36: I1b Employee referral sprint (bonus on hire) | C36: =SUMIFS(Channels!$AA$5:$AA$34,Channels!$B$5:$B$34,B36) -> 10977.728 | D36: =SUMIFS(Channels!$U$5:$U$34,Channels!$B$5:$B$34,B36) -> 10.977728 | E36: =IF(D36>0,C36/D36,"–") -> 1000 | F36: =IF($C$9>0,C36/$C$9,0) -> 0.1073555
B37: I2 Handwerk → Industrie (construction electricians) | C37: =SUMIFS(Channels!$AA$5:$AA$34,Channels!$B$5:$B$34,B37) -> 11112 | D37: =SUMIFS(Channels!$U$5:$U$34,Channels!$B$5:$B$34,B37) -> 8.36325 | E37: =IF(D37>0,C37/D37,"–") -> 1328.6701 | F37: =IF($C$9>0,C37/$C$9,0) -> 0.1086686
B38: I3 Polish border corridor + PL pre-screener | C38: =SUMIFS(Channels!$AA$5:$AA$34,Channels!$B$5:$B$34,B38) -> 6893.5065 | D38: =SUMIFS(Channels!$U$5:$U$34,Channels!$B$5:$B$34,B38) -> 18 | E38: =IF(D38>0,C38/D38,"–") -> 382.97258 | F38: =IF($C$9>0,C38/$C$9,0) -> 0.067414301
B39: Total | C39: =SUM(C29:C38) -> 102255.85 | D39: =SUM(D29:D38) -> 100
B40: =IF(LEFT(Summary!$C$19,1)<>"✓",Summary!$C$19,IF(Assumptions!$D$48>=1,"✗ reserve share must be below 100%",IF(ABS(C39-C9)<1,"✓ ties to planned spend","✗ check: channel totals ≠ planned spend"))) -> ✓ ties to planned spend
B42: Part 2.5 — What 30% less budget buys
B43: ="If money is cut: drop the most expensive cost-per-hire cells first and keep the reserve at "&TEXT(Assumptions!$D$48,"0%")&". If assessment slots run out, hires are capped (scenario detail below)." -> If money is cut: drop the most expensive cost-per-hire cells first and keep the reserve at 15%. If assessment slots run out, hires are capped (scenario detail below).
B44: Budget level | C44: Total budget € | D44: Electricians | E44: Mechatronics | F44: Automation | G44: Supervisors | H44: Total hires | I44: Cost per hire
B45: =Budget!F51 -> 1 | C45: =Budget!F52 -> 122500 | D45: =Budget!F87 -> 30 | E45: =Budget!F88 -> 45 | F45: =Budget!F89 -> 15 | G45: =Budget!F90 -> 10 | H45: =SUM(D45:G45) -> 100 | I45: =IF(H45>0,C45/H45,0) -> 1225
B46: =Budget!G51 -> 0.7 | C46: =Budget!G52 -> 85750 | D46: =Budget!G87 -> 20.5254 | E46: =Budget!G88 -> 43.980041 | F46: =Budget!G89 -> 14.49498 | G46: =Budget!G90 -> 8.0573858 | H46: =SUM(D46:G46) -> 87.057806 | I46: =IF(H46>0,C46/H46,0) -> 984.97772
A49: Budget scenarios: cut the most expensive cost-per-hire cells first
A50: Cells are cut in order of planned cost per hire (most expensive first). A cut removes media first; a cell's set-up cost is only saved once its media is fully cut, so partially cut cells keep their set-up.
E51: Budget level → | F51: =1 -> 1 | G51: =1-Assumptions!$D$52 -> 0.7
E52: Total budget € | F52: =Budget!$C$12*F51 -> 122500 | G52: =Budget!$C$12*G51 -> 85750
E53: Spend available (after reserve) € | F53: =F52*(1-Assumptions!$D$48) -> 104125 | G53: =G52*(1-Assumptions!$D$48) -> 72887.5
E54: Savings needed € | F54: =MAX(0,Budget!$C$9-F53) -> 0 | G54: =MAX(0,Budget!$C$9-G53) -> 29368.348
A55: ID (+ to expand) | B55: Role | C55: Total € (media + fixed) | D55: Sort key (planned cost per hire) | E55: Hires | F55: Hires @ recommended | G55: Hires @ cut | J55: Cut € @ recommended | K55: Cut € @ cut | N55: Media € | O55: Qualified @ recommended | P55: Qualified @ cut
A56: =Channels!A5 -> C01 | B56: =Channels!C5 -> Electricians | C56: =Channels!AA5 -> 0 | D56: =IF(ISNUMBER(Channels!AB5),Channels!AB5,0)+ROW()/1000000 -> 5.6e-05 | E56: =Channels!U5 -> 5.788125 | F56: =IF(N56>0,E56*MAX(0,N56-MIN(J56,N56))/N56,IF(C56>0,E56*(1-J56/C56),E56)) -> 5.788125 | G56: =IF(N56>0,E56*MAX(0,N56-MIN(K56,N56))/N56,IF(C56>0,E56*(1-K56/C56),E56)) -> 5.788125 | J56: =MIN(C56,MAX(0,F$54-SUMPRODUCT(($D$56:$D$85>D56)*$C$56:$C$85))) -> 0 | K56: =MIN(C56,MAX(0,G$54-SUMPRODUCT(($D$56:$D$85>D56)*$C$56:$C$85))) -> 0 | N56: =Channels!X5 -> 0 | O56: =IF(E56>0,F56*Channels!V5/E56,0) -> 18.375 | P56: =IF(E56>0,G56*Channels!V5/E56,0) -> 18.375
A57: =Channels!A6 -> C02 | B57: =Channels!C6 -> Mechatronics | C57: =Channels!AA6 -> 0 | D57: =IF(ISNUMBER(Channels!AB6),Channels!AB6,0)+ROW()/1000000 -> 5.7e-05 | E57: =Channels!U6 -> 10.265063 | F57: =IF(N57>0,E57*MAX(0,N57-MIN(J57,N57))/N57,IF(C57>0,E57*(1-J57/C57),E57)) -> 10.265063 | G57: =IF(N57>0,E57*MAX(0,N57-MIN(K57,N57))/N57,IF(C57>0,E57*(1-K57/C57),E57)) -> 10.265063 | J57: =MIN(C57,MAX(0,F$54-SUMPRODUCT(($D$56:$D$85>D57)*$C$56:$C$85))) -> 0 | K57: =MIN(C57,MAX(0,G$54-SUMPRODUCT(($D$56:$D$85>D57)*$C$56:$C$85))) -> 0 | N57: =Channels!X6 -> 0 | O57: =IF(E57>0,F57*Channels!V6/E57,0) -> 27.65 | P57: =IF(E57>0,G57*Channels!V6/E57,0) -> 27.65
A58: =Channels!A7 -> C03 | B58: =Channels!C7 -> Automation | C58: =Channels!AA7 -> 0 | D58: =IF(ISNUMBER(Channels!AB7),Channels!AB7,0)+ROW()/1000000 -> 5.8e-05 | E58: =Channels!U7 -> 2.6294625 | F58: =IF(N58>0,E58*MAX(0,N58-MIN(J58,N58))/N58,IF(C58>0,E58*(1-J58/C58),E58)) -> 2.6294625 | G58: =IF(N58>0,E58*MAX(0,N58-MIN(K58,N58))/N58,IF(C58>0,E58*(1-K58/C58),E58)) -> 2.6294625 | J58: =MIN(C58,MAX(0,F$54-SUMPRODUCT(($D$56:$D$85>D58)*$C$56:$C$85))) -> 0 | K58: =MIN(C58,MAX(0,G$54-SUMPRODUCT(($D$56:$D$85>D58)*$C$56:$C$85))) -> 0 | N58: =Channels!X7 -> 0 | O58: =IF(E58>0,F58*Channels!V7/E58,0) -> 9.275 | P58: =IF(E58>0,G58*Channels!V7/E58,0) -> 9.275
A59: =Channels!A8 -> C04 | B59: =Channels!C8 -> Supervisors | C59: =Channels!AA8 -> 0 | D59: =IF(ISNUMBER(Channels!AB8),Channels!AB8,0)+ROW()/1000000 -> 5.9e-05 | E59: =Channels!U8 -> 1.34113 | F59: =IF(N59>0,E59*MAX(0,N59-MIN(J59,N59))/N59,IF(C59>0,E59*(1-J59/C59),E59)) -> 1.34113 | G59: =IF(N59>0,E59*MAX(0,N59-MIN(K59,N59))/N59,IF(C59>0,E59*(1-K59/C59),E59)) -> 1.34113 | J59: =MIN(C59,MAX(0,F$54-SUMPRODUCT(($D$56:$D$85>D59)*$C$56:$C$85))) -> 0 | K59: =MIN(C59,MAX(0,G$54-SUMPRODUCT(($D$56:$D$85>D59)*$C$56:$C$85))) -> 0 | N59: =Channels!X8 -> 0 | O59: =IF(E59>0,F59*Channels!V8/E59,0) -> 5.635 | P59: =IF(E59>0,G59*Channels!V8/E59,0) -> 5.635
A60: =Channels!A9 -> C05 | B60: =Channels!C9 -> Electricians | C60: =Channels!AA9 -> 20343.013 | D60: =IF(ISNUMBER(Channels!AB9),Channels!AB9,0)+ROW()/1000000 -> 2271.605 | E60: =Channels!U9 -> 8.9553481 | F60: =IF(N60>0,E60*MAX(0,N60-MIN(J60,N60))/N60,IF(C60>0,E60*(1-J60/C60),E60)) -> 8.9553481 | G60: =IF(N60>0,E60*MAX(0,N60-MIN(K60,N60))/N60,IF(C60>0,E60*(1-K60/C60),E60)) -> 0 | J60: =MIN(C60,MAX(0,F$54-SUMPRODUCT(($D$56:$D$85>D60)*$C$56:$C$85))) -> 0 | K60: =MIN(C60,MAX(0,G$54-SUMPRODUCT(($D$56:$D$85>D60)*$C$56:$C$85))) -> 20343.013 | N60: =Channels!X9 -> 20343.013 | O60: =IF(E60>0,F60*Channels!V9/E60,0) -> 28.429676 | P60: =IF(E60>0,G60*Channels!V9/E60,0) -> 0
A61: =Channels!A10 -> C06 | B61: =Channels!C10 -> Mechatronics | C61: =Channels!AA10 -> 13831.584 | D61: =IF(ISNUMBER(Channels!AB10),Channels!AB10,0)+ROW()/1000000 -> 1927.4224 | E61: =Channels!U10 -> 7.1762083 | F61: =IF(N61>0,E61*MAX(0,N61-MIN(J61,N61))/N61,IF(C61>0,E61*(1-J61/C61),E61)) -> 7.1762083 | G61: =IF(N61>0,E61*MAX(0,N61-MIN(K61,N61))/N61,IF(C61>0,E61*(1-K61/C61),E61)) -> 7.1762083 | J61: =MIN(C61,MAX(0,F$54-SUMPRODUCT(($D$56:$D$85>D61)*$C$56:$C$85))) -> 0 | K61: =MIN(C61,MAX(0,G$54-SUMPRODUCT(($D$56:$D$85>D61)*$C$56:$C$85))) -> 0 | N61: =Channels!X10 -> 13831.584 | O61: =IF(E61>0,F61*Channels!V10/E61,0) -> 19.329854 | P61: =IF(E61>0,G61*Channels!V10/E61,0) -> 19.329854
A62: =Channels!A11 -> C07 | B62: =Channels!C11 -> Automation | C62: =Channels!AA11 -> 750 | D62: =IF(ISNUMBER(Channels!AB11),Channels!AB11,0)+ROW()/1000000 -> 2524.0055 | E62: =Channels!U11 -> 0.29714674 | F62: =IF(N62>0,E62*MAX(0,N62-MIN(J62,N62))/N62,IF(C62>0,E62*(1-J62/C62),E62)) -> 0.29714674 | G62: =IF(N62>0,E62*MAX(0,N62-MIN(K62,N62))/N62,IF(C62>0,E62*(1-K62/C62),E62)) -> 0 | J62: =MIN(C62,MAX(0,F$54-SUMPRODUCT(($D$56:$D$85>D62)*$C$56:$C$85))) -> 0 | K62: =MIN(C62,MAX(0,G$54-SUMPRODUCT(($D$56:$D$85>D62)*$C$56:$C$85))) -> 750 | N62: =Channels!X11 -> 750 | O62: =IF(E62>0,F62*Channels!V11/E62,0) -> 1.0481366 | P62: =IF(E62>0,G62*Channels!V11/E62,0) -> 0
A63: =Channels!A12 -> C08 | B63: =Channels!C12 -> Supervisors | C63: =Channels!AA12 -> 750 | D63: =IF(ISNUMBER(Channels!AB12),Channels!AB12,0)+ROW()/1000000 -> 3267.9739 | E63: =Channels!U12 -> 0.2295 | F63: =IF(N63>0,E63*MAX(0,N63-MIN(J63,N63))/N63,IF(C63>0,E63*(1-J63/C63),E63)) -> 0.2295 | G63: =IF(N63>0,E63*MAX(0,N63-MIN(K63,N63))/N63,IF(C63>0,E63*(1-K63/C63),E63)) -> 0 | J63: =MIN(C63,MAX(0,F$54-SUMPRODUCT(($D$56:$D$85>D63)*$C$56:$C$85))) -> 0 | K63: =MIN(C63,MAX(0,G$54-SUMPRODUCT(($D$56:$D$85>D63)*$C$56:$C$85))) -> 750 | N63: =Channels!X12 -> 750 | O63: =IF(E63>0,F63*Channels!V12/E63,0) -> 0.96428571 | P63: =IF(E63>0,G63*Channels!V12/E63,0) -> 0
A64: =Channels!A13 -> C09 | B64: =Channels!C13 -> Electricians | C64: =Channels!AA13 -> 2898 | D64: =IF(ISNUMBER(Channels!AB13),Channels!AB13,0)+ROW()/1000000 -> 1703.7038 | E64: =Channels!U13 -> 1.701 | F64: =IF(N64>0,E64*MAX(0,N64-MIN(J64,N64))/N64,IF(C64>0,E64*(1-J64/C64),E64)) -> 1.701 | G64: =IF(N64>0,E64*MAX(0,N64-MIN(K64,N64))/N64,IF(C64>0,E64*(1-K64/C64),E64)) -> 1.701 | J64: =MIN(C64,MAX(0,F$54-SUMPRODUCT(($D$56:$D$85>D64)*$C$56:$C$85))) -> 0 | K64: =MIN(C64,MAX(0,G$54-SUMPRODUCT(($D$56:$D$85>D64)*$C$56:$C$85))) -> 0 | N64: =Channels!X13 -> 2898 | O64: =IF(E64>0,F64*Channels!V13/E64,0) -> 5.4 | P64: =IF(E64>0,G64*Channels!V13/E64,0) -> 5.4
A65: =Channels!A14 -> C10 | B65: =Channels!C14 -> Mechatronics | C65: =Channels!AA14 -> 2898 | D65: =IF(ISNUMBER(Channels!AB14),Channels!AB14,0)+ROW()/1000000 -> 1445.5668 | E65: =Channels!U14 -> 2.00475 | F65: =IF(N65>0,E65*MAX(0,N65-MIN(J65,N65))/N65,IF(C65>0,E65*(1-J65/C65),E65)) -> 2.00475 | G65: =IF(N65>0,E65*MAX(0,N65-MIN(K65,N65))/N65,IF(C65>0,E65*(1-K65/C65),E65)) -> 2.00475 | J65: =MIN(C65,MAX(0,F$54-SUMPRODUCT(($D$56:$D$85>D65)*$C$56:$C$85))) -> 0 | K65: =MIN(C65,MAX(0,G$54-SUMPRODUCT(($D$56:$D$85>D65)*$C$56:$C$85))) -> 0 | N65: =Channels!X14 -> 2898 | O65: =IF(E65>0,F65*Channels!V14/E65,0) -> 5.4 | P65: =IF(E65>0,G65*Channels!V14/E65,0) -> 5.4
A66: =Channels!A15 -> C11 | B66: =Channels!C15 -> Automation | C66: =Channels!AA15 -> 0 | D66: =IF(ISNUMBER(Channels!AB15),Channels!AB15,0)+ROW()/1000000 -> 6.6e-05 | E66: =Channels!U15 -> 0 | F66: =IF(N66>0,E66*MAX(0,N66-MIN(J66,N66))/N66,IF(C66>0,E66*(1-J66/C66),E66)) -> 0 | G66: =IF(N66>0,E66*MAX(0,N66-MIN(K66,N66))/N66,IF(C66>0,E66*(1-K66/C66),E66)) -> 0 | J66: =MIN(C66,MAX(0,F$54-SUMPRODUCT(($D$56:$D$85>D66)*$C$56:$C$85))) -> 0 | K66: =MIN(C66,MAX(0,G$54-SUMPRODUCT(($D$56:$D$85>D66)*$C$56:$C$85))) -> 0 | N66: =Channels!X15 -> 0 | O66: =IF(E66>0,F66*Channels!V15/E66,0) -> 0 | P66: =IF(E66>0,G66*Channels!V15/E66,0) -> 0
A67: =Channels!A16 -> C12 | B67: =Channels!C16 -> Supervisors | C67: =Channels!AA16 -> 0 | D67: =IF(ISNUMBER(Channels!AB16),Channels!AB16,0)+ROW()/1000000 -> 6.7e-05 | E67: =Channels!U16 -> 0 | F67: =IF(N67>0,E67*MAX(0,N67-MIN(J67,N67))/N67,IF(C67>0,E67*(1-J67/C67),E67)) -> 0 | G67: =IF(N67>0,E67*MAX(0,N67-MIN(K67,N67))/N67,IF(C67>0,E67*(1-K67/C67),E67)) -> 0 | J67: =MIN(C67,MAX(0,F$54-SUMPRODUCT(($D$56:$D$85>D67)*$C$56:$C$85))) -> 0 | K67: =MIN(C67,MAX(0,G$54-SUMPRODUCT(($D$56:$D$85>D67)*$C$56:$C$85))) -> 0 | N67: =Channels!X16 -> 0 | O67: =IF(E67>0,F67*Channels!V16/E67,0) -> 0 | P67: =IF(E67>0,G67*Channels!V16/E67,0) -> 0
... A84: =Channels!A33 -> I2-E | B84: =Channels!C33 -> Electricians | C84: =Channels!AA33 -> 11112 | D84: =IF(ISNUMBER(Channels!AB33),Channels!AB33,0)+ROW()/1000000 -> 1328.6702 | E84: =Channels!U33 -> 8.36325 | F84: =IF(N84>0,E84*MAX(0,N84-MIN(J84,N84))/N84,IF(C84>0,E84*(1-J84/C84),E84)) -> 8.36325 | G84: =IF(N84>0,E84*MAX(0,N84-MIN(K84,N84))/N84,IF(C84>0,E84*(1-K84/C84),E84)) -> 8.36325 | J84: =MIN(C84,MAX(0,F$54-SUMPRODUCT(($D$56:$D$85>D84)*$C$56:$C$85))) -> 0 | K84: =MIN(C84,MAX(0,G$54-SUMPRODUCT(($D$56:$D$85>D84)*$C$56:$C$85))) -> 0 | N84: =Channels!X33 -> 9912 | O84: =IF(E84>0,F84*Channels!V33/E84,0) -> 29.5 | P84: =IF(E84>0,G84*Channels!V33/E84,0) -> 29.5
A85: =Channels!A34 -> I3-M | B85: =Channels!C34 -> Mechatronics | C85: =Channels!AA34 -> 6893.5065 | D85: =IF(ISNUMBER(Channels!AB34),Channels!AB34,0)+ROW()/1000000 -> 382.97267 | E85: =Channels!U34 -> 18 | F85: =IF(Assumptions!$D$10>=1,IF(N85>0,E85*MAX(0,N85-MIN(J85,N85))/N85,IF(C85>0,E85*(1-J85/C85),E85)),MIN(IF(N85>0,E85*MAX(0,N85-MIN(J85,N85))/N85,IF(C85>0,E85*(1-J85/C85),E85)),Assumptions!$D$10/(1-Assumptions!$D$10)*SUMIFS(F$56:F$84,$B$56:$B$84,"Mechatronics"))) -> 18 | G85: =IF(Assumptions!$D$10>=1,IF(N85>0,E85*MAX(0,N85-MIN(K85,N85))/N85,IF(C85>0,E85*(1-K85/C85),E85)),MIN(IF(N85>0,E85*MAX(0,N85-MIN(K85,N85))/N85,IF(C85>0,E85*(1-K85/C85),E85)),Assumptions!$D$10/(1-Assumptions!$D$10)*SUMIFS(G$56:G$84,$B$56:$B$84,"Mechatronics"))) -> 17.592016 | J85: =MIN(C85,MAX(0,F$54-SUMPRODUCT(($D$56:$D$85>D85)*$C$56:$C$85))) -> 0 | K85: =MIN(C85,MAX(0,G$54-SUMPRODUCT(($D$56:$D$85>D85)*$C$56:$C$85))) -> 0 | N85: =Channels!X34 -> 6493.5065 | O85: =IF(E85>0,F85*Channels!V34/E85,0) -> 48.484848 | P85: =IF(E85>0,G85*Channels!V34/E85,0) -> 47.385903
E86: Hires by role
E87: Electricians | F87: =SUMIFS(F$56:F$85,$B$56:$B$85,$E87)*F$95 -> 30 | G87: =SUMIFS(G$56:G$85,$B$56:$B$85,$E87)*G$95 -> 20.5254
E88: Mechatronics | F88: =SUMIFS(F$56:F$85,$B$56:$B$85,$E88)*F$95 -> 45 | G88: =SUMIFS(G$56:G$85,$B$56:$B$85,$E88)*G$95 -> 43.980041
E89: Automation | F89: =SUMIFS(F$56:F$85,$B$56:$B$85,$E89)*F$95 -> 15 | G89: =SUMIFS(G$56:G$85,$B$56:$B$85,$E89)*G$95 -> 14.49498
E90: Supervisors | F90: =SUMIFS(F$56:F$85,$B$56:$B$85,$E90)*F$95 -> 10 | G90: =SUMIFS(G$56:G$85,$B$56:$B$85,$E90)*G$95 -> 8.0573858
E91: Total | F91: =SUM(F87:F90) -> 100 | G91: =SUM(G87:G90) -> 87.057806
E92: Cost per hire | F92: =IF(F91>0,F52/F91,0) -> 1225 | G92: =IF(G91>0,G52/G91,0) -> 984.97772
E94: Qualified applicants (before capacity cap) | F94: =SUM(O56:O85) -> 307.97308 | G94: =SUM(P56:P85) -> 265.20399
E95: Capacity factor (assessment slots ÷ qualified, max 1) | F95: =IF(F94>0,MIN(1,Funnel!$B$22/F94),1) -> 1 | G95: =IF(G94>0,MIN(1,Funnel!$B$22/G94),1) -> 1
A97: Hires by role are scaled by the capacity factor: if a scenario's qualified applicants exceed the assessment slots, only the share that can be assessed turns into hires (same rule as Budget C13).

Sheet Weekly
A1: Week-by-week plan: cash out, qualified flow vs 55/week, signatures
A2: Cash by week: tests in weeks 1–2, StepStone ads and set-up in week 1, media by the weekly shares, referral bonuses when people sign (signatures land ~24 days after application, rounded to whole weeks).
A3: Week | B3: Start (Tue) | C3: End | D3: Spend share E/M/A | E3: Spend share Supervisors | F3: Signing share E/M/A | G3: Signing share Supervisors | H3: CPC/CPA media after tests € | I3: StepStone ads € | J3: Referral bonuses € | K3: Set-up costs € | L3: Test tranches € | M3: Cash out € | N3: Cumulative € | O3: Applications | P3: Qualified arriving | Q3: Assessment slots | R3: Slot use | S3: Flag | T3: Signed (E/M/A) | U3: Signed (Supervisors) | V3: Signed total | W3: Cum. signed | X3: Test share | Y3: Rediscovery share | Z3: Input share (Assumptions W1–W11) | AA3: Supervisor share before re-scaling (useful days only) | AB3: I2 share (from go-live) | AC3: I3 share (from go-live) | AD3: I2 share before re-scaling | AE3: I3 share before re-scaling | AF3: I2 live days (fallback) | AG3: I3 live days (fallback)
A4: 1 | B4: =Assumptions!$D$7+7*(A4-1) -> 46315 | C4: =MIN(B4+6,Assumptions!$D$8) -> 46321 | D4: =IF(SUMPRODUCT(($B$4:$B$14<=Funnel!$B$19)*$Z$4:$Z$14)>0,IF(B4<=Funnel!$B$19,Z4,0)/SUMPRODUCT(($B$4:$B$14<=Funnel!$B$19)*$Z$4:$Z$14),0) -> 0.316 | E4: =IF(SUM($AA$4:$AA$14)>0,AA4/SUM($AA$4:$AA$14),0) -> 0.39212906 | F4: =IF(A4-ROUNDUP(Funnel!$B$15/7,0)>=1,INDEX($D$4:$D$14,A4-ROUNDUP(Funnel!$B$15/7,0)),0) -> 0 | G4: =IF(A4-ROUNDUP(Funnel!$B$16/7,0)>=1,INDEX($E$4:$E$14,A4-ROUNDUP(Funnel!$B$16/7,0)),0) -> 0 | H4: =($F$19-$L$19-$L$23)*D4+$L$19*AB4+$L$23*AC4+$F$20*E4+$F$31*Y4 -> 21493.924 | I4: =IF(A4=1,$F$21,0) -> 5796 | J4: =$F$22*F4+$F$23*G4 -> 0 | K4: =IF(A4=1,Budget!$C$6,0) -> 1600 | L4: =$F$24*X4 -> 3600 | M4: =SUM(H4:L4) -> 32489.924 | N4: =SUM($M$4:M4) -> 32489.924 | O4: =(Funnel!$M$5+Funnel!$M$6+Funnel!$M$7-$F$27-$F$34-$L$20-$L$24)*D4+$L$20*AB4+$L$24*AC4+(Funnel!$M$8-$F$28-$F$35)*E4+($F$27+$F$28)*X4+($F$34+$F$35)*Y4 -> 376.18954 | P4: =(Funnel!$O$5+Funnel!$O$6+Funnel!$O$7-$F$25-$F$32-$L$21-$L$25)*D4+$L$21*AB4+$L$25*AC4+(Funnel!$O$8-$F$26-$F$33)*E4+($F$25+$F$26)*X4+($F$32+$F$33)*Y4 -> 86.193289 | Q4: =Assumptions!$D$9*MAX(0,MIN(C4+Assumptions!$D$21,Funnel!$B$17)-MAX(IF(A4=1,Funnel!$B$13,B4+Assumptions!$D$21),Funnel!$B$13)+1)/7 -> 86.428571 | R4: =IF(Q4>0,P4/Q4,IF(P4>0,9.99,0)) -> 0.99727772 | S4: =IF(P4>Q4+0.5,"OVER "&Assumptions!$D$9&"/wk – pace down",IF(R4>Assumptions!$D$102,"Full",IF(AND(Q4>=Assumptions!$D$103,P4<Assumptions!$D$103),"Under "&Assumptions!$D$103&" – release reserve",""))) -> Full | T4: =$F$38*(F4*(Budget!$G$21+Budget!$G$22+Budget!$G$23-$F$29-$F$36-$L$22-$L$26)+IF(A4-ROUNDUP(Funnel!$B$15/7,0)>=1,INDEX($X$4:$X$14,A4-ROUNDUP(Funnel!$B$15/7,0))*$F$29+INDEX($Y$4:$Y$14,A4-ROUNDUP(Funnel!$B$15/7,0))*$F$36+INDEX($AB$4:$AB$14,A4-ROUNDUP(Funnel!$B$15/7,0))*$L$22+INDEX($AC$4:$AC$14,A4-ROUNDUP(Funnel!$B$15/7,0))*$L$26,0)) -> 0 | U4: =$F$38*(G4*(Budget!$G$24-$F$30-$F$37)+IF(A4-ROUNDUP(Funnel!$B$16/7,0)>=1,INDEX($X$4:$X$14,A4-ROUNDUP(Funnel!$B$16/7,0))*$F$30+INDEX($Y$4:$Y$14,A4-ROUNDUP(Funnel!$B$16/7,0))*$F$37,0)) -> 0 | V4: =T4+U4 -> 0 | W4: =SUM($V$4:V4) -> 0 | X4: =IF(A4=1,Assumptions!$D$50,IF(A4=2,1-Assumptions!$D$50,0)) -> 0.4 | Y4: =Assumptions!$D$93 -> 0.6 | Z4: =Assumptions!$D$53 -> 0.316 | AA4: =D4*IF(MAX(0,MIN(C4,Funnel!$B$19)-B4+1)>0,MAX(0,MIN(C4,Funnel!$B$20)-B4+1)/MAX(0,MIN(C4,Funnel!$B$19)-B4+1),0) -> 0.316 | AB4: =IF(SUM($AD$4:$AD$14)>0,AD4/SUM($AD$4:$AD$14),IF(SUM($AF$4:$AF$14)>0,AF4/SUM($AF$4:$AF$14),0)) -> 0.20885658 | AC4: =IF(SUM($AE$4:$AE$14)>0,AE4/SUM($AE$4:$AE$14),IF(SUM($AG$4:$AG$14)>0,AG4/SUM($AG$4:$AG$14),0)) -> 0 | AD4: =D4*IF(MAX(0,MIN(C4,Funnel!$B$19)-B4+1)>0,MAX(0,MIN(C4,Funnel!$B$19)-MAX(B4,Assumptions!$D$7+Assumptions!$D$181)+1)/MAX(0,MIN(C4,Funnel!$B$19)-B4+1),0) -> 0.18057143 | AE4: =D4*IF(MAX(0,MIN(C4,Funnel!$B$19)-B4+1)>0,MAX(0,MIN(C4,Funnel!$B$19)-MAX(B4,Assumptions!$D$7+Assumptions!$D$182)+1)/MAX(0,MIN(C4,Funnel!$B$19)-B4+1),0) -> 0 | AF4: =MAX(0,MIN(C4,Funnel!$B$19)-MAX(B4,Assumptions!$D$7+Assumptions!$D$181)+1) -> 4 | AG4: =MAX(0,MIN(C4,Funnel!$B$19)-MAX(B4,Assumptions!$D$7+Assumptions!$D$182)+1) -> 0
A5: 2 | B5: =Assumptions!$D$7+7*(A5-1) -> 46322 | C5: =MIN(B5+6,Assumptions!$D$8) -> 46328 | D5: =IF(SUMPRODUCT(($B$4:$B$14<=Funnel!$B$19)*$Z$4:$Z$14)>0,IF(B5<=Funnel!$B$19,Z5,0)/SUMPRODUCT(($B$4:$B$14<=Funnel!$B$19)*$Z$4:$Z$14),0) -> 0.131 | E5: =IF(SUM($AA$4:$AA$14)>0,AA5/SUM($AA$4:$AA$14),0) -> 0.16255983 | F5: =IF(A5-ROUNDUP(Funnel!$B$15/7,0)>=1,INDEX($D$4:$D$14,A5-ROUNDUP(Funnel!$B$15/7,0)),0) -> 0 | G5: =IF(A5-ROUNDUP(Funnel!$B$16/7,0)>=1,INDEX($E$4:$E$14,A5-ROUNDUP(Funnel!$B$16/7,0)),0) -> 0 | H5: =($F$19-$L$19-$L$23)*D5+$L$19*AB5+$L$23*AC5+$F$20*E5+$F$31*Y5 -> 10800.365 | I5: =IF(A5=1,$F$21,0) -> 0 | J5: =$F$22*F5+$F$23*G5 -> 0 | K5: =IF(A5=1,Budget!$C$6,0) -> 0 | L5: =$F$24*X5 -> 5400 | M5: =SUM(H5:L5) -> 16200.365 | N5: =SUM($M$4:M5) -> 48690.289 | O5: =(Funnel!$M$5+Funnel!$M$6+Funnel!$M$7-$F$27-$F$34-$L$20-$L$24)*D5+$L$20*AB5+$L$24*AC5+(Funnel!$M$8-$F$28-$F$35)*E5+($F$27+$F$28)*X5+($F$34+$F$35)*Y5 -> 260.89102 | P5: =(Funnel!$O$5+Funnel!$O$6+Funnel!$O$7-$F$25-$F$32-$L$21-$L$25)*D5+$L$21*AB5+$L$25*AC5+(Funnel!$O$8-$F$26-$F$33)*E5+($F$25+$F$26)*X5+($F$32+$F$33)*Y5 -> 52.747848 | Q5: =Assumptions!$D$9*MAX(0,MIN(C5+Assumptions!$D$21,Funnel!$B$17)-MAX(IF(A5=1,Funnel!$B$13,B5+Assumptions!$D$21),Funnel!$B$13)+1)/7 -> 55 | R5: =IF(Q5>0,P5/Q5,IF(P5>0,9.99,0)) -> 0.95905178 | S5: =IF(P5>Q5+0.5,"OVER "&Assumptions!$D$9&"/wk – pace down",IF(R5>Assumptions!$D$102,"Full",IF(AND(Q5>=Assumptions!$D$103,P5<Assumptions!$D$103),"Under "&Assumptions!$D$103&" – release reserve",""))) -> Full | T5: =$F$38*(F5*(Budget!$G$21+Budget!$G$22+Budget!$G$23-$F$29-$F$36-$L$22-$L$26)+IF(A5-ROUNDUP(Funnel!$B$15/7,0)>=1,INDEX($X$4:$X$14,A5-ROUNDUP(Funnel!$B$15/7,0))*$F$29+INDEX($Y$4:$Y$14,A5-ROUNDUP(Funnel!$B$15/7,0))*$F$36+INDEX($AB$4:$AB$14,A5-ROUNDUP(Funnel!$B$15/7,0))*$L$22+INDEX($AC$4:$AC$14,A5-ROUNDUP(Funnel!$B$15/7,0))*$L$26,0)) -> 0 | U5: =$F$38*(G5*(Budget!$G$24-$F$30-$F$37)+IF(A5-ROUNDUP(Funnel!$B$16/7,0)>=1,INDEX($X$4:$X$14,A5-ROUNDUP(Funnel!$B$16/7,0))*$F$30+INDEX($Y$4:$Y$14,A5-ROUNDUP(Funnel!$B$16/7,0))*$F$37,0)) -> 0 | V5: =T5+U5 -> 0 | W5: =SUM($V$4:V5) -> 0 | X5: =IF(A5=1,Assumptions!$D$50,IF(A5=2,1-Assumptions!$D$50,0)) -> 0.6 | Y5: =Assumptions!$D$94 -> 0.29 | Z5: =Assumptions!$D$54 -> 0.131 | AA5: =D5*IF(MAX(0,MIN(C5,Funnel!$B$19)-B5+1)>0,MAX(0,MIN(C5,Funnel!$B$20)-B5+1)/MAX(0,MIN(C5,Funnel!$B$19)-B5+1),0) -> 0.131 | AB5: =IF(SUM($AD$4:$AD$14)>0,AD5/SUM($AD$4:$AD$14),IF(SUM($AF$4:$AF$14)>0,AF5/SUM($AF$4:$AF$14),0)) -> 0.15152016 | AC5: =IF(SUM($AE$4:$AE$14)>0,AE5/SUM($AE$4:$AE$14),IF(SUM($AG$4:$AG$14)>0,AG5/SUM($AG$4:$AG$14),0)) -> 0.19152047 | AD5: =D5*IF(MAX(0,MIN(C5,Funnel!$B$19)-B5+1)>0,MAX(0,MIN(C5,Funnel!$B$19)-MAX(B5,Assumptions!$D$7+Assumptions!$D$181)+1)/MAX(0,MIN(C5,Funnel!$B$19)-B5+1),0) -> 0.131 | AE5: =D5*IF(MAX(0,MIN(C5,Funnel!$B$19)-B5+1)>0,MAX(0,MIN(C5,Funnel!$B$19)-MAX(B5,Assumptions!$D$7+Assumptions!$D$182)+1)/MAX(0,MIN(C5,Funnel!$B$19)-B5+1),0) -> 0.131 | AF5: =MAX(0,MIN(C5,Funnel!$B$19)-MAX(B5,Assumptions!$D$7+Assumptions!$D$181)+1) -> 7 | AG5: =MAX(0,MIN(C5,Funnel!$B$19)-MAX(B5,Assumptions!$D$7+Assumptions!$D$182)+1) -> 7
A6: 3 | B6: =Assumptions!$D$7+7*(A6-1) -> 46329 | C6: =MIN(B6+6,Assumptions!$D$8) -> 46335 | D6: =IF(SUMPRODUCT(($B$4:$B$14<=Funnel!$B$19)*$Z$4:$Z$14)>0,IF(B6<=Funnel!$B$19,Z6,0)/SUMPRODUCT(($B$4:$B$14<=Funnel!$B$19)*$Z$4:$Z$14),0) -> 0.161 | E6: =IF(SUM($AA$4:$AA$14)>0,AA6/SUM($AA$4:$AA$14),0) -> 0.19978727 | F6: =IF(A6-ROUNDUP(Funnel!$B$15/7,0)>=1,INDEX($D$4:$D$14,A6-ROUNDUP(Funnel!$B$15/7,0)),0) -> 0 | G6: =IF(A6-ROUNDUP(Funnel!$B$16/7,0)>=1,INDEX($E$4:$E$14,A6-ROUNDUP(Funnel!$B$16/7,0)),0) -> 0 | H6: =($F$19-$L$19-$L$23)*D6+$L$19*AB6+$L$23*AC6+$F$20*E6+$F$31*Y6 -> 13258.133 | I6: =IF(A6=1,$F$21,0) -> 0 | J6: =$F$22*F6+$F$23*G6 -> 0 | K6: =IF(A6=1,Budget!$C$6,0) -> 0 | L6: =$F$24*X6 -> 0 | M6: =SUM(H6:L6) -> 13258.133 | N6: =SUM($M$4:M6) -> 61948.422 | O6: =(Funnel!$M$5+Funnel!$M$6+Funnel!$M$7-$F$27-$F$34-$L$20-$L$24)*D6+$L$20*AB6+$L$24*AC6+(Funnel!$M$8-$F$28-$F$35)*E6+($F$27+$F$28)*X6+($F$34+$F$35)*Y6 -> 263.60882 | P6: =(Funnel!$O$5+Funnel!$O$6+Funnel!$O$7-$F$25-$F$32-$L$21-$L$25)*D6+$L$21*AB6+$L$25*AC6+(Funnel!$O$8-$F$26-$F$33)*E6+($F$25+$F$26)*X6+($F$32+$F$33)*Y6 -> 52.72018 | Q6: =Assumptions!$D$9*MAX(0,MIN(C6+Assumptions!$D$21,Funnel!$B$17)-MAX(IF(A6=1,Funnel!$B$13,B6+Assumptions!$D$21),Funnel!$B$13)+1)/7 -> 55 | R6: =IF(Q6>0,P6/Q6,IF(P6>0,9.99,0)) -> 0.95854873 | S6: =IF(P6>Q6+0.5,"OVER "&Assumptions!$D$9&"/wk – pace down",IF(R6>Assumptions!$D$102,"Full",IF(AND(Q6>=Assumptions!$D$103,P6<Assumptions!$D$103),"Under "&Assumptions!$D$103&" – release reserve",""))) -> Full | T6: =$F$38*(F6*(Budget!$G$21+Budget!$G$22+Budget!$G$23-$F$29-$F$36-$L$22-$L$26)+IF(A6-ROUNDUP(Funnel!$B$15/7,0)>=1,INDEX($X$4:$X$14,A6-ROUNDUP(Funnel!$B$15/7,0))*$F$29+INDEX($Y$4:$Y$14,A6-ROUNDUP(Funnel!$B$15/7,0))*$F$36+INDEX($AB$4:$AB$14,A6-ROUNDUP(Funnel!$B$15/7,0))*$L$22+INDEX($AC$4:$AC$14,A6-ROUNDUP(Funnel!$B$15/7,0))*$L$26,0)) -> 0 | U6: =$F$38*(G6*(Budget!$G$24-$F$30-$F$37)+IF(A6-ROUNDUP(Funnel!$B$16/7,0)>=1,INDEX($X$4:$X$14,A6-ROUNDUP(Funnel!$B$16/7,0))*$F$30+INDEX($Y$4:$Y$14,A6-ROUNDUP(Funnel!$B$16/7,0))*$F$37,0)) -> 0 | V6: =T6+U6 -> 0 | W6: =SUM($V$4:V6) -> 0 | X6: =IF(A6=1,Assumptions!$D$50,IF(A6=2,1-Assumptions!$D$50,0)) -> 0 | Y6: =Assumptions!$D$95 -> 0.11 | Z6: =Assumptions!$D$55 -> 0.161 | AA6: =D6*IF(MAX(0,MIN(C6,Funnel!$B$19)-B6+1)>0,MAX(0,MIN(C6,Funnel!$B$20)-B6+1)/MAX(0,MIN(C6,Funnel!$B$19)-B6+1),0) -> 0.161 | AB6: =IF(SUM($AD$4:$AD$14)>0,AD6/SUM($AD$4:$AD$14),IF(SUM($AF$4:$AF$14)>0,AF6/SUM($AF$4:$AF$14),0)) -> 0.18621943 | AC6: =IF(SUM($AE$4:$AE$14)>0,AE6/SUM($AE$4:$AE$14),IF(SUM($AG$4:$AG$14)>0,AG6/SUM($AG$4:$AG$14),0)) -> 0.23538012 | AD6: =D6*IF(MAX(0,MIN(C6,Funnel!$B$19)-B6+1)>0,MAX(0,MIN(C6,Funnel!$B$19)-MAX(B6,Assumptions!$D$7+Assumptions!$D$181)+1)/MAX(0,MIN(C6,Funnel!$B$19)-B6+1),0) -> 0.161 | AE6: =D6*IF(MAX(0,MIN(C6,Funnel!$B$19)-B6+1)>0,MAX(0,MIN(C6,Funnel!$B$19)-MAX(B6,Assumptions!$D$7+Assumptions!$D$182)+1)/MAX(0,MIN(C6,Funnel!$B$19)-B6+1),0) -> 0.161 | AF6: =MAX(0,MIN(C6,Funnel!$B$19)-MAX(B6,Assumptions!$D$7+Assumptions!$D$181)+1) -> 7 | AG6: =MAX(0,MIN(C6,Funnel!$B$19)-MAX(B6,Assumptions!$D$7+Assumptions!$D$182)+1) -> 7
A7: 4 | B7: =Assumptions!$D$7+7*(A7-1) -> 46336 | C7: =MIN(B7+6,Assumptions!$D$8) -> 46342 | D7: =IF(SUMPRODUCT(($B$4:$B$14<=Funnel!$B$19)*$Z$4:$Z$14)>0,IF(B7<=Funnel!$B$19,Z7,0)/SUMPRODUCT(($B$4:$B$14<=Funnel!$B$19)*$Z$4:$Z$14),0) -> 0.17 | E7: =IF(SUM($AA$4:$AA$14)>0,AA7/SUM($AA$4:$AA$14),0) -> 0.2109555 | F7: =IF(A7-ROUNDUP(Funnel!$B$15/7,0)>=1,INDEX($D$4:$D$14,A7-ROUNDUP(Funnel!$B$15/7,0)),0) -> 0.316 | G7: =IF(A7-ROUNDUP(Funnel!$B$16/7,0)>=1,INDEX($E$4:$E$14,A7-ROUNDUP(Funnel!$B$16/7,0)),0) -> 0 | H7: =($F$19-$L$19-$L$23)*D7+$L$19*AB7+$L$23*AC7+$F$20*E7+$F$31*Y7 -> 13991.919 | I7: =IF(A7=1,$F$21,0) -> 0 | J7: =$F$22*F7+$F$23*G7 -> 3118.6806 | K7: =IF(A7=1,Budget!$C$6,0) -> 0 | L7: =$F$24*X7 -> 0 | M7: =SUM(H7:L7) -> 17110.599 | N7: =SUM($M$4:M7) -> 79059.021 | O7: =(Funnel!$M$5+Funnel!$M$6+Funnel!$M$7-$F$27-$F$34-$L$20-$L$24)*D7+$L$20*AB7+$L$24*AC7+(Funnel!$M$8-$F$28-$F$35)*E7+($F$27+$F$28)*X7+($F$34+$F$35)*Y7 -> 275.40383 | P7: =(Funnel!$O$5+Funnel!$O$6+Funnel!$O$7-$F$25-$F$32-$L$21-$L$25)*D7+$L$21*AB7+$L$25*AC7+(Funnel!$O$8-$F$26-$F$33)*E7+($F$25+$F$26)*X7+($F$32+$F$33)*Y7 -> 54.196824 | Q7: =Assumptions!$D$9*MAX(0,MIN(C7+Assumptions!$D$21,Funnel!$B$17)-MAX(IF(A7=1,Funnel!$B$13,B7+Assumptions!$D$21),Funnel!$B$13)+1)/7 -> 55 | R7: =IF(Q7>0,P7/Q7,IF(P7>0,9.99,0)) -> 0.9853968 | S7: =IF(P7>Q7+0.5,"OVER "&Assumptions!$D$9&"/wk – pace down",IF(R7>Assumptions!$D$102,"Full",IF(AND(Q7>=Assumptions!$D$103,P7<Assumptions!$D$103),"Under "&Assumptions!$D$103&" – release reserve",""))) -> Full | T7: =$F$38*(F7*(Budget!$G$21+Budget!$G$22+Budget!$G$23-$F$29-$F$36-$L$22-$L$26)+IF(A7-ROUNDUP(Funnel!$B$15/7,0)>=1,INDEX($X$4:$X$14,A7-ROUNDUP(Funnel!$B$15/7,0))*$F$29+INDEX($Y$4:$Y$14,A7-ROUNDUP(Funnel!$B$15/7,0))*$F$36+INDEX($AB$4:$AB$14,A7-ROUNDUP(Funnel!$B$15/7,0))*$L$22+INDEX($AC$4:$AC$14,A7-ROUNDUP(Funnel!$B$15/7,0))*$L$26,0)) -> 23.260895 | U7: =$F$38*(G7*(Budget!$G$24-$F$30-$F$37)+IF(A7-ROUNDUP(Funnel!$B$16/7,0)>=1,INDEX($X$4:$X$14,A7-ROUNDUP(Funnel!$B$16/7,0))*$F$30+INDEX($Y$4:$Y$14,A7-ROUNDUP(Funnel!$B$16/7,0))*$F$37,0)) -> 0 | V7: =T7+U7 -> 23.260895 | W7: =SUM($V$4:V7) -> 23.260895 | X7: =IF(A7=1,Assumptions!$D$50,IF(A7=2,1-Assumptions!$D$50,0)) -> 0 | Y7: =0 -> 0 | Z7: =Assumptions!$D$56 -> 0.17 | AA7: =D7*IF(MAX(0,MIN(C7,Funnel!$B$19)-B7+1)>0,MAX(0,MIN(C7,Funnel!$B$20)-B7+1)/MAX(0,MIN(C7,Funnel!$B$19)-B7+1),0) -> 0.17 | AB7: =IF(SUM($AD$4:$AD$14)>0,AD7/SUM($AD$4:$AD$14),IF(SUM($AF$4:$AF$14)>0,AF7/SUM($AF$4:$AF$14),0)) -> 0.19662921 | AC7: =IF(SUM($AE$4:$AE$14)>0,AE7/SUM($AE$4:$AE$14),IF(SUM($AG$4:$AG$14)>0,AG7/SUM($AG$4:$AG$14),0)) -> 0.24853801 | AD7: =D7*IF(MAX(0,MIN(C7,Funnel!$B$19)-B7+1)>0,MAX(0,MIN(C7,Funnel!$B$19)-MAX(B7,Assumptions!$D$7+Assumptions!$D$181)+1)/MAX(0,MIN(C7,Funnel!$B$19)-B7+1),0) -> 0.17 | AE7: =D7*IF(MAX(0,MIN(C7,Funnel!$B$19)-B7+1)>0,MAX(0,MIN(C7,Funnel!$B$19)-MAX(B7,Assumptions!$D$7+Assumptions!$D$182)+1)/MAX(0,MIN(C7,Funnel!$B$19)-B7+1),0) -> 0.17 | AF7: =MAX(0,MIN(C7,Funnel!$B$19)-MAX(B7,Assumptions!$D$7+Assumptions!$D$181)+1) -> 7 | AG7: =MAX(0,MIN(C7,Funnel!$B$19)-MAX(B7,Assumptions!$D$7+Assumptions!$D$182)+1) -> 7
A8: 5 | B8: =Assumptions!$D$7+7*(A8-1) -> 46343 | C8: =MIN(B8+6,Assumptions!$D$8) -> 46349 | D8: =IF(SUMPRODUCT(($B$4:$B$14<=Funnel!$B$19)*$Z$4:$Z$14)>0,IF(B8<=Funnel!$B$19,Z8,0)/SUMPRODUCT(($B$4:$B$14<=Funnel!$B$19)*$Z$4:$Z$14),0) -> 0.195 | E8: =IF(SUM($AA$4:$AA$14)>0,AA8/SUM($AA$4:$AA$14),0) -> 0.034568339 | F8: =IF(A8-ROUNDUP(Funnel!$B$15/7,0)>=1,INDEX($D$4:$D$14,A8-ROUNDUP(Funnel!$B$15/7,0)),0) -> 0.131 | G8: =IF(A8-ROUNDUP(Funnel!$B$16/7,0)>=1,INDEX($E$4:$E$14,A8-ROUNDUP(Funnel!$B$16/7,0)),0) -> 0.39212906 | H8: =($F$19-$L$19-$L$23)*D8+$L$19*AB8+$L$23*AC8+$F$20*E8+$F$31*Y8 -> 13523.576 | I8: =IF(A8=1,$F$21,0) -> 0 | J8: =$F$22*F8+$F$23*G8 -> 1727.5399 | K8: =IF(A8=1,Budget!$C$6,0) -> 0 | L8: =$F$24*X8 -> 0 | M8: =SUM(H8:L8) -> 15251.116 | N8: =SUM($M$4:M8) -> 94310.137 | O8: =(Funnel!$M$5+Funnel!$M$6+Funnel!$M$7-$F$27-$F$34-$L$20-$L$24)*D8+$L$20*AB8+$L$24*AC8+(Funnel!$M$8-$F$28-$F$35)*E8+($F$27+$F$28)*X8+($F$34+$F$35)*Y8 -> 280.46608 | P8: =(Funnel!$O$5+Funnel!$O$6+Funnel!$O$7-$F$25-$F$32-$L$21-$L$25)*D8+$L$21*AB8+$L$25*AC8+(Funnel!$O$8-$F$26-$F$33)*E8+($F$25+$F$26)*X8+($F$32+$F$33)*Y8 -> 54.711539 | Q8: =Assumptions!$D$9*MAX(0,MIN(C8+Assumptions!$D$21,Funnel!$B$17)-MAX(IF(A8=1,Funnel!$B$13,B8+Assumptions!$D$21),Funnel!$B$13)+1)/7 -> 55 | R8: =IF(Q8>0,P8/Q8,IF(P8>0,9.99,0)) -> 0.99475526 | S8: =IF(P8>Q8+0.5,"OVER "&Assumptions!$D$9&"/wk – pace down",IF(R8>Assumptions!$D$102,"Full",IF(AND(Q8>=Assumptions!$D$103,P8<Assumptions!$D$103),"Under "&Assumptions!$D$103&" – release reserve",""))) -> Full | T8: =$F$38*(F8*(Budget!$G$21+Budget!$G$22+Budget!$G$23-$F$29-$F$36-$L$22-$L$26)+IF(A8-ROUNDUP(Funnel!$B$15/7,0)>=1,INDEX($X$4:$X$14,A8-ROUNDUP(Funnel!$B$15/7,0))*$F$29+INDEX($Y$4:$Y$14,A8-ROUNDUP(Funnel!$B$15/7,0))*$F$36+INDEX($AB$4:$AB$14,A8-ROUNDUP(Funnel!$B$15/7,0))*$L$22+INDEX($AC$4:$AC$14,A8-ROUNDUP(Funnel!$B$15/7,0))*$L$26,0)) -> 15.041818 | U8: =$F$38*(G8*(Budget!$G$24-$F$30-$F$37)+IF(A8-ROUNDUP(Funnel!$B$16/7,0)>=1,INDEX($X$4:$X$14,A8-ROUNDUP(Funnel!$B$16/7,0))*$F$30+INDEX($Y$4:$Y$14,A8-ROUNDUP(Funnel!$B$16/7,0))*$F$37,0)) -> 4.0366271 | V8: =T8+U8 -> 19.078445 | W8: =SUM($V$4:V8) -> 42.33934 | X8: =IF(A8=1,Assumptions!$D$50,IF(A8=2,1-Assumptions!$D$50,0)) -> 0 | Y8: =0 -> 0 | Z8: =Assumptions!$D$57 -> 0.195 | AA8: =D8*IF(MAX(0,MIN(C8,Funnel!$B$19)-B8+1)>0,MAX(0,MIN(C8,Funnel!$B$20)-B8+1)/MAX(0,MIN(C8,Funnel!$B$19)-B8+1),0) -> 0.027857143 | AB8: =IF(SUM($AD$4:$AD$14)>0,AD8/SUM($AD$4:$AD$14),IF(SUM($AF$4:$AF$14)>0,AF8/SUM($AF$4:$AF$14),0)) -> 0.22554527 | AC8: =IF(SUM($AE$4:$AE$14)>0,AE8/SUM($AE$4:$AE$14),IF(SUM($AG$4:$AG$14)>0,AG8/SUM($AG$4:$AG$14),0)) -> 0.28508772 | AD8: =D8*IF(MAX(0,MIN(C8,Funnel!$B$19)-B8+1)>0,MAX(0,MIN(C8,Funnel!$B$19)-MAX(B8,Assumptions!$D$7+Assumptions!$D$181)+1)/MAX(0,MIN(C8,Funnel!$B$19)-B8+1),0) -> 0.195 | AE8: =D8*IF(MAX(0,MIN(C8,Funnel!$B$19)-B8+1)>0,MAX(0,MIN(C8,Funnel!$B$19)-MAX(B8,Assumptions!$D$7+Assumptions!$D$182)+1)/MAX(0,MIN(C8,Funnel!$B$19)-B8+1),0) -> 0.195 | AF8: =MAX(0,MIN(C8,Funnel!$B$19)-MAX(B8,Assumptions!$D$7+Assumptions!$D$181)+1) -> 7 | AG8: =MAX(0,MIN(C8,Funnel!$B$19)-MAX(B8,Assumptions!$D$7+Assumptions!$D$182)+1) -> 7
A9: 6 | B9: =Assumptions!$D$7+7*(A9-1) -> 46350 | C9: =MIN(B9+6,Assumptions!$D$8) -> 46356 | D9: =IF(SUMPRODUCT(($B$4:$B$14<=Funnel!$B$19)*$Z$4:$Z$14)>0,IF(B9<=Funnel!$B$19,Z9,0)/SUMPRODUCT(($B$4:$B$14<=Funnel!$B$19)*$Z$4:$Z$14),0) -> 0.027 | E9: =IF(SUM($AA$4:$AA$14)>0,AA9/SUM($AA$4:$AA$14),0) -> 0 | F9: =IF(A9-ROUNDUP(Funnel!$B$15/7,0)>=1,INDEX($D$4:$D$14,A9-ROUNDUP(Funnel!$B$15/7,0)),0) -> 0.161 | G9: =IF(A9-ROUNDUP(Funnel!$B$16/7,0)>=1,INDEX($E$4:$E$14,A9-ROUNDUP(Funnel!$B$16/7,0)),0) -> 0.16255983 | H9: =($F$19-$L$19-$L$23)*D9+$L$19*AB9+$L$23*AC9+$F$20*E9+$F$31*Y9 -> 1814.2033 | I9: =IF(A9=1,$F$21,0) -> 0 | J9: =$F$22*F9+$F$23*G9 -> 1769.1432 | K9: =IF(A9=1,Budget!$C$6,0) -> 0 | L9: =$F$24*X9 -> 0 | M9: =SUM(H9:L9) -> 3583.3465 | N9: =SUM($M$4:M9) -> 97893.484 | O9: =(Funnel!$M$5+Funnel!$M$6+Funnel!$M$7-$F$27-$F$34-$L$20-$L$24)*D9+$L$20*AB9+$L$24*AC9+(Funnel!$M$8-$F$28-$F$35)*E9+($F$27+$F$28)*X9+($F$34+$F$35)*Y9 -> 38.015957 | P9: =(Funnel!$O$5+Funnel!$O$6+Funnel!$O$7-$F$25-$F$32-$L$21-$L$25)*D9+$L$21*AB9+$L$25*AC9+(Funnel!$O$8-$F$26-$F$33)*E9+($F$25+$F$26)*X9+($F$32+$F$33)*Y9 -> 7.4033961 | Q9: =Assumptions!$D$9*MAX(0,MIN(C9+Assumptions!$D$21,Funnel!$B$17)-MAX(IF(A9=1,Funnel!$B$13,B9+Assumptions!$D$21),Funnel!$B$13)+1)/7 -> 7.8571429 | R9: =IF(Q9>0,P9/Q9,IF(P9>0,9.99,0)) -> 0.94225041 | S9: =IF(P9>Q9+0.5,"OVER "&Assumptions!$D$9&"/wk – pace down",IF(R9>Assumptions!$D$102,"Full",IF(AND(Q9>=Assumptions!$D$103,P9<Assumptions!$D$103),"Under "&Assumptions!$D$103&" – release reserve",""))) -> Full | T9: =$F$38*(F9*(Budget!$G$21+Budget!$G$22+Budget!$G$23-$F$29-$F$36-$L$22-$L$26)+IF(A9-ROUNDUP(Funnel!$B$15/7,0)>=1,INDEX($X$4:$X$14,A9-ROUNDUP(Funnel!$B$15/7,0))*$F$29+INDEX($Y$4:$Y$14,A9-ROUNDUP(Funnel!$B$15/7,0))*$F$36+INDEX($AB$4:$AB$14,A9-ROUNDUP(Funnel!$B$15/7,0))*$L$22+INDEX($AC$4:$AC$14,A9-ROUNDUP(Funnel!$B$15/7,0))*$L$26,0)) -> 15.371035 | U9: =$F$38*(G9*(Budget!$G$24-$F$30-$F$37)+IF(A9-ROUNDUP(Funnel!$B$16/7,0)>=1,INDEX($X$4:$X$14,A9-ROUNDUP(Funnel!$B$16/7,0))*$F$30+INDEX($Y$4:$Y$14,A9-ROUNDUP(Funnel!$B$16/7,0))*$F$37,0)) -> 2.0315589 | V9: =T9+U9 -> 17.402594 | W9: =SUM($V$4:V9) -> 59.741934 | X9: =IF(A9=1,Assumptions!$D$50,IF(A9=2,1-Assumptions!$D$50,0)) -> 0 | Y9: =0 -> 0 | Z9: =Assumptions!$D$58 -> 0.027 | AA9: =D9*IF(MAX(0,MIN(C9,Funnel!$B$19)-B9+1)>0,MAX(0,MIN(C9,Funnel!$B$20)-B9+1)/MAX(0,MIN(C9,Funnel!$B$19)-B9+1),0) -> 0 | AB9: =IF(SUM($AD$4:$AD$14)>0,AD9/SUM($AD$4:$AD$14),IF(SUM($AF$4:$AF$14)>0,AF9/SUM($AF$4:$AF$14),0)) -> 0.031229346 | AC9: =IF(SUM($AE$4:$AE$14)>0,AE9/SUM($AE$4:$AE$14),IF(SUM($AG$4:$AG$14)>0,AG9/SUM($AG$4:$AG$14),0)) -> 0.039473684 | AD9: =D9*IF(MAX(0,MIN(C9,Funnel!$B$19)-B9+1)>0,MAX(0,MIN(C9,Funnel!$B$19)-MAX(B9,Assumptions!$D$7+Assumptions!$D$181)+1)/MAX(0,MIN(C9,Funnel!$B$19)-B9+1),0) -> 0.027 | AE9: =D9*IF(MAX(0,MIN(C9,Funnel!$B$19)-B9+1)>0,MAX(0,MIN(C9,Funnel!$B$19)-MAX(B9,Assumptions!$D$7+Assumptions!$D$182)+1)/MAX(0,MIN(C9,Funnel!$B$19)-B9+1),0) -> 0.027 | AF9: =MAX(0,MIN(C9,Funnel!$B$19)-MAX(B9,Assumptions!$D$7+Assumptions!$D$181)+1) -> 1 | AG9: =MAX(0,MIN(C9,Funnel!$B$19)-MAX(B9,Assumptions!$D$7+Assumptions!$D$182)+1) -> 1
A10: 7 | B10: =Assumptions!$D$7+7*(A10-1) -> 46357 | C10: =MIN(B10+6,Assumptions!$D$8) -> 46363 | D10: =IF(SUMPRODUCT(($B$4:$B$14<=Funnel!$B$19)*$Z$4:$Z$14)>0,IF(B10<=Funnel!$B$19,Z10,0)/SUMPRODUCT(($B$4:$B$14<=Funnel!$B$19)*$Z$4:$Z$14),0) -> 0 | E10: =IF(SUM($AA$4:$AA$14)>0,AA10/SUM($AA$4:$AA$14),0) -> 0 | F10: =IF(A10-ROUNDUP(Funnel!$B$15/7,0)>=1,INDEX($D$4:$D$14,A10-ROUNDUP(Funnel!$B$15/7,0)),0) -> 0.17 | G10: =IF(A10-ROUNDUP(Funnel!$B$16/7,0)>=1,INDEX($E$4:$E$14,A10-ROUNDUP(Funnel!$B$16/7,0)),0) -> 0.19978727 | H10: =($F$19-$L$19-$L$23)*D10+$L$19*AB10+$L$23*AC10+$F$20*E10+$F$31*Y10 -> 0 | I10: =IF(A10=1,$F$21,0) -> 0 | J10: =$F$22*F10+$F$23*G10 -> 1899.2324 | K10: =IF(A10=1,Budget!$C$6,0) -> 0 | L10: =$F$24*X10 -> 0 | M10: =SUM(H10:L10) -> 1899.2324 | N10: =SUM($M$4:M10) -> 99792.716 | O10: =(Funnel!$M$5+Funnel!$M$6+Funnel!$M$7-$F$27-$F$34-$L$20-$L$24)*D10+$L$20*AB10+$L$24*AC10+(Funnel!$M$8-$F$28-$F$35)*E10+($F$27+$F$28)*X10+($F$34+$F$35)*Y10 -> 0 | P10: =(Funnel!$O$5+Funnel!$O$6+Funnel!$O$7-$F$25-$F$32-$L$21-$L$25)*D10+$L$21*AB10+$L$25*AC10+(Funnel!$O$8-$F$26-$F$33)*E10+($F$25+$F$26)*X10+($F$32+$F$33)*Y10 -> 0 | Q10: =Assumptions!$D$9*MAX(0,MIN(C10+Assumptions!$D$21,Funnel!$B$17)-MAX(IF(A10=1,Funnel!$B$13,B10+Assumptions!$D$21),Funnel!$B$13)+1)/7 -> 0 | R10: =IF(Q10>0,P10/Q10,IF(P10>0,9.99,0)) -> 0 | S10: =IF(P10>Q10+0.5,"OVER "&Assumptions!$D$9&"/wk – pace down",IF(R10>Assumptions!$D$102,"Full",IF(AND(Q10>=Assumptions!$D$103,P10<Assumptions!$D$103),"Under "&Assumptions!$D$103&" – release reserve",""))) | T10: =$F$38*(F10*(Budget!$G$21+Budget!$G$22+Budget!$G$23-$F$29-$F$36-$L$22-$L$26)+IF(A10-ROUNDUP(Funnel!$B$15/7,0)>=1,INDEX($X$4:$X$14,A10-ROUNDUP(Funnel!$B$15/7,0))*$F$29+INDEX($Y$4:$Y$14,A10-ROUNDUP(Funnel!$B$15/7,0))*$F$36+INDEX($AB$4:$AB$14,A10-ROUNDUP(Funnel!$B$15/7,0))*$L$22+INDEX($AC$4:$AC$14,A10-ROUNDUP(Funnel!$B$15/7,0))*$L$26,0)) -> 15.753732 | U10: =$F$38*(G10*(Budget!$G$24-$F$30-$F$37)+IF(A10-ROUNDUP(Funnel!$B$16/7,0)>=1,INDEX($X$4:$X$14,A10-ROUNDUP(Funnel!$B$16/7,0))*$F$30+INDEX($Y$4:$Y$14,A10-ROUNDUP(Funnel!$B$16/7,0))*$F$37,0)) -> 1.7958658 | V10: =T10+U10 -> 17.549598 | W10: =SUM($V$4:V10) -> 77.291531 | X10: =IF(A10=1,Assumptions!$D$50,IF(A10=2,1-Assumptions!$D$50,0)) -> 0 | Y10: =0 -> 0 | Z10: =Assumptions!$D$59 -> 0 | AA10: =D10*IF(MAX(0,MIN(C10,Funnel!$B$19)-B10+1)>0,MAX(0,MIN(C10,Funnel!$B$20)-B10+1)/MAX(0,MIN(C10,Funnel!$B$19)-B10+1),0) -> 0 | AB10: =IF(SUM($AD$4:$AD$14)>0,AD10/SUM($AD$4:$AD$14),IF(SUM($AF$4:$AF$14)>0,AF10/SUM($AF$4:$AF$14),0)) -> 0 | AC10: =IF(SUM($AE$4:$AE$14)>0,AE10/SUM($AE$4:$AE$14),IF(SUM($AG$4:$AG$14)>0,AG10/SUM($AG$4:$AG$14),0)) -> 0 | AD10: =D10*IF(MAX(0,MIN(C10,Funnel!$B$19)-B10+1)>0,MAX(0,MIN(C10,Funnel!$B$19)-MAX(B10,Assumptions!$D$7+Assumptions!$D$181)+1)/MAX(0,MIN(C10,Funnel!$B$19)-B10+1),0) -> 0 | AE10: =D10*IF(MAX(0,MIN(C10,Funnel!$B$19)-B10+1)>0,MAX(0,MIN(C10,Funnel!$B$19)-MAX(B10,Assumptions!$D$7+Assumptions!$D$182)+1)/MAX(0,MIN(C10,Funnel!$B$19)-B10+1),0) -> 0 | AF10: =MAX(0,MIN(C10,Funnel!$B$19)-MAX(B10,Assumptions!$D$7+Assumptions!$D$181)+1) -> 0 | AG10: =MAX(0,MIN(C10,Funnel!$B$19)-MAX(B10,Assumptions!$D$7+Assumptions!$D$182)+1) -> 0
A11: 8 | B11: =Assumptions!$D$7+7*(A11-1) -> 46364 | C11: =MIN(B11+6,Assumptions!$D$8) -> 46370 | D11: =IF(SUMPRODUCT(($B$4:$B$14<=Funnel!$B$19)*$Z$4:$Z$14)>0,IF(B11<=Funnel!$B$19,Z11,0)/SUMPRODUCT(($B$4:$B$14<=Funnel!$B$19)*$Z$4:$Z$14),0) -> 0 | E11: =IF(SUM($AA$4:$AA$14)>0,AA11/SUM($AA$4:$AA$14),0) -> 0 | F11: =IF(A11-ROUNDUP(Funnel!$B$15/7,0)>=1,INDEX($D$4:$D$14,A11-ROUNDUP(Funnel!$B$15/7,0)),0) -> 0.195 | G11: =IF(A11-ROUNDUP(Funnel!$B$16/7,0)>=1,INDEX($E$4:$E$14,A11-ROUNDUP(Funnel!$B$16/7,0)),0) -> 0.2109555 | H11: =($F$19-$L$19-$L$23)*D11+$L$19*AB11+$L$23*AC11+$F$20*E11+$F$31*Y11 -> 0 | I11: =IF(A11=1,$F$21,0) -> 0 | J11: =$F$22*F11+$F$23*G11 -> 2158.3433 | K11: =IF(A11=1,Budget!$C$6,0) -> 0 | L11: =$F$24*X11 -> 0 | M11: =SUM(H11:L11) -> 2158.3433 | N11: =SUM($M$4:M11) -> 101951.06 | O11: =(Funnel!$M$5+Funnel!$M$6+Funnel!$M$7-$F$27-$F$34-$L$20-$L$24)*D11+$L$20*AB11+$L$24*AC11+(Funnel!$M$8-$F$28-$F$35)*E11+($F$27+$F$28)*X11+($F$34+$F$35)*Y11 -> 0 | P11: =(Funnel!$O$5+Funnel!$O$6+Funnel!$O$7-$F$25-$F$32-$L$21-$L$25)*D11+$L$21*AB11+$L$25*AC11+(Funnel!$O$8-$F$26-$F$33)*E11+($F$25+$F$26)*X11+($F$32+$F$33)*Y11 -> 0 | Q11: =Assumptions!$D$9*MAX(0,MIN(C11+Assumptions!$D$21,Funnel!$B$17)-MAX(IF(A11=1,Funnel!$B$13,B11+Assumptions!$D$21),Funnel!$B$13)+1)/7 -> 0 | R11: =IF(Q11>0,P11/Q11,IF(P11>0,9.99,0)) -> 0 | S11: =IF(P11>Q11+0.5,"OVER "&Assumptions!$D$9&"/wk – pace down",IF(R11>Assumptions!$D$102,"Full",IF(AND(Q11>=Assumptions!$D$103,P11<Assumptions!$D$103),"Under "&Assumptions!$D$103&" – release reserve",""))) | T11: =$F$38*(F11*(Budget!$G$21+Budget!$G$22+Budget!$G$23-$F$29-$F$36-$L$22-$L$26)+IF(A11-ROUNDUP(Funnel!$B$15/7,0)>=1,INDEX($X$4:$X$14,A11-ROUNDUP(Funnel!$B$15/7,0))*$F$29+INDEX($Y$4:$Y$14,A11-ROUNDUP(Funnel!$B$15/7,0))*$F$36+INDEX($AB$4:$AB$14,A11-ROUNDUP(Funnel!$B$15/7,0))*$L$22+INDEX($AC$4:$AC$14,A11-ROUNDUP(Funnel!$B$15/7,0))*$L$26,0)) -> 18.070457 | U11: =$F$38*(G11*(Budget!$G$24-$F$30-$F$37)+IF(A11-ROUNDUP(Funnel!$B$16/7,0)>=1,INDEX($X$4:$X$14,A11-ROUNDUP(Funnel!$B$16/7,0))*$F$30+INDEX($Y$4:$Y$14,A11-ROUNDUP(Funnel!$B$16/7,0))*$F$37,0)) -> 1.835219 | V11: =T11+U11 -> 19.905676 | W11: =SUM($V$4:V11) -> 97.197208 | X11: =IF(A11=1,Assumptions!$D$50,IF(A11=2,1-Assumptions!$D$50,0)) -> 0 | Y11: =0 -> 0 | Z11: =Assumptions!$D$60 -> 0 | AA11: =D11*IF(MAX(0,MIN(C11,Funnel!$B$19)-B11+1)>0,MAX(0,MIN(C11,Funnel!$B$20)-B11+1)/MAX(0,MIN(C11,Funnel!$B$19)-B11+1),0) -> 0 | AB11: =IF(SUM($AD$4:$AD$14)>0,AD11/SUM($AD$4:$AD$14),IF(SUM($AF$4:$AF$14)>0,AF11/SUM($AF$4:$AF$14),0)) -> 0 | AC11: =IF(SUM($AE$4:$AE$14)>0,AE11/SUM($AE$4:$AE$14),IF(SUM($AG$4:$AG$14)>0,AG11/SUM($AG$4:$AG$14),0)) -> 0 | AD11: =D11*IF(MAX(0,MIN(C11,Funnel!$B$19)-B11+1)>0,MAX(0,MIN(C11,Funnel!$B$19)-MAX(B11,Assumptions!$D$7+Assumptions!$D$181)+1)/MAX(0,MIN(C11,Funnel!$B$19)-B11+1),0) -> 0 | AE11: =D11*IF(MAX(0,MIN(C11,Funnel!$B$19)-B11+1)>0,MAX(0,MIN(C11,Funnel!$B$19)-MAX(B11,Assumptions!$D$7+Assumptions!$D$182)+1)/MAX(0,MIN(C11,Funnel!$B$19)-B11+1),0) -> 0 | AF11: =MAX(0,MIN(C11,Funnel!$B$19)-MAX(B11,Assumptions!$D$7+Assumptions!$D$181)+1) -> 0 | AG11: =MAX(0,MIN(C11,Funnel!$B$19)-MAX(B11,Assumptions!$D$7+Assumptions!$D$182)+1) -> 0
A12: 9 | B12: =Assumptions!$D$7+7*(A12-1) -> 46371 | C12: =MIN(B12+6,Assumptions!$D$8) -> 46377 | D12: =IF(SUMPRODUCT(($B$4:$B$14<=Funnel!$B$19)*$Z$4:$Z$14)>0,IF(B12<=Funnel!$B$19,Z12,0)/SUMPRODUCT(($B$4:$B$14<=Funnel!$B$19)*$Z$4:$Z$14),0) -> 0 | E12: =IF(SUM($AA$4:$AA$14)>0,AA12/SUM($AA$4:$AA$14),0) -> 0 | F12: =IF(A12-ROUNDUP(Funnel!$B$15/7,0)>=1,INDEX($D$4:$D$14,A12-ROUNDUP(Funnel!$B$15/7,0)),0) -> 0.027 | G12: =IF(A12-ROUNDUP(Funnel!$B$16/7,0)>=1,INDEX($E$4:$E$14,A12-ROUNDUP(Funnel!$B$16/7,0)),0) -> 0.034568339 | H12: =($F$19-$L$19-$L$23)*D12+$L$19*AB12+$L$23*AC12+$F$20*E12+$F$31*Y12 -> 0 | I12: =IF(A12=1,$F$21,0) -> 0 | J12: =$F$22*F12+$F$23*G12 -> 304.78803 | K12: =IF(A12=1,Budget!$C$6,0) -> 0 | L12: =$F$24*X12 -> 0 | M12: =SUM(H12:L12) -> 304.78803 | N12: =SUM($M$4:M12) -> 102255.85 | O12: =(Funnel!$M$5+Funnel!$M$6+Funnel!$M$7-$F$27-$F$34-$L$20-$L$24)*D12+$L$20*AB12+$L$24*AC12+(Funnel!$M$8-$F$28-$F$35)*E12+($F$27+$F$28)*X12+($F$34+$F$35)*Y12 -> 0 | P12: =(Funnel!$O$5+Funnel!$O$6+Funnel!$O$7-$F$25-$F$32-$L$21-$L$25)*D12+$L$21*AB12+$L$25*AC12+(Funnel!$O$8-$F$26-$F$33)*E12+($F$25+$F$26)*X12+($F$32+$F$33)*Y12 -> 0 | Q12: =Assumptions!$D$9*MAX(0,MIN(C12+Assumptions!$D$21,Funnel!$B$17)-MAX(IF(A12=1,Funnel!$B$13,B12+Assumptions!$D$21),Funnel!$B$13)+1)/7 -> 0 | R12: =IF(Q12>0,P12/Q12,IF(P12>0,9.99,0)) -> 0 | S12: =IF(P12>Q12+0.5,"OVER "&Assumptions!$D$9&"/wk – pace down",IF(R12>Assumptions!$D$102,"Full",IF(AND(Q12>=Assumptions!$D$103,P12<Assumptions!$D$103),"Under "&Assumptions!$D$103&" – release reserve",""))) | T12: =$F$38*(F12*(Budget!$G$21+Budget!$G$22+Budget!$G$23-$F$29-$F$36-$L$22-$L$26)+IF(A12-ROUNDUP(Funnel!$B$15/7,0)>=1,INDEX($X$4:$X$14,A12-ROUNDUP(Funnel!$B$15/7,0))*$F$29+INDEX($Y$4:$Y$14,A12-ROUNDUP(Funnel!$B$15/7,0))*$F$36+INDEX($AB$4:$AB$14,A12-ROUNDUP(Funnel!$B$15/7,0))*$L$22+INDEX($AC$4:$AC$14,A12-ROUNDUP(Funnel!$B$15/7,0))*$L$26,0)) -> 2.5020633 | U12: =$F$38*(G12*(Budget!$G$24-$F$30-$F$37)+IF(A12-ROUNDUP(Funnel!$B$16/7,0)>=1,INDEX($X$4:$X$14,A12-ROUNDUP(Funnel!$B$16/7,0))*$F$30+INDEX($Y$4:$Y$14,A12-ROUNDUP(Funnel!$B$16/7,0))*$F$37,0)) -> 0.30072917 | V12: =T12+U12 -> 2.8027925 | W12: =SUM($V$4:V12) -> 100 | X12: =IF(A12=1,Assumptions!$D$50,IF(A12=2,1-Assumptions!$D$50,0)) -> 0 | Y12: =0 -> 0 | Z12: =Assumptions!$D$61 -> 0 | AA12: =D12*IF(MAX(0,MIN(C12,Funnel!$B$19)-B12+1)>0,MAX(0,MIN(C12,Funnel!$B$20)-B12+1)/MAX(0,MIN(C12,Funnel!$B$19)-B12+1),0) -> 0 | AB12: =IF(SUM($AD$4:$AD$14)>0,AD12/SUM($AD$4:$AD$14),IF(SUM($AF$4:$AF$14)>0,AF12/SUM($AF$4:$AF$14),0)) -> 0 | AC12: =IF(SUM($AE$4:$AE$14)>0,AE12/SUM($AE$4:$AE$14),IF(SUM($AG$4:$AG$14)>0,AG12/SUM($AG$4:$AG$14),0)) -> 0 | AD12: =D12*IF(MAX(0,MIN(C12,Funnel!$B$19)-B12+1)>0,MAX(0,MIN(C12,Funnel!$B$19)-MAX(B12,Assumptions!$D$7+Assumptions!$D$181)+1)/MAX(0,MIN(C12,Funnel!$B$19)-B12+1),0) -> 0 | AE12: =D12*IF(MAX(0,MIN(C12,Funnel!$B$19)-B12+1)>0,MAX(0,MIN(C12,Funnel!$B$19)-MAX(B12,Assumptions!$D$7+Assumptions!$D$182)+1)/MAX(0,MIN(C12,Funnel!$B$19)-B12+1),0) -> 0 | AF12: =MAX(0,MIN(C12,Funnel!$B$19)-MAX(B12,Assumptions!$D$7+Assumptions!$D$181)+1) -> 0 | AG12: =MAX(0,MIN(C12,Funnel!$B$19)-MAX(B12,Assumptions!$D$7+Assumptions!$D$182)+1) -> 0
A13: 10 | B13: =Assumptions!$D$7+7*(A13-1) -> 46378 | C13: =MIN(B13+6,Assumptions!$D$8) -> 46384 | D13: =IF(SUMPRODUCT(($B$4:$B$14<=Funnel!$B$19)*$Z$4:$Z$14)>0,IF(B13<=Funnel!$B$19,Z13,0)/SUMPRODUCT(($B$4:$B$14<=Funnel!$B$19)*$Z$4:$Z$14),0) -> 0 | E13: =IF(SUM($AA$4:$AA$14)>0,AA13/SUM($AA$4:$AA$14),0) -> 0 | F13: =IF(A13-ROUNDUP(Funnel!$B$15/7,0)>=1,INDEX($D$4:$D$14,A13-ROUNDUP(Funnel!$B$15/7,0)),0) -> 0 | G13: =IF(A13-ROUNDUP(Funnel!$B$16/7,0)>=1,INDEX($E$4:$E$14,A13-ROUNDUP(Funnel!$B$16/7,0)),0) -> 0 | H13: =($F$19-$L$19-$L$23)*D13+$L$19*AB13+$L$23*AC13+$F$20*E13+$F$31*Y13 -> 0 | I13: =IF(A13=1,$F$21,0) -> 0 | J13: =$F$22*F13+$F$23*G13 -> 0 | K13: =IF(A13=1,Budget!$C$6,0) -> 0 | L13: =$F$24*X13 -> 0 | M13: =SUM(H13:L13) -> 0 | N13: =SUM($M$4:M13) -> 102255.85 | O13: =(Funnel!$M$5+Funnel!$M$6+Funnel!$M$7-$F$27-$F$34-$L$20-$L$24)*D13+$L$20*AB13+$L$24*AC13+(Funnel!$M$8-$F$28-$F$35)*E13+($F$27+$F$28)*X13+($F$34+$F$35)*Y13 -> 0 | P13: =(Funnel!$O$5+Funnel!$O$6+Funnel!$O$7-$F$25-$F$32-$L$21-$L$25)*D13+$L$21*AB13+$L$25*AC13+(Funnel!$O$8-$F$26-$F$33)*E13+($F$25+$F$26)*X13+($F$32+$F$33)*Y13 -> 0 | Q13: =Assumptions!$D$9*MAX(0,MIN(C13+Assumptions!$D$21,Funnel!$B$17)-MAX(IF(A13=1,Funnel!$B$13,B13+Assumptions!$D$21),Funnel!$B$13)+1)/7 -> 0 | R13: =IF(Q13>0,P13/Q13,IF(P13>0,9.99,0)) -> 0 | S13: =IF(P13>Q13+0.5,"OVER "&Assumptions!$D$9&"/wk – pace down",IF(R13>Assumptions!$D$102,"Full",IF(AND(Q13>=Assumptions!$D$103,P13<Assumptions!$D$103),"Under "&Assumptions!$D$103&" – release reserve",""))) | T13: =$F$38*(F13*(Budget!$G$21+Budget!$G$22+Budget!$G$23-$F$29-$F$36-$L$22-$L$26)+IF(A13-ROUNDUP(Funnel!$B$15/7,0)>=1,INDEX($X$4:$X$14,A13-ROUNDUP(Funnel!$B$15/7,0))*$F$29+INDEX($Y$4:$Y$14,A13-ROUNDUP(Funnel!$B$15/7,0))*$F$36+INDEX($AB$4:$AB$14,A13-ROUNDUP(Funnel!$B$15/7,0))*$L$22+INDEX($AC$4:$AC$14,A13-ROUNDUP(Funnel!$B$15/7,0))*$L$26,0)) -> 0 | U13: =$F$38*(G13*(Budget!$G$24-$F$30-$F$37)+IF(A13-ROUNDUP(Funnel!$B$16/7,0)>=1,INDEX($X$4:$X$14,A13-ROUNDUP(Funnel!$B$16/7,0))*$F$30+INDEX($Y$4:$Y$14,A13-ROUNDUP(Funnel!$B$16/7,0))*$F$37,0)) -> 0 | V13: =T13+U13 -> 0 | W13: =SUM($V$4:V13) -> 100 | X13: =IF(A13=1,Assumptions!$D$50,IF(A13=2,1-Assumptions!$D$50,0)) -> 0 | Y13: =0 -> 0 | Z13: =Assumptions!$D$62 -> 0 | AA13: =D13*IF(MAX(0,MIN(C13,Funnel!$B$19)-B13+1)>0,MAX(0,MIN(C13,Funnel!$B$20)-B13+1)/MAX(0,MIN(C13,Funnel!$B$19)-B13+1),0) -> 0 | AB13: =IF(SUM($AD$4:$AD$14)>0,AD13/SUM($AD$4:$AD$14),IF(SUM($AF$4:$AF$14)>0,AF13/SUM($AF$4:$AF$14),0)) -> 0 | AC13: =IF(SUM($AE$4:$AE$14)>0,AE13/SUM($AE$4:$AE$14),IF(SUM($AG$4:$AG$14)>0,AG13/SUM($AG$4:$AG$14),0)) -> 0 | AD13: =D13*IF(MAX(0,MIN(C13,Funnel!$B$19)-B13+1)>0,MAX(0,MIN(C13,Funnel!$B$19)-MAX(B13,Assumptions!$D$7+Assumptions!$D$181)+1)/MAX(0,MIN(C13,Funnel!$B$19)-B13+1),0) -> 0 | AE13: =D13*IF(MAX(0,MIN(C13,Funnel!$B$19)-B13+1)>0,MAX(0,MIN(C13,Funnel!$B$19)-MAX(B13,Assumptions!$D$7+Assumptions!$D$182)+1)/MAX(0,MIN(C13,Funnel!$B$19)-B13+1),0) -> 0 | AF13: =MAX(0,MIN(C13,Funnel!$B$19)-MAX(B13,Assumptions!$D$7+Assumptions!$D$181)+1) -> 0 | AG13: =MAX(0,MIN(C13,Funnel!$B$19)-MAX(B13,Assumptions!$D$7+Assumptions!$D$182)+1) -> 0
A14: 11 | B14: =Assumptions!$D$7+7*(A14-1) -> 46385 | C14: =MIN(B14+6,Assumptions!$D$8) -> 46387 | D14: =IF(SUMPRODUCT(($B$4:$B$14<=Funnel!$B$19)*$Z$4:$Z$14)>0,IF(B14<=Funnel!$B$19,Z14,0)/SUMPRODUCT(($B$4:$B$14<=Funnel!$B$19)*$Z$4:$Z$14),0) -> 0 | E14: =IF(SUM($AA$4:$AA$14)>0,AA14/SUM($AA$4:$AA$14),0) -> 0 | F14: =IF(A14-ROUNDUP(Funnel!$B$15/7,0)>=1,INDEX($D$4:$D$14,A14-ROUNDUP(Funnel!$B$15/7,0)),0) -> 0 | G14: =IF(A14-ROUNDUP(Funnel!$B$16/7,0)>=1,INDEX($E$4:$E$14,A14-ROUNDUP(Funnel!$B$16/7,0)),0) -> 0 | H14: =($F$19-$L$19-$L$23)*D14+$L$19*AB14+$L$23*AC14+$F$20*E14+$F$31*Y14 -> 0 | I14: =IF(A14=1,$F$21,0) -> 0 | J14: =$F$22*F14+$F$23*G14 -> 0 | K14: =IF(A14=1,Budget!$C$6,0) -> 0 | L14: =$F$24*X14 -> 0 | M14: =SUM(H14:L14) -> 0 | N14: =SUM($M$4:M14) -> 102255.85 | O14: =(Funnel!$M$5+Funnel!$M$6+Funnel!$M$7-$F$27-$F$34-$L$20-$L$24)*D14+$L$20*AB14+$L$24*AC14+(Funnel!$M$8-$F$28-$F$35)*E14+($F$27+$F$28)*X14+($F$34+$F$35)*Y14 -> 0 | P14: =(Funnel!$O$5+Funnel!$O$6+Funnel!$O$7-$F$25-$F$32-$L$21-$L$25)*D14+$L$21*AB14+$L$25*AC14+(Funnel!$O$8-$F$26-$F$33)*E14+($F$25+$F$26)*X14+($F$32+$F$33)*Y14 -> 0 | Q14: =Assumptions!$D$9*MAX(0,MIN(C14+Assumptions!$D$21,Funnel!$B$17)-MAX(IF(A14=1,Funnel!$B$13,B14+Assumptions!$D$21),Funnel!$B$13)+1)/7 -> 0 | R14: =IF(Q14>0,P14/Q14,IF(P14>0,9.99,0)) -> 0 | S14: =IF(P14>Q14+0.5,"OVER "&Assumptions!$D$9&"/wk – pace down",IF(R14>Assumptions!$D$102,"Full",IF(AND(Q14>=Assumptions!$D$103,P14<Assumptions!$D$103),"Under "&Assumptions!$D$103&" – release reserve",""))) | T14: =$F$38*(F14*(Budget!$G$21+Budget!$G$22+Budget!$G$23-$F$29-$F$36-$L$22-$L$26)+IF(A14-ROUNDUP(Funnel!$B$15/7,0)>=1,INDEX($X$4:$X$14,A14-ROUNDUP(Funnel!$B$15/7,0))*$F$29+INDEX($Y$4:$Y$14,A14-ROUNDUP(Funnel!$B$15/7,0))*$F$36+INDEX($AB$4:$AB$14,A14-ROUNDUP(Funnel!$B$15/7,0))*$L$22+INDEX($AC$4:$AC$14,A14-ROUNDUP(Funnel!$B$15/7,0))*$L$26,0)) -> 0 | U14: =$F$38*(G14*(Budget!$G$24-$F$30-$F$37)+IF(A14-ROUNDUP(Funnel!$B$16/7,0)>=1,INDEX($X$4:$X$14,A14-ROUNDUP(Funnel!$B$16/7,0))*$F$30+INDEX($Y$4:$Y$14,A14-ROUNDUP(Funnel!$B$16/7,0))*$F$37,0)) -> 0 | V14: =T14+U14 -> 0 | W14: =SUM($V$4:V14) -> 100 | X14: =IF(A14=1,Assumptions!$D$50,IF(A14=2,1-Assumptions!$D$50,0)) -> 0 | Y14: =0 -> 0 | Z14: =Assumptions!$D$63 -> 0 | AA14: =D14*IF(MAX(0,MIN(C14,Funnel!$B$19)-B14+1)>0,MAX(0,MIN(C14,Funnel!$B$20)-B14+1)/MAX(0,MIN(C14,Funnel!$B$19)-B14+1),0) -> 0 | AB14: =IF(SUM($AD$4:$AD$14)>0,AD14/SUM($AD$4:$AD$14),IF(SUM($AF$4:$AF$14)>0,AF14/SUM($AF$4:$AF$14),0)) -> 0 | AC14: =IF(SUM($AE$4:$AE$14)>0,AE14/SUM($AE$4:$AE$14),IF(SUM($AG$4:$AG$14)>0,AG14/SUM($AG$4:$AG$14),0)) -> 0 | AD14: =D14*IF(MAX(0,MIN(C14,Funnel!$B$19)-B14+1)>0,MAX(0,MIN(C14,Funnel!$B$19)-MAX(B14,Assumptions!$D$7+Assumptions!$D$181)+1)/MAX(0,MIN(C14,Funnel!$B$19)-B14+1),0) -> 0 | AE14: =D14*IF(MAX(0,MIN(C14,Funnel!$B$19)-B14+1)>0,MAX(0,MIN(C14,Funnel!$B$19)-MAX(B14,Assumptions!$D$7+Assumptions!$D$182)+1)/MAX(0,MIN(C14,Funnel!$B$19)-B14+1),0) -> 0 | AF14: =MAX(0,MIN(C14,Funnel!$B$19)-MAX(B14,Assumptions!$D$7+Assumptions!$D$181)+1) -> 0 | AG14: =MAX(0,MIN(C14,Funnel!$B$19)-MAX(B14,Assumptions!$D$7+Assumptions!$D$182)+1) -> 0
A15: Total | D15: =SUM(D4:D14) -> 1 | E15: =SUM(E4:E14) -> 1 | F15: =SUM(F4:F14) -> 1 | G15: =SUM(G4:G14) -> 1 | H15: =SUM(H4:H14) -> 74882.12 | I15: =SUM(I4:I14) -> 5796 | J15: =SUM(J4:J14) -> 10977.728 | K15: =SUM(K4:K14) -> 1600 | ... M15: =SUM(M4:M14) -> 102255.85 | O15: =SUM(O4:O14) -> 1494.5752 | P15: =SUM(P4:P14) -> 307.97308 | Q15: =SUM(Q4:Q14) -> 314.28571 | S15: =IF(LEFT(Summary!$C$19,1)<>"✓",Summary!$C$19,IF(Assumptions!$D$48>=1,"✗ reserve share must be below 100%",IF(Funnel!B19<Assumptions!$D$7,"✗ no application can sign by the deadline (Funnel B19 is before the campaign starts)",IF(AND(Budget!G24>0,Funnel!B20<Assumptions!$D$7),"✗ supervisors cannot apply in time (Funnel B20 is before the campaign starts)",IF(Funnel!B13>Funnel!B17,"✗ assessments start (Funnel B13) after the last useful assessment day (Funnel B17): no hire can sign in time",IF(SUMPRODUCT(($B$4:$B$14<=Funnel!$B$19)*$Z$4:$Z$14)<=0.0001,"✗ no spend share falls before the last useful application (Funnel B19): move shares into the early weeks",IF(OR(ABS(Z15-1)>0.001,ABS(Y15-1)>0.001),"✗ shares must sum to 100%",IF(AND(F20>0,ABS(E15-1)>0.001),"✗ no spend share falls before the supervisor cut-off (Funnel B20): move weekly shares into weeks 1–5",IF(ABS(M15-Budget!C9)>1,"✗ weeks ≠ planned spend",IF(ABS(P15-Funnel!O9)>0.5,"✗ qualified ≠ plan",IF(ABS(V15-Budget!C13)>0.5,"✗ signatures ≠ expected hires","✓ ties to plan"&IF(SUMPRODUCT(($B$4:$B$14>Funnel!$B$19)*$Z$4:$Z$14)>0.0001," · ℹ "&TEXT(SUMPRODUCT(($B$4:$B$14>Funnel!$B$19)*$Z$4:$Z$14),"0%")&" of the weekly input shares (col Z) fall after the last useful application and are re-spread over earlier weeks (col D)","")))))))))))) -> ✓ ties to plan | T15: =SUM(T4:T14) -> 90 | U15: =SUM(U4:U14) -> 10 | V15: =SUM(V4:V14) -> 100 | X15: =SUM(X4:X14) -> 1 | Y15: =SUM(Y4:Y14) -> 1 | Z15: =SUM(Z4:Z14) -> 1
A16: Weak channels are cut from Mon 2 Nov; tests are judged by Mon 9 Nov; the reserve is released only from week 3, on the Tracker rules.
A18: Helper totals | H18: Late launches (paced from their go-live dates, cols AB–AE)
B19: Spreadable media E/M/A (after tests, excl. rediscovery) | F19: =SUMIFS(Channels!$X$5:$X$34,Channels!$C$5:$C$34,"<>Supervisors",Channels!$E$5:$E$34,"<>Slot",Channels!$B$5:$B$34,"<>I1b Employee referral sprint (bonus on hire)",Channels!$B$5:$B$34,"<>I1a Talent rediscovery (past applicants in ATS)")-SUMIFS(Channels!$Z$5:$Z$34,Channels!$C$5:$C$34,"<>Supervisors") -> 62640.152 | H19: I2 media € | L19: =SUMIFS(Channels!$X$5:$X$34,Channels!$B$5:$B$34,"I2 Handwerk → Industrie (construction electricians)") -> 9912
B20: Spreadable media Supervisors (after tests, excl. rediscovery) | F20: =SUMIFS(Channels!$X$5:$X$34,Channels!$C$5:$C$34,"Supervisors",Channels!$E$5:$E$34,"<>Slot",Channels!$B$5:$B$34,"<>I1b Employee referral sprint (bonus on hire)",Channels!$B$5:$B$34,"<>I1a Talent rediscovery (past applicants in ATS)")-SUMIFS(Channels!$Z$5:$Z$34,Channels!$C$5:$C$34,"Supervisors") -> 12178.668 | H20: I2 applications | L20: =SUMIFS(Channels!$W$5:$W$34,Channels!$B$5:$B$34,"I2 Handwerk → Industrie (construction electricians)") -> 118
B21: StepStone ads (all roles) | F21: =SUMIFS(Channels!$X$5:$X$34,Channels!$E$5:$E$34,"Slot") -> 5796 | H21: I2 qualified | L21: =SUMIFS(Channels!$V$5:$V$34,Channels!$B$5:$B$34,"I2 Handwerk → Industrie (construction electricians)") -> 29.5
B22: Referral bonuses E/M/A | F22: =SUMIFS(Channels!$X$5:$X$34,Channels!$B$5:$B$34,"I1b Employee referral sprint (bonus on hire)",Channels!$C$5:$C$34,"<>Supervisors") -> 9869.2425 | H22: I2 hires | L22: =SUMIFS(Channels!$U$5:$U$34,Channels!$B$5:$B$34,"I2 Handwerk → Industrie (construction electricians)") -> 8.36325
B23: Referral bonuses Supervisors | F23: =SUMIFS(Channels!$X$5:$X$34,Channels!$B$5:$B$34,"I1b Employee referral sprint (bonus on hire)",Channels!$C$5:$C$34,"Supervisors") -> 1108.485 | H23: I3 media € | L23: =SUMIFS(Channels!$X$5:$X$34,Channels!$B$5:$B$34,"I3 Polish border corridor + PL pre-screener") -> 6493.5065
B24: Test tranches (all roles) | F24: =SUM(Channels!$Z$5:$Z$34) -> 9000 | H24: I3 applications | L24: =SUMIFS(Channels!$W$5:$W$34,Channels!$B$5:$B$34,"I3 Polish border corridor + PL pre-screener") -> 346.32035
B25: Test qualified E/M/A | F25: =SUMIFS(Channels!$AF$5:$AF$34,Channels!$C$5:$C$34,"<>Supervisors") -> 8.9323003 | H25: I3 qualified | L25: =SUMIFS(Channels!$V$5:$V$34,Channels!$B$5:$B$34,"I3 Polish border corridor + PL pre-screener") -> 48.484848
B26: Test qualified Supervisors | F26: =SUMIFS(Channels!$AF$5:$AF$34,Channels!$C$5:$C$34,"Supervisors") -> 3.2560542 | H26: I3 hires | L26: =SUMIFS(Channels!$U$5:$U$34,Channels!$B$5:$B$34,"I3 Polish border corridor + PL pre-screener") -> 18
B27: Test applications E/M/A | F27: =SUMIFS(Channels!$AE$5:$AE$34,Channels!$C$5:$C$34,"<>Supervisors") -> 52.214631
B28: Test applications Supervisors | F28: =SUMIFS(Channels!$AE$5:$AE$34,Channels!$C$5:$C$34,"Supervisors") -> 16.660829
B29: Test hires E/M/A | F29: =SUMIFS(Channels!$AG$5:$AG$34,Channels!$C$5:$C$34,"<>Supervisors") -> 2.8538714
B30: Test hires Supervisors | F30: =SUMIFS(Channels!$AG$5:$AG$34,Channels!$C$5:$C$34,"Supervisors") -> 0.7749409
B31: Rediscovery spend (all roles) | F31: =SUMIFS(Channels!$X$5:$X$34,Channels!$B$5:$B$34,"I1a Talent rediscovery (past applicants in ATS)") -> 63.3
B32: Rediscovery qualified E/M/A | F32: =SUMIFS(Channels!$V$5:$V$34,Channels!$B$5:$B$34,"I1a Talent rediscovery (past applicants in ATS)",Channels!$C$5:$C$34,"<>Supervisors") -> 10.74
B33: Rediscovery qualified Supervisors | F33: =SUMIFS(Channels!$V$5:$V$34,Channels!$B$5:$B$34,"I1a Talent rediscovery (past applicants in ATS)",Channels!$C$5:$C$34,"Supervisors") -> 1.92
B34: Rediscovery applications E/M/A | F34: =SUMIFS(Channels!$W$5:$W$34,Channels!$B$5:$B$34,"I1a Talent rediscovery (past applicants in ATS)",Channels!$C$5:$C$34,"<>Supervisors") -> 21.48
B35: Rediscovery applications Supervisors | F35: =SUMIFS(Channels!$W$5:$W$34,Channels!$B$5:$B$34,"I1a Talent rediscovery (past applicants in ATS)",Channels!$C$5:$C$34,"Supervisors") -> 3.84
B36: Rediscovery hires E/M/A | F36: =SUMIFS(Channels!$U$5:$U$34,Channels!$B$5:$B$34,"I1a Talent rediscovery (past applicants in ATS)",Channels!$C$5:$C$34,"<>Supervisors") -> 4.102947
B37: Rediscovery hires Supervisors | F37: =SUMIFS(Channels!$U$5:$U$34,Channels!$B$5:$B$34,"I1a Talent rediscovery (past applicants in ATS)",Channels!$C$5:$C$34,"Supervisors") -> 0.525504
B38: Capacity factor (share of planned qualified that can be assessed) | F38: =IF(Funnel!B23>0,MIN(1,Funnel!B22/Funnel!B23),1) -> 1
A42: Cash out by channel × week (€)
B43: Channel | C43: Wk 1 | D43: Wk 2 | E43: Wk 3 | F43: Wk 4 | G43: Wk 5 | H43: Wk 6 | I43: Wk 7 | J43: Wk 8 | K43: Wk 9 | L43: Wk 10 | M43: Wk 11 | N43: Total
B44: =Budget!B29 -> Organic (Tesla careers, BA Jobbörse, Google for Jobs) | C44: =(SUMIFS(Channels!$X$5:$X$34,Channels!$B$5:$B$34,$B44,Channels!$C$5:$C$34,"<>Supervisors",Channels!$E$5:$E$34,"<>Slot")-SUMIFS(Channels!$Z$5:$Z$34,Channels!$B$5:$B$34,$B44,Channels!$C$5:$C$34,"<>Supervisors"))*$D$4+(SUMIFS(Channels!$X$5:$X$34,Channels!$B$5:$B$34,$B44,Channels!$C$5:$C$34,"Supervisors",Channels!$E$5:$E$34,"<>Slot")-SUMIFS(Channels!$Z$5:$Z$34,Channels!$B$5:$B$34,$B44,Channels!$C$5:$C$34,"Supervisors"))*$E$4+SUMIFS(Channels!$Z$5:$Z$34,Channels!$B$5:$B$34,$B44)*$X$4+SUMIFS(Channels!$X$5:$X$34,Channels!$B$5:$B$34,$B44,Channels!$E$5:$E$34,"Slot")+SUMIFS(Channels!$Y$5:$Y$34,Channels!$B$5:$B$34,$B44) -> 0 | D44: =(SUMIFS(Channels!$X$5:$X$34,Channels!$B$5:$B$34,$B44,Channels!$C$5:$C$34,"<>Supervisors",Channels!$E$5:$E$34,"<>Slot")-SUMIFS(Channels!$Z$5:$Z$34,Channels!$B$5:$B$34,$B44,Channels!$C$5:$C$34,"<>Supervisors"))*$D$5+(SUMIFS(Channels!$X$5:$X$34,Channels!$B$5:$B$34,$B44,Channels!$C$5:$C$34,"Supervisors",Channels!$E$5:$E$34,"<>Slot")-SUMIFS(Channels!$Z$5:$Z$34,Channels!$B$5:$B$34,$B44,Channels!$C$5:$C$34,"Supervisors"))*$E$5+SUMIFS(Channels!$Z$5:$Z$34,Channels!$B$5:$B$34,$B44)*$X$5 -> 0 | E44: =(SUMIFS(Channels!$X$5:$X$34,Channels!$B$5:$B$34,$B44,Channels!$C$5:$C$34,"<>Supervisors",Channels!$E$5:$E$34,"<>Slot")-SUMIFS(Channels!$Z$5:$Z$34,Channels!$B$5:$B$34,$B44,Channels!$C$5:$C$34,"<>Supervisors"))*$D$6+(SUMIFS(Channels!$X$5:$X$34,Channels!$B$5:$B$34,$B44,Channels!$C$5:$C$34,"Supervisors",Channels!$E$5:$E$34,"<>Slot")-SUMIFS(Channels!$Z$5:$Z$34,Channels!$B$5:$B$34,$B44,Channels!$C$5:$C$34,"Supervisors"))*$E$6+SUMIFS(Channels!$Z$5:$Z$34,Channels!$B$5:$B$34,$B44)*$X$6 -> 0 | F44: =(SUMIFS(Channels!$X$5:$X$34,Channels!$B$5:$B$34,$B44,Channels!$C$5:$C$34,"<>Supervisors",Channels!$E$5:$E$34,"<>Slot")-SUMIFS(Channels!$Z$5:$Z$34,Channels!$B$5:$B$34,$B44,Channels!$C$5:$C$34,"<>Supervisors"))*$D$7+(SUMIFS(Channels!$X$5:$X$34,Channels!$B$5:$B$34,$B44,Channels!$C$5:$C$34,"Supervisors",Channels!$E$5:$E$34,"<>Slot")-SUMIFS(Channels!$Z$5:$Z$34,Channels!$B$5:$B$34,$B44,Channels!$C$5:$C$34,"Supervisors"))*$E$7+SUMIFS(Channels!$Z$5:$Z$34,Channels!$B$5:$B$34,$B44)*$X$7 -> 0 | G44: =(SUMIFS(Channels!$X$5:$X$34,Channels!$B$5:$B$34,$B44,Channels!$C$5:$C$34,"<>Supervisors",Channels!$E$5:$E$34,"<>Slot")-SUMIFS(Channels!$Z$5:$Z$34,Channels!$B$5:$B$34,$B44,Channels!$C$5:$C$34,"<>Supervisors"))*$D$8+(SUMIFS(Channels!$X$5:$X$34,Channels!$B$5:$B$34,$B44,Channels!$C$5:$C$34,"Supervisors",Channels!$E$5:$E$34,"<>Slot")-SUMIFS(Channels!$Z$5:$Z$34,Channels!$B$5:$B$34,$B44,Channels!$C$5:$C$34,"Supervisors"))*$E$8+SUMIFS(Channels!$Z$5:$Z$34,Channels!$B$5:$B$34,$B44)*$X$8 -> 0 | H44: =(SUMIFS(Channels!$X$5:$X$34,Channels!$B$5:$B$34,$B44,Channels!$C$5:$C$34,"<>Supervisors",Channels!$E$5:$E$34,"<>Slot")-SUMIFS(Channels!$Z$5:$Z$34,Channels!$B$5:$B$34,$B44,Channels!$C$5:$C$34,"<>Supervisors"))*$D$9+(SUMIFS(Channels!$X$5:$X$34,Channels!$B$5:$B$34,$B44,Channels!$C$5:$C$34,"Supervisors",Channels!$E$5:$E$34,"<>Slot")-SUMIFS(Channels!$Z$5:$Z$34,Channels!$B$5:$B$34,$B44,Channels!$C$5:$C$34,"Supervisors"))*$E$9+SUMIFS(Channels!$Z$5:$Z$34,Channels!$B$5:$B$34,$B44)*$X$9 -> 0 | I44: =(SUMIFS(Channels!$X$5:$X$34,Channels!$B$5:$B$34,$B44,Channels!$C$5:$C$34,"<>Supervisors",Channels!$E$5:$E$34,"<>Slot")-SUMIFS(Channels!$Z$5:$Z$34,Channels!$B$5:$B$34,$B44,Channels!$C$5:$C$34,"<>Supervisors"))*$D$10+(SUMIFS(Channels!$X$5:$X$34,Channels!$B$5:$B$34,$B44,Channels!$C$5:$C$34,"Supervisors",Channels!$E$5:$E$34,"<>Slot")-SUMIFS(Channels!$Z$5:$Z$34,Channels!$B$5:$B$34,$B44,Channels!$C$5:$C$34,"Supervisors"))*$E$10+SUMIFS(Channels!$Z$5:$Z$34,Channels!$B$5:$B$34,$B44)*$X$10 -> 0 | J44: =(SUMIFS(Channels!$X$5:$X$34,Channels!$B$5:$B$34,$B44,Channels!$C$5:$C$34,"<>Supervisors",Channels!$E$5:$E$34,"<>Slot")-SUMIFS(Channels!$Z$5:$Z$34,Channels!$B$5:$B$34,$B44,Channels!$C$5:$C$34,"<>Supervisors"))*$D$11+(SUMIFS(Channels!$X$5:$X$34,Channels!$B$5:$B$34,$B44,Channels!$C$5:$C$34,"Supervisors",Channels!$E$5:$E$34,"<>Slot")-SUMIFS(Channels!$Z$5:$Z$34,Channels!$B$5:$B$34,$B44,Channels!$C$5:$C$34,"Supervisors"))*$E$11+SUMIFS(Channels!$Z$5:$Z$34,Channels!$B$5:$B$34,$B44)*$X$11 -> 0 | K44: =(SUMIFS(Channels!$X$5:$X$34,Channels!$B$5:$B$34,$B44,Channels!$C$5:$C$34,"<>Supervisors",Channels!$E$5:$E$34,"<>Slot")-SUMIFS(Channels!$Z$5:$Z$34,Channels!$B$5:$B$34,$B44,Channels!$C$5:$C$34,"<>Supervisors"))*$D$12+(SUMIFS(Channels!$X$5:$X$34,Channels!$B$5:$B$34,$B44,Channels!$C$5:$C$34,"Supervisors",Channels!$E$5:$E$34,"<>Slot")-SUMIFS(Channels!$Z$5:$Z$34,Channels!$B$5:$B$34,$B44,Channels!$C$5:$C$34,"Supervisors"))*$E$12+SUMIFS(Channels!$Z$5:$Z$34,Channels!$B$5:$B$34,$B44)*$X$12 -> 0 | L44: =(SUMIFS(Channels!$X$5:$X$34,Channels!$B$5:$B$34,$B44,Channels!$C$5:$C$34,"<>Supervisors",Channels!$E$5:$E$34,"<>Slot")-SUMIFS(Channels!$Z$5:$Z$34,Channels!$B$5:$B$34,$B44,Channels!$C$5:$C$34,"<>Supervisors"))*$D$13+(SUMIFS(Channels!$X$5:$X$34,Channels!$B$5:$B$34,$B44,Channels!$C$5:$C$34,"Supervisors",Channels!$E$5:$E$34,"<>Slot")-SUMIFS(Channels!$Z$5:$Z$34,Channels!$B$5:$B$34,$B44,Channels!$C$5:$C$34,"Supervisors"))*$E$13+SUMIFS(Channels!$Z$5:$Z$34,Channels!$B$5:$B$34,$B44)*$X$13 -> 0 | M44: =(SUMIFS(Channels!$X$5:$X$34,Channels!$B$5:$B$34,$B44,Channels!$C$5:$C$34,"<>Supervisors",Channels!$E$5:$E$34,"<>Slot")-SUMIFS(Channels!$Z$5:$Z$34,Channels!$B$5:$B$34,$B44,Channels!$C$5:$C$34,"<>Supervisors"))*$D$14+(SUMIFS(Channels!$X$5:$X$34,Channels!$B$5:$B$34,$B44,Channels!$C$5:$C$34,"Supervisors",Channels!$E$5:$E$34,"<>Slot")-SUMIFS(Channels!$Z$5:$Z$34,Channels!$B$5:$B$34,$B44,Channels!$C$5:$C$34,"Supervisors"))*$E$14+SUMIFS(Channels!$Z$5:$Z$34,Channels!$B$5:$B$34,$B44)*$X$14 -> 0 | N44: =SUM(C44:M44) -> 0
B45: =Budget!B30 -> Programmatic job ads (Joveo: Indeed, Jooble, Talent.com, Kimeta, meinestadt…) | C45: =(SUMIFS(Channels!$X$5:$X$34,Channels!$B$5:$B$34,$B45,Channels!$C$5:$C$34,"<>Supervisors",Channels!$E$5:$E$34,"<>Slot")-SUMIFS(Channels!$Z$5:$Z$34,Channels!$B$5:$B$34,$B45,Channels!$C$5:$C$34,"<>Supervisors"))*$D$4+(SUMIFS(Channels!$X$5:$X$34,Channels!$B$5:$B$34,$B45,Channels!$C$5:$C$34,"Supervisors",Channels!$E$5:$E$34,"<>Slot")-SUMIFS(Channels!$Z$5:$Z$34,Channels!$B$5:$B$34,$B45,Channels!$C$5:$C$34,"Supervisors"))*$E$4+SUMIFS(Channels!$Z$5:$Z$34,Channels!$B$5:$B$34,$B45)*$X$4+SUMIFS(Channels!$X$5:$X$34,Channels!$B$5:$B$34,$B45,Channels!$E$5:$E$34,"Slot")+SUMIFS(Channels!$Y$5:$Y$34,Channels!$B$5:$B$34,$B45) -> 11525.173 | D45: =(SUMIFS(Channels!$X$5:$X$34,Channels!$B$5:$B$34,$B45,Channels!$C$5:$C$34,"<>Supervisors",Channels!$E$5:$E$34,"<>Slot")-SUMIFS(Channels!$Z$5:$Z$34,Channels!$B$5:$B$34,$B45,Channels!$C$5:$C$34,"<>Supervisors"))*$D$5+(SUMIFS(Channels!$X$5:$X$34,Channels!$B$5:$B$34,$B45,Channels!$C$5:$C$34,"Supervisors",Channels!$E$5:$E$34,"<>Slot")-SUMIFS(Channels!$Z$5:$Z$34,Channels!$B$5:$B$34,$B45,Channels!$C$5:$C$34,"Supervisors"))*$E$5+SUMIFS(Channels!$Z$5:$Z$34,Channels!$B$5:$B$34,$B45)*$X$5 -> 6080.3722 | E45: =(SUMIFS(Channels!$X$5:$X$34,Channels!$B$5:$B$34,$B45,Channels!$C$5:$C$34,"<>Supervisors",Channels!$E$5:$E$34,"<>Slot")-SUMIFS(Channels!$Z$5:$Z$34,Channels!$B$5:$B$34,$B45,Channels!$C$5:$C$34,"<>Supervisors"))*$D$6+(SUMIFS(Channels!$X$5:$X$34,Channels!$B$5:$B$34,$B45,Channels!$C$5:$C$34,"Supervisors",Channels!$E$5:$E$34,"<>Slot")-SUMIFS(Channels!$Z$5:$Z$34,Channels!$B$5:$B$34,$B45,Channels!$C$5:$C$34,"Supervisors"))*$E$6+SUMIFS(Channels!$Z$5:$Z$34,Channels!$B$5:$B$34,$B45)*$X$6 -> 5260.6102 | F45: =(SUMIFS(Channels!$X$5:$X$34,Channels!$B$5:$B$34,$B45,Channels!$C$5:$C$34,"<>Supervisors",Channels!$E$5:$E$34,"<>Slot")-SUMIFS(Channels!$Z$5:$Z$34,Channels!$B$5:$B$34,$B45,Channels!$C$5:$C$34,"<>Supervisors"))*$D$7+(SUMIFS(Channels!$X$5:$X$34,Channels!$B$5:$B$34,$B45,Channels!$C$5:$C$34,"Supervisors",Channels!$E$5:$E$34,"<>Slot")-SUMIFS(Channels!$Z$5:$Z$34,Channels!$B$5:$B$34,$B45,Channels!$C$5:$C$34,"Supervisors"))*$E$7+SUMIFS(Channels!$Z$5:$Z$34,Channels!$B$5:$B$34,$B45)*$X$7 -> 5554.6815 | G45: =(SUMIFS(Channels!$X$5:$X$34,Channels!$B$5:$B$34,$B45,Channels!$C$5:$C$34,"<>Supervisors",Channels!$E$5:$E$34,"<>Slot")-SUMIFS(Channels!$Z$5:$Z$34,Channels!$B$5:$B$34,$B45,Channels!$C$5:$C$34,"<>Supervisors"))*$D$8+(SUMIFS(Channels!$X$5:$X$34,Channels!$B$5:$B$34,$B45,Channels!$C$5:$C$34,"Supervisors",Channels!$E$5:$E$34,"<>Slot")-SUMIFS(Channels!$Z$5:$Z$34,Channels!$B$5:$B$34,$B45,Channels!$C$5:$C$34,"Supervisors"))*$E$8+SUMIFS(Channels!$Z$5:$Z$34,Channels!$B$5:$B$34,$B45)*$X$8 -> 6371.5465 | H45: =(SUMIFS(Channels!$X$5:$X$34,Channels!$B$5:$B$34,$B45,Channels!$C$5:$C$34,"<>Supervisors",Channels!$E$5:$E$34,"<>Slot")-SUMIFS(Channels!$Z$5:$Z$34,Channels!$B$5:$B$34,$B45,Channels!$C$5:$C$34,"<>Supervisors"))*$D$9+(SUMIFS(Channels!$X$5:$X$34,Channels!$B$5:$B$34,$B45,Channels!$C$5:$C$34,"Supervisors",Channels!$E$5:$E$34,"<>Slot")-SUMIFS(Channels!$Z$5:$Z$34,Channels!$B$5:$B$34,$B45,Channels!$C$5:$C$34,"Supervisors"))*$E$9+SUMIFS(Channels!$Z$5:$Z$34,Channels!$B$5:$B$34,$B45)*$X$9 -> 882.21413 | I45: =(SUMIFS(Channels!$X$5:$X$34,Channels!$B$5:$B$34,$B45,Channels!$C$5:$C$34,"<>Supervisors",Channels!$E$5:$E$34,"<>Slot")-SUMIFS(Channels!$Z$5:$Z$34,Channels!$B$5:$B$34,$B45,Channels!$C$5:$C$34,"<>Supervisors"))*$D$10+(SUMIFS(Channels!$X$5:$X$34,Channels!$B$5:$B$34,$B45,Channels!$C$5:$C$34,"Supervisors",Channels!$E$5:$E$34,"<>Slot")-SUMIFS(Channels!$Z$5:$Z$34,Channels!$B$5:$B$34,$B45,Channels!$C$5:$C$34,"Supervisors"))*$E$10+SUMIFS(Channels!$Z$5:$Z$34,Channels!$B$5:$B$34,$B45)*$X$10 -> 0 | J45: =(SUMIFS(Channels!$X$5:$X$34,Channels!$B$5:$B$34,$B45,Channels!$C$5:$C$34,"<>Supervisors",Channels!$E$5:$E$34,"<>Slot")-SUMIFS(Channels!$Z$5:$Z$34,Channels!$B$5:$B$34,$B45,Channels!$C$5:$C$34,"<>Supervisors"))*$D$11+(SUMIFS(Channels!$X$5:$X$34,Channels!$B$5:$B$34,$B45,Channels!$C$5:$C$34,"Supervisors",Channels!$E$5:$E$34,"<>Slot")-SUMIFS(Channels!$Z$5:$Z$34,Channels!$B$5:$B$34,$B45,Channels!$C$5:$C$34,"Supervisors"))*$E$11+SUMIFS(Channels!$Z$5:$Z$34,Channels!$B$5:$B$34,$B45)*$X$11 -> 0 | K45: =(SUMIFS(Channels!$X$5:$X$34,Channels!$B$5:$B$34,$B45,Channels!$C$5:$C$34,"<>Supervisors",Channels!$E$5:$E$34,"<>Slot")-SUMIFS(Channels!$Z$5:$Z$34,Channels!$B$5:$B$34,$B45,Channels!$C$5:$C$34,"<>Supervisors"))*$D$12+(SUMIFS(Channels!$X$5:$X$34,Channels!$B$5:$B$34,$B45,Channels!$C$5:$C$34,"Supervisors",Channels!$E$5:$E$34,"<>Slot")-SUMIFS(Channels!$Z$5:$Z$34,Channels!$B$5:$B$34,$B45,Channels!$C$5:$C$34,"Supervisors"))*$E$12+SUMIFS(Channels!$Z$5:$Z$34,Channels!$B$5:$B$34,$B45)*$X$12 -> 0 | L45: =(SUMIFS(Channels!$X$5:$X$34,Channels!$B$5:$B$34,$B45,Channels!$C$5:$C$34,"<>Supervisors",Channels!$E$5:$E$34,"<>Slot")-SUMIFS(Channels!$Z$5:$Z$34,Channels!$B$5:$B$34,$B45,Channels!$C$5:$C$34,"<>Supervisors"))*$D$13+(SUMIFS(Channels!$X$5:$X$34,Channels!$B$5:$B$34,$B45,Channels!$C$5:$C$34,"Supervisors",Channels!$E$5:$E$34,"<>Slot")-SUMIFS(Channels!$Z$5:$Z$34,Channels!$B$5:$B$34,$B45,Channels!$C$5:$C$34,"Supervisors"))*$E$13+SUMIFS(Channels!$Z$5:$Z$34,Channels!$B$5:$B$34,$B45)*$X$13 -> 0 | M45: =(SUMIFS(Channels!$X$5:$X$34,Channels!$B$5:$B$34,$B45,Channels!$C$5:$C$34,"<>Supervisors",Channels!$E$5:$E$34,"<>Slot")-SUMIFS(Channels!$Z$5:$Z$34,Channels!$B$5:$B$34,$B45,Channels!$C$5:$C$34,"<>Supervisors"))*$D$14+(SUMIFS(Channels!$X$5:$X$34,Channels!$B$5:$B$34,$B45,Channels!$C$5:$C$34,"Supervisors",Channels!$E$5:$E$34,"<>Slot")-SUMIFS(Channels!$Z$5:$Z$34,Channels!$B$5:$B$34,$B45,Channels!$C$5:$C$34,"Supervisors"))*$E$14+SUMIFS(Channels!$Z$5:$Z$34,Channels!$B$5:$B$34,$B45)*$X$14 -> 0 | N45: =SUM(C45:M45) -> 35674.597
B46: =Budget!B31 -> StepStone (30-day single ad) | C46: =(SUMIFS(Channels!$X$5:$X$34,Channels!$B$5:$B$34,$B46,Channels!$C$5:$C$34,"<>Supervisors",Channels!$E$5:$E$34,"<>Slot")-SUMIFS(Channels!$Z$5:$Z$34,Channels!$B$5:$B$34,$B46,Channels!$C$5:$C$34,"<>Supervisors"))*$D$4+(SUMIFS(Channels!$X$5:$X$34,Channels!$B$5:$B$34,$B46,Channels!$C$5:$C$34,"Supervisors",Channels!$E$5:$E$34,"<>Slot")-SUMIFS(Channels!$Z$5:$Z$34,Channels!$B$5:$B$34,$B46,Channels!$C$5:$C$34,"Supervisors"))*$E$4+SUMIFS(Channels!$Z$5:$Z$34,Channels!$B$5:$B$34,$B46)*$X$4+SUMIFS(Channels!$X$5:$X$34,Channels!$B$5:$B$34,$B46,Channels!$E$5:$E$34,"Slot")+SUMIFS(Channels!$Y$5:$Y$34,Channels!$B$5:$B$34,$B46) -> 5796 | D46: =(SUMIFS(Channels!$X$5:$X$34,Channels!$B$5:$B$34,$B46,Channels!$C$5:$C$34,"<>Supervisors",Channels!$E$5:$E$34,"<>Slot")-SUMIFS(Channels!$Z$5:$Z$34,Channels!$B$5:$B$34,$B46,Channels!$C$5:$C$34,"<>Supervisors"))*$D$5+(SUMIFS(Channels!$X$5:$X$34,Channels!$B$5:$B$34,$B46,Channels!$C$5:$C$34,"Supervisors",Channels!$E$5:$E$34,"<>Slot")-SUMIFS(Channels!$Z$5:$Z$34,Channels!$B$5:$B$34,$B46,Channels!$C$5:$C$34,"Supervisors"))*$E$5+SUMIFS(Channels!$Z$5:$Z$34,Channels!$B$5:$B$34,$B46)*$X$5 -> 0 | E46: =(SUMIFS(Channels!$X$5:$X$34,Channels!$B$5:$B$34,$B46,Channels!$C$5:$C$34,"<>Supervisors",Channels!$E$5:$E$34,"<>Slot")-SUMIFS(Channels!$Z$5:$Z$34,Channels!$B$5:$B$34,$B46,Channels!$C$5:$C$34,"<>Supervisors"))*$D$6+(SUMIFS(Channels!$X$5:$X$34,Channels!$B$5:$B$34,$B46,Channels!$C$5:$C$34,"Supervisors",Channels!$E$5:$E$34,"<>Slot")-SUMIFS(Channels!$Z$5:$Z$34,Channels!$B$5:$B$34,$B46,Channels!$C$5:$C$34,"Supervisors"))*$E$6+SUMIFS(Channels!$Z$5:$Z$34,Channels!$B$5:$B$34,$B46)*$X$6 -> 0 | F46: =(SUMIFS(Channels!$X$5:$X$34,Channels!$B$5:$B$34,$B46,Channels!$C$5:$C$34,"<>Supervisors",Channels!$E$5:$E$34,"<>Slot")-SUMIFS(Channels!$Z$5:$Z$34,Channels!$B$5:$B$34,$B46,Channels!$C$5:$C$34,"<>Supervisors"))*$D$7+(SUMIFS(Channels!$X$5:$X$34,Channels!$B$5:$B$34,$B46,Channels!$C$5:$C$34,"Supervisors",Channels!$E$5:$E$34,"<>Slot")-SUMIFS(Channels!$Z$5:$Z$34,Channels!$B$5:$B$34,$B46,Channels!$C$5:$C$34,"Supervisors"))*$E$7+SUMIFS(Channels!$Z$5:$Z$34,Channels!$B$5:$B$34,$B46)*$X$7 -> 0 | G46: =(SUMIFS(Channels!$X$5:$X$34,Channels!$B$5:$B$34,$B46,Channels!$C$5:$C$34,"<>Supervisors",Channels!$E$5:$E$34,"<>Slot")-SUMIFS(Channels!$Z$5:$Z$34,Channels!$B$5:$B$34,$B46,Channels!$C$5:$C$34,"<>Supervisors"))*$D$8+(SUMIFS(Channels!$X$5:$X$34,Channels!$B$5:$B$34,$B46,Channels!$C$5:$C$34,"Supervisors",Channels!$E$5:$E$34,"<>Slot")-SUMIFS(Channels!$Z$5:$Z$34,Channels!$B$5:$B$34,$B46,Channels!$C$5:$C$34,"Supervisors"))*$E$8+SUMIFS(Channels!$Z$5:$Z$34,Channels!$B$5:$B$34,$B46)*$X$8 -> 0 | H46: =(SUMIFS(Channels!$X$5:$X$34,Channels!$B$5:$B$34,$B46,Channels!$C$5:$C$34,"<>Supervisors",Channels!$E$5:$E$34,"<>Slot")-SUMIFS(Channels!$Z$5:$Z$34,Channels!$B$5:$B$34,$B46,Channels!$C$5:$C$34,"<>Supervisors"))*$D$9+(SUMIFS(Channels!$X$5:$X$34,Channels!$B$5:$B$34,$B46,Channels!$C$5:$C$34,"Supervisors",Channels!$E$5:$E$34,"<>Slot")-SUMIFS(Channels!$Z$5:$Z$34,Channels!$B$5:$B$34,$B46,Channels!$C$5:$C$34,"Supervisors"))*$E$9+SUMIFS(Channels!$Z$5:$Z$34,Channels!$B$5:$B$34,$B46)*$X$9 -> 0 | I46: =(SUMIFS(Channels!$X$5:$X$34,Channels!$B$5:$B$34,$B46,Channels!$C$5:$C$34,"<>Supervisors",Channels!$E$5:$E$34,"<>Slot")-SUMIFS(Channels!$Z$5:$Z$34,Channels!$B$5:$B$34,$B46,Channels!$C$5:$C$34,"<>Supervisors"))*$D$10+(SUMIFS(Channels!$X$5:$X$34,Channels!$B$5:$B$34,$B46,Channels!$C$5:$C$34,"Supervisors",Channels!$E$5:$E$34,"<>Slot")-SUMIFS(Channels!$Z$5:$Z$34,Channels!$B$5:$B$34,$B46,Channels!$C$5:$C$34,"Supervisors"))*$E$10+SUMIFS(Channels!$Z$5:$Z$34,Channels!$B$5:$B$34,$B46)*$X$10 -> 0 | J46: =(SUMIFS(Channels!$X$5:$X$34,Channels!$B$5:$B$34,$B46,Channels!$C$5:$C$34,"<>Supervisors",Channels!$E$5:$E$34,"<>Slot")-SUMIFS(Channels!$Z$5:$Z$34,Channels!$B$5:$B$34,$B46,Channels!$C$5:$C$34,"<>Supervisors"))*$D$11+(SUMIFS(Channels!$X$5:$X$34,Channels!$B$5:$B$34,$B46,Channels!$C$5:$C$34,"Supervisors",Channels!$E$5:$E$34,"<>Slot")-SUMIFS(Channels!$Z$5:$Z$34,Channels!$B$5:$B$34,$B46,Channels!$C$5:$C$34,"Supervisors"))*$E$11+SUMIFS(Channels!$Z$5:$Z$34,Channels!$B$5:$B$34,$B46)*$X$11 -> 0 | K46: =(SUMIFS(Channels!$X$5:$X$34,Channels!$B$5:$B$34,$B46,Channels!$C$5:$C$34,"<>Supervisors",Channels!$E$5:$E$34,"<>Slot")-SUMIFS(Channels!$Z$5:$Z$34,Channels!$B$5:$B$34,$B46,Channels!$C$5:$C$34,"<>Supervisors"))*$D$12+(SUMIFS(Channels!$X$5:$X$34,Channels!$B$5:$B$34,$B46,Channels!$C$5:$C$34,"Supervisors",Channels!$E$5:$E$34,"<>Slot")-SUMIFS(Channels!$Z$5:$Z$34,Channels!$B$5:$B$34,$B46,Channels!$C$5:$C$34,"Supervisors"))*$E$12+SUMIFS(Channels!$Z$5:$Z$34,Channels!$B$5:$B$34,$B46)*$X$12 -> 0 | L46: =(SUMIFS(Channels!$X$5:$X$34,Channels!$B$5:$B$34,$B46,Channels!$C$5:$C$34,"<>Supervisors",Channels!$E$5:$E$34,"<>Slot")-SUMIFS(Channels!$Z$5:$Z$34,Channels!$B$5:$B$34,$B46,Channels!$C$5:$C$34,"<>Supervisors"))*$D$13+(SUMIFS(Channels!$X$5:$X$34,Channels!$B$5:$B$34,$B46,Channels!$C$5:$C$34,"Supervisors",Channels!$E$5:$E$34,"<>Slot")-SUMIFS(Channels!$Z$5:$Z$34,Channels!$B$5:$B$34,$B46,Channels!$C$5:$C$34,"Supervisors"))*$E$13+SUMIFS(Channels!$Z$5:$Z$34,Channels!$B$5:$B$34,$B46)*$X$13 -> 0 | M46: =(SUMIFS(Channels!$X$5:$X$34,Channels!$B$5:$B$34,$B46,Channels!$C$5:$C$34,"<>Supervisors",Channels!$E$5:$E$34,"<>Slot")-SUMIFS(Channels!$Z$5:$Z$34,Channels!$B$5:$B$34,$B46,Channels!$C$5:$C$34,"<>Supervisors"))*$D$14+(SUMIFS(Channels!$X$5:$X$34,Channels!$B$5:$B$34,$B46,Channels!$C$5:$C$34,"Supervisors",Channels!$E$5:$E$34,"<>Slot")-SUMIFS(Channels!$Z$5:$Z$34,Channels!$B$5:$B$34,$B46,Channels!$C$5:$C$34,"Supervisors"))*$E$14+SUMIFS(Channels!$Z$5:$Z$34,Channels!$B$5:$B$34,$B46)*$X$14 -> 0 | N46: =SUM(C46:M46) -> 5796
B47: =Budget!B32 -> LinkedIn (promoted jobs + InMail) | C47: =(SUMIFS(Channels!$X$5:$X$34,Channels!$B$5:$B$34,$B47,Channels!$C$5:$C$34,"<>Supervisors",Channels!$E$5:$E$34,"<>Slot")-SUMIFS(Channels!$Z$5:$Z$34,Channels!$B$5:$B$34,$B47,Channels!$C$5:$C$34,"<>Supervisors"))*$D$4+(SUMIFS(Channels!$X$5:$X$34,Channels!$B$5:$B$34,$B47,Channels!$C$5:$C$34,"Supervisors",Channels!$E$5:$E$34,"<>Slot")-SUMIFS(Channels!$Z$5:$Z$34,Channels!$B$5:$B$34,$B47,Channels!$C$5:$C$34,"Supervisors"))*$E$4+SUMIFS(Channels!$Z$5:$Z$34,Channels!$B$5:$B$34,$B47)*$X$4+SUMIFS(Channels!$X$5:$X$34,Channels!$B$5:$B$34,$B47,Channels!$E$5:$E$34,"Slot")+SUMIFS(Channels!$Y$5:$Y$34,Channels!$B$5:$B$34,$B47) -> 9660.5848 | D47: =(SUMIFS(Channels!$X$5:$X$34,Channels!$B$5:$B$34,$B47,Channels!$C$5:$C$34,"<>Supervisors",Channels!$E$5:$E$34,"<>Slot")-SUMIFS(Channels!$Z$5:$Z$34,Channels!$B$5:$B$34,$B47,Channels!$C$5:$C$34,"<>Supervisors"))*$D$5+(SUMIFS(Channels!$X$5:$X$34,Channels!$B$5:$B$34,$B47,Channels!$C$5:$C$34,"Supervisors",Channels!$E$5:$E$34,"<>Slot")-SUMIFS(Channels!$Z$5:$Z$34,Channels!$B$5:$B$34,$B47,Channels!$C$5:$C$34,"Supervisors"))*$E$5+SUMIFS(Channels!$Z$5:$Z$34,Channels!$B$5:$B$34,$B47)*$X$5 -> 4656.1285 | E47: =(SUMIFS(Channels!$X$5:$X$34,Channels!$B$5:$B$34,$B47,Channels!$C$5:$C$34,"<>Supervisors",Channels!$E$5:$E$34,"<>Slot")-SUMIFS(Channels!$Z$5:$Z$34,Channels!$B$5:$B$34,$B47,Channels!$C$5:$C$34,"<>Supervisors"))*$D$6+(SUMIFS(Channels!$X$5:$X$34,Channels!$B$5:$B$34,$B47,Channels!$C$5:$C$34,"Supervisors",Channels!$E$5:$E$34,"<>Slot")-SUMIFS(Channels!$Z$5:$Z$34,Channels!$B$5:$B$34,$B47,Channels!$C$5:$C$34,"Supervisors"))*$E$6+SUMIFS(Channels!$Z$5:$Z$34,Channels!$B$5:$B$34,$B47)*$X$6 -> 4616.3106 | F47: =(SUMIFS(Channels!$X$5:$X$34,Channels!$B$5:$B$34,$B47,Channels!$C$5:$C$34,"<>Supervisors",Channels!$E$5:$E$34,"<>Slot")-SUMIFS(Channels!$Z$5:$Z$34,Channels!$B$5:$B$34,$B47,Channels!$C$5:$C$34,"<>Supervisors"))*$D$7+(SUMIFS(Channels!$X$5:$X$34,Channels!$B$5:$B$34,$B47,Channels!$C$5:$C$34,"Supervisors",Channels!$E$5:$E$34,"<>Slot")-SUMIFS(Channels!$Z$5:$Z$34,Channels!$B$5:$B$34,$B47,Channels!$C$5:$C$34,"Supervisors"))*$E$7+SUMIFS(Channels!$Z$5:$Z$34,Channels!$B$5:$B$34,$B47)*$X$7 -> 4874.3652 | G47: =(SUMIFS(Channels!$X$5:$X$34,Channels!$B$5:$B$34,$B47,Channels!$C$5:$C$34,"<>Supervisors",Channels!$E$5:$E$34,"<>Slot")-SUMIFS(Channels!$Z$5:$Z$34,Channels!$B$5:$B$34,$B47,Channels!$C$5:$C$34,"<>Supervisors"))*$D$8+(SUMIFS(Channels!$X$5:$X$34,Channels!$B$5:$B$34,$B47,Channels!$C$5:$C$34,"Supervisors",Channels!$E$5:$E$34,"<>Slot")-SUMIFS(Channels!$Z$5:$Z$34,Channels!$B$5:$B$34,$B47,Channels!$C$5:$C$34,"Supervisors"))*$E$8+SUMIFS(Channels!$Z$5:$Z$34,Channels!$B$5:$B$34,$B47)*$X$8 -> 3065.2058 | H47: =(SUMIFS(Channels!$X$5:$X$34,Channels!$B$5:$B$34,$B47,Channels!$C$5:$C$34,"<>Supervisors",Channels!$E$5:$E$34,"<>Slot")-SUMIFS(Channels!$Z$5:$Z$34,Channels!$B$5:$B$34,$B47,Channels!$C$5:$C$34,"<>Supervisors"))*$D$9+(SUMIFS(Channels!$X$5:$X$34,Channels!$B$5:$B$34,$B47,Channels!$C$5:$C$34,"Supervisors",Channels!$E$5:$E$34,"<>Slot")-SUMIFS(Channels!$Z$5:$Z$34,Channels!$B$5:$B$34,$B47,Channels!$C$5:$C$34,"Supervisors"))*$E$9+SUMIFS(Channels!$Z$5:$Z$34,Channels!$B$5:$B$34,$B47)*$X$9 -> 366.12131 | I47: =(SUMIFS(Channels!$X$5:$X$34,Channels!$B$5:$B$34,$B47,Channels!$C$5:$C$34,"<>Supervisors",Channels!$E$5:$E$34,"<>Slot")-SUMIFS(Channels!$Z$5:$Z$34,Channels!$B$5:$B$34,$B47,Channels!$C$5:$C$34,"<>Supervisors"))*$D$10+(SUMIFS(Channels!$X$5:$X$34,Channels!$B$5:$B$34,$B47,Channels!$C$5:$C$34,"Supervisors",Channels!$E$5:$E$34,"<>Slot")-SUMIFS(Channels!$Z$5:$Z$34,Channels!$B$5:$B$34,$B47,Channels!$C$5:$C$34,"Supervisors"))*$E$10+SUMIFS(Channels!$Z$5:$Z$34,Channels!$B$5:$B$34,$B47)*$X$10 -> 0 | J47: =(SUMIFS(Channels!$X$5:$X$34,Channels!$B$5:$B$34,$B47,Channels!$C$5:$C$34,"<>Supervisors",Channels!$E$5:$E$34,"<>Slot")-SUMIFS(Channels!$Z$5:$Z$34,Channels!$B$5:$B$34,$B47,Channels!$C$5:$C$34,"<>Supervisors"))*$D$11+(SUMIFS(Channels!$X$5:$X$34,Channels!$B$5:$B$34,$B47,Channels!$C$5:$C$34,"Supervisors",Channels!$E$5:$E$34,"<>Slot")-SUMIFS(Channels!$Z$5:$Z$34,Channels!$B$5:$B$34,$B47,Channels!$C$5:$C$34,"Supervisors"))*$E$11+SUMIFS(Channels!$Z$5:$Z$34,Channels!$B$5:$B$34,$B47)*$X$11 -> 0 | K47: =(SUMIFS(Channels!$X$5:$X$34,Channels!$B$5:$B$34,$B47,Channels!$C$5:$C$34,"<>Supervisors",Channels!$E$5:$E$34,"<>Slot")-SUMIFS(Channels!$Z$5:$Z$34,Channels!$B$5:$B$34,$B47,Channels!$C$5:$C$34,"<>Supervisors"))*$D$12+(SUMIFS(Channels!$X$5:$X$34,Channels!$B$5:$B$34,$B47,Channels!$C$5:$C$34,"Supervisors",Channels!$E$5:$E$34,"<>Slot")-SUMIFS(Channels!$Z$5:$Z$34,Channels!$B$5:$B$34,$B47,Channels!$C$5:$C$34,"Supervisors"))*$E$12+SUMIFS(Channels!$Z$5:$Z$34,Channels!$B$5:$B$34,$B47)*$X$12 -> 0 | L47: =(SUMIFS(Channels!$X$5:$X$34,Channels!$B$5:$B$34,$B47,Channels!$C$5:$C$34,"<>Supervisors",Channels!$E$5:$E$34,"<>Slot")-SUMIFS(Channels!$Z$5:$Z$34,Channels!$B$5:$B$34,$B47,Channels!$C$5:$C$34,"<>Supervisors"))*$D$13+(SUMIFS(Channels!$X$5:$X$34,Channels!$B$5:$B$34,$B47,Channels!$C$5:$C$34,"Supervisors",Channels!$E$5:$E$34,"<>Slot")-SUMIFS(Channels!$Z$5:$Z$34,Channels!$B$5:$B$34,$B47,Channels!$C$5:$C$34,"Supervisors"))*$E$13+SUMIFS(Channels!$Z$5:$Z$34,Channels!$B$5:$B$34,$B47)*$X$13 -> 0 | M47: =(SUMIFS(Channels!$X$5:$X$34,Channels!$B$5:$B$34,$B47,Channels!$C$5:$C$34,"<>Supervisors",Channels!$E$5:$E$34,"<>Slot")-SUMIFS(Channels!$Z$5:$Z$34,Channels!$B$5:$B$34,$B47,Channels!$C$5:$C$34,"<>Supervisors"))*$D$14+(SUMIFS(Channels!$X$5:$X$34,Channels!$B$5:$B$34,$B47,Channels!$C$5:$C$34,"Supervisors",Channels!$E$5:$E$34,"<>Slot")-SUMIFS(Channels!$Z$5:$Z$34,Channels!$B$5:$B$34,$B47,Channels!$C$5:$C$34,"Supervisors"))*$E$14+SUMIFS(Channels!$Z$5:$Z$34,Channels!$B$5:$B$34,$B47)*$X$14 -> 0 | N47: =SUM(C47:M47) -> 27238.716
